Workbook
Name Die_Type: Data!$E$2:$E$11
Name Password: Data!$G$1
Name Supplier: Table3[Supplier Name]

Sheet Summary
A3: Plant | B3: STATUS | C3: Supplier | D3: DIE NO | E3: Count of Order No | J3: GEX-1 Dies Budgeted Vs Actual -2025
A4: GEX 1 | B4: AWAITING FOR DESIGN | E4: 5 | J4: Type | K4: JAN | L4: FEB | M4: MAR | N4: APR | O4: MAY | P4: JUN | Q4: JUL | R4: AUG | S4: SEP | T4: OCT | U4: NOV | V4: DEC | W4: YTD | X4: Deviation YTD
B5: PENDING FOR DESIGN APPROVAL | E5: 7 | J5: BACK UP DIES | K5: 48.095349 | L5: 50.67953 | M5: 50.612308 | N5: 45.923212 | O5: 49.518926 | P5: 49.136309 | Q5: 50.927211 | R5: 46.089044 | S5: 50.552392 | T5: 49.390328 | U5: 50.108052 | V5: 48.168525 | W5: =SUM(K5:Q5) -> 344.89285 | X5: =W5-W6 -> -59.107154
B6: PENDING FOR ORDERING | E6: 9 | J6: ACTUAL | K6: =COUNTIFS(tbl_die_ordering[Plant],"GEX 1",tbl_die_ordering[month],Summary!K4,tbl_die_ordering[TYPE],"B") -> 60 | L6: =COUNTIFS(tbl_die_ordering[Plant],"GEX 1",tbl_die_ordering[month],Summary!L4,tbl_die_ordering[TYPE],"B") -> 66 | M6: =COUNTIFS(tbl_die_ordering[Plant],"GEX 1",tbl_die_ordering[month],Summary!M4,tbl_die_ordering[TYPE],"B") -> 47 | N6: =COUNTIFS(tbl_die_ordering[Plant],"GEX 1",tbl_die_ordering[month],Summary!N4,tbl_die_ordering[TYPE],"B") -> 54 | O6: =COUNTIFS(tbl_die_ordering[Plant],"GEX 1",tbl_die_ordering[month],Summary!O4,tbl_die_ordering[TYPE],"B") -> 52 | P6: =COUNTIFS(tbl_die_ordering[Plant],"GEX 1",tbl_die_ordering[month],Summary!P4,tbl_die_ordering[TYPE],"B") -> 49 | Q6: =COUNTIFS(tbl_die_ordering[Plant],"GEX 1",tbl_die_ordering[month],Summary!Q4,tbl_die_ordering[TYPE],"B") -> 76 | R6: =COUNTIFS(tbl_die_ordering[Plant],"GEX 1",tbl_die_ordering[month],Summary!R4,tbl_die_ordering[TYPE],"B") -> 60 | ... V6: =COUNTIFS(tbl_die_ordering[Plant],"GEX 1",tbl_die_ordering[month],Summary!V4,tbl_die_ordering[TYPE],"B") -> 19 | W6: =SUM(K6:Q6) -> 404
B7: UNDER SIMULATION | E7: 13 | J7: NEW DIES | K7: 33.304248 | L7: 35.093698 | M7: 35.047149 | N7: 31.800124 | O7: 34.290022 | P7: 34.025074 | Q7: 35.265208 | R7: 35.265208 | S7: 35.005659 | T7: 34.200973 | U7: 34.69797 | V7: 33.354919 | W7: =SUM(K7:Q7) -> 238.82552 | X7: =W7-W8 -> -104.17448 | AA7: =Q6+Q8 -> 164
A8: GEX 2 | B8: HOLD | E8: 1 | J8: ACTUAL | K8: =COUNTIFS(tbl_die_ordering[Plant],"GEX 1",tbl_die_ordering[month],Summary!K4,tbl_die_ordering[TYPE],"N") -> 63 | L8: =COUNTIFS(tbl_die_ordering[Plant],"GEX 1",tbl_die_ordering[month],Summary!L4,tbl_die_ordering[TYPE],"N") -> 17 | M8: =COUNTIFS(tbl_die_ordering[Plant],"GEX 1",tbl_die_ordering[month],Summary!M4,tbl_die_ordering[TYPE],"N") -> 47 | N8: =COUNTIFS(tbl_die_ordering[Plant],"GEX 1",tbl_die_ordering[month],Summary!N4,tbl_die_ordering[TYPE],"N") -> 70 | O8: =COUNTIFS(tbl_die_ordering[Plant],"GEX 1",tbl_die_ordering[month],Summary!O4,tbl_die_ordering[TYPE],"N") -> 32 | P8: =COUNTIFS(tbl_die_ordering[Plant],"GEX 1",tbl_die_ordering[month],Summary!P4,tbl_die_ordering[TYPE],"N") -> 26 | Q8: =COUNTIFS(tbl_die_ordering[Plant],"GEX 1",tbl_die_ordering[month],Summary!Q4,tbl_die_ordering[TYPE],"N") -> 88 | R8: =COUNTIFS(tbl_die_ordering[Plant],"GEX 1",tbl_die_ordering[month],Summary!R4,tbl_die_ordering[TYPE],"N") -> 27 | S8: =COUNTIFS(tbl_die_ordering[Plant],"GEX 1",tbl_die_ordering[month],Summary!S4,tbl_die_ordering[TYPE],"N") -> 11 | T8: =COUNTIFS(tbl_die_ordering[Plant],"GEX 1",tbl_die_ordering[month],Summary!S4,tbl_die_ordering[TYPE],"N") -> 11 | U8: =COUNTIFS(tbl_die_ordering[Plant],"GEX 1",tbl_die_ordering[month],Summary!U4,tbl_die_ordering[TYPE],"N") -> 33 | V8: =COUNTIFS(tbl_die_ordering[Plant],"GEX 1",tbl_die_ordering[month],Summary!V4,tbl_die_ordering[TYPE],"N") -> 2 | W8: =SUM(K8:Q8) -> 343
B9: PENDING FOR DESIGN APPROVAL | E9: 3
B10: PENDING FOR ORACLE ENTRY | E10: 5 | J10: GEX-2 Dies Budgeted Vs Actual
B11: PENDING FOR ORDERING | E11: 9 | J11: Type | K11: JAN | L11: FEB | M11: MAR | N11: APR | O11: MAY | P11: JUN | Q11: JUL | R11: AUG | S11: SEP | T11: OCT | U11: NOV | V11: DEC | W11: YTD | X11: Deviation YTD
B12: UNDER SIMULATION | E12: 4 | J12: BACK UP DIES | K12: 25 | L12: 25 | M12: 25 | N12: 23 | O12: 24 | P12: 25 | Q12: 25 | R12: 23 | S12: 25 | T12: 23 | U12: 23 | V12: 24 | W12: =SUM(K12:V12) -> 290 | X12: =W12-W13 -> -31
A13: Grand Total | E13: 56 | J13: ACTUAL | K13: =COUNTIFS(tbl_die_ordering[Plant],"GEX 2",tbl_die_ordering[month],Summary!K4,tbl_die_ordering[TYPE],"B") -> 25 | L13: =COUNTIFS(tbl_die_ordering[Plant],"GEX 2",tbl_die_ordering[month],Summary!L4,tbl_die_ordering[TYPE],"B") -> 23 | M13: =COUNTIFS(tbl_die_ordering[Plant],"GEX 2",tbl_die_ordering[month],Summary!M4,tbl_die_ordering[TYPE],"B") -> 28 | N13: =COUNTIFS(tbl_die_ordering[Plant],"GEX 2",tbl_die_ordering[month],Summary!N4,tbl_die_ordering[TYPE],"B") -> 23 | O13: =COUNTIFS(tbl_die_ordering[Plant],"GEX 2",tbl_die_ordering[month],Summary!O4,tbl_die_ordering[TYPE],"B") -> 23 | P13: =COUNTIFS(tbl_die_ordering[Plant],"GEX 2",tbl_die_ordering[month],Summary!P4,tbl_die_ordering[TYPE],"B") -> 25 | Q13: =COUNTIFS(tbl_die_ordering[Plant],"GEX 2",tbl_die_ordering[month],Summary!Q4,tbl_die_ordering[TYPE],"B") -> 27 | R13: =COUNTIFS(tbl_die_ordering[Plant],"GEX 2",tbl_die_ordering[month],Summary!R4,tbl_die_ordering[TYPE],"B") -> 29 | ... V13: =COUNTIFS(tbl_die_ordering[Plant],"GEX 2",tbl_die_ordering[month],Summary!V4,tbl_die_ordering[TYPE],"B") -> 10 | W13: =SUM(K13:V13) -> 321
J14: NEW DIES | K14: 12 | L14: 12 | M14: 12 | N14: 11 | O14: 11 | P14: 12 | Q14: 12 | R14: 11 | S14: 12 | T14: 11 | U14: 11 | V14: 12 | W14: =SUM(K14:V14) -> 139 | X14: =W14-W15 -> -2
J15: ACTUAL | K15: =COUNTIFS(tbl_die_ordering[Plant],"GEX 2",tbl_die_ordering[month],Summary!K4,tbl_die_ordering[TYPE],"N") -> 52 | L15: =COUNTIFS(tbl_die_ordering[Plant],"GEX 2",tbl_die_ordering[month],Summary!L4,tbl_die_ordering[TYPE],"N") -> 5 | M15: =COUNTIFS(tbl_die_ordering[Plant],"GEX 2",tbl_die_ordering[month],Summary!M4,tbl_die_ordering[TYPE],"N") -> 7 | N15: =COUNTIFS(tbl_die_ordering[Plant],"GEX 2",tbl_die_ordering[month],Summary!N4,tbl_die_ordering[TYPE],"N") -> 10 | O15: =COUNTIFS(tbl_die_ordering[Plant],"GEX 2",tbl_die_ordering[month],Summary!O4,tbl_die_ordering[TYPE],"N") -> 5 | P15: =COUNTIFS(tbl_die_ordering[Plant],"GEX 2",tbl_die_ordering[month],Summary!P4,tbl_die_ordering[TYPE],"N") -> 6 | Q15: =COUNTIFS(tbl_die_ordering[Plant],"GEX 2",tbl_die_ordering[month],Summary!Q4,tbl_die_ordering[TYPE],"N") -> 22 | R15: =COUNTIFS(tbl_die_ordering[Plant],"GEX 2",tbl_die_ordering[month],Summary!R4,tbl_die_ordering[TYPE],"N") -> 8 | ... V15: =COUNTIFS(tbl_die_ordering[Plant],"GEX 2",tbl_die_ordering[month],Summary!V4,tbl_die_ordering[TYPE],"N") -> 5 | W15: =SUM(K15:V15) -> 141
J18: Type | K18: JAN | L18: FEB | M18: MAR | N18: APR | O18: MAY | P18: JUN | Q18: JUL | R18: AUG | S18: SEP | T18: OCT | U18: NOV | V18: DEC | W18: YTD
J19: BACK UP DIES | K19: =K5+K12 -> 73.095349 | L19: =L5+L12 -> 75.67953 | M19: =M5+M12 -> 75.612308 | N19: =N5+N12 -> 68.923212 | O19: =O5+O12 -> 73.518926 | P19: =P5+P12 -> 74.136309 | Q19: =Q5+Q12 -> 75.927211 | R19: =R5+R12 -> 69.089044 | ... V19: =V5+V12 -> 72.168525 | W19: =SUM(K19:V19) -> 879.20119
J20: ACTUAL | K20: =K6+K13 -> 85 | L20: =L6+L13 -> 89 | M20: =M6+M13 -> 75 | N20: =N6+N13 -> 77 | O20: =O6+O13 -> 75 | P20: =P6+P13 -> 74 | Q20: =Q6+Q13 -> 103 | R20: =R6+R13 -> 89 | ... V20: =V6+V13 -> 29 | W20: =SUM(K20:V20) -> 1017 | AA20: =Q20+Q22 -> 213
J21: NEW DIES | K21: =K7+K14 -> 45.304248 | L21: =L7+L14 -> 47.093698 | M21: =M7+M14 -> 47.047149 | N21: =N7+N14 -> 42.800124 | O21: =O7+O14 -> 45.290022 | P21: =P7+P14 -> 46.025074 | Q21: =Q7+Q14 -> 47.265208 | R21: =R7+R14 -> 46.265208 | ... V21: =V7+V14 -> 45.354919 | W21: =SUM(K21:V21) -> 550.35025
J22: ACTUAL | K22: =K8+K15 -> 115 | L22: =L8+L15 -> 22 | M22: =M8+M15 -> 54 | N22: =N8+N15 -> 80 | O22: =O8+O15 -> 37 | P22: =P8+P15 -> 32 | Q22: =Q8+Q15 -> 110 | R22: =R8+R15 -> 35 | ... V22: =V8+V15 -> 7 | W22: =SUM(K22:V22) -> 568
A27: Status | B27: Die no | C27: Quality Issue
A28: Hold
A29: OPEN | B29: 014861-3502 | C29: Mandrel deflection and Rib crack
A30: OPEN | B30: 28117-426 | C30: not good shape flow defect. Requested for full set foc die
A31: OPEN | B31: 29826-203 | C31: unbalance flow. Foc Die (full set) requested
A32: OPEN | B32: 30143-401 | C32: Profile shape and dimension not ok. Quality desicrepancy raised for FOC Die Set. Foc die received on 12/04/2025. again QD is reopen due to Diesize Issue. QD sent again on 19/05/2025.
A33: OPEN | B33: 90324-409 | C33: even after 3 trials, shape is not able to achieve, involving supplier for correction
A34: OPEN | B34: Ins-23396 | C34: The QD was sent to Gulfex Purchase on 19/05/2025. Upon inspection, no lifting hole was found on the insert. Therefore, we sent it to a local supplier to have the lifting hole made. The cost for this modification is to be borne by the supplier, Ekstek.
A35: Rejected | B35: 29826-204 | C35: mandrel deflected Foc Mandrel Requested
A36: Grand Total

Sheet Sheet1
A1: Months (Die Requested Date) | B1: Oct
A2: Days (Die Requested Date) | B2: (All)
A3: Die Requested Date | B3: (All)
A5: Row Labels | B5: Count of Die Size
A6: Al saho | B6: 3
A7: Continual Facade | B7: 1
A8: Emirates Global | B8: 1
A9: Hueck | B9: 1
A10: Redcom Contruction | B10: 1
A11: Schuco | B11: 1
A12: Sobha construction | B12: 4
A13: Grand Total | B13: 12

Sheet Sheet3
A1: Plant | B1: Order No | C1: DIE NO | D1: TYPE | E1: Die Size | F1: Die Requested Date | G1: Ordered date | H1: Type of shipment | I1: Mandrels per Cavity | J1: Total Mandrels | K1: Design Received Date | L1: Design Approved Date | M1: Sim | N1: Delay | O1: PR Entry | P1: Oracle Entry | Q1: PR Forwarded date | R1: PR No.: | S1: Supplier | T1: Design saved to EMS FOLDER | U1: Customer of new profile | V1: Remarks | W1: STATUS
A2: GEX 1 | C2: 30392-602 | D2: B | E2: 450X250 | F2: 45971 | H2: AIR | I2: 7 | J2: 7 | S2: WEFA | W2: PENDING FOR ORDERING
A3: GEX 2 | C3: 005279-3507 | D3: B | E3: 355X200 | F3: 45979 | H3: LAND | I3: 1 | J3: 3 | S3: PHME | W3: PENDING FOR ORDERING
A4: GEX 2 | C4: 027911-3501 | D4: B | E4: 450X260 | F4: 45979 | H4: LAND | I4: 0 | J4: 0 | K4: 45981 | L4: 45982 | O4: 45983 | Q4: 45983 | R4: 212501595 | S4: PHME | T4: 45983 | W4: PENDING FOR ORDERING
A5: GEX 1 | C5: 07098-607 | D5: B | E5: 320X160 | F5: 45979 | H5: LAND | I5: 0 | J5: 0 | K5: 45981 | S5: PDTMC | W5: PENDING FOR ORDERING
A6: GEX 1 | C6: 11069-408 | D6: B | E6: 280X160 | F6: 45979 | H6: LAND | I6: 0 | J6: 0 | K6: 45982 | L6: 45982 | O6: 45983 | P6: 45979 | Q6: 45983 | R6: 112505137 | S6: PDTMC | T6: 45983 | W6: PENDING FOR ORDERING
A7: GEX 1 | C7: 28546-601 | D7: B | E7: 320X160 | F7: 45979 | H7: AIR | I7: 1 | J7: 1 | K7: 45982 | S7: JIANGSU | V7: Not for anodizing order | W7: PENDING FOR ORDERING
A8: GEX 1 | C8: 30379-501 | D8: B | E8: 280X160 | F8: 45979 | H8: AIR | I8: 7 | J8: 7 | S8: WEFA | W8: PENDING FOR ORDERING
A9: GEX 1 | C9: 07098-608 | D9: B | E9: 320X160 | F9: 45980 | H9: LAND | I9: 0 | J9: 0 | K9: 45981 | L9: 45982 | O9: 45983 | Q9: 45983 | R9: 112505137 | S9: PHME | T9: 45983 | W9: PENDING FOR ORDERING
A10: GEX 2 | C10: 007108-2503 | D10: B | E10: 220X130 | F10: 45980 | H10: LAND | I10: 0 | J10: 0 | S10: PDTMC | W10: PENDING FOR ORDERING
A11: GEX 1 | C11: 11388-218 | D11: B | E11: 280X160 | F11: 45980 | H11: AIR | I11: 0 | J11: 0 | S11: JIANGSU | W11: PENDING FOR ORDERING
A12: GEX 1 | C12: 12098-215 | D12: B | E12: 280X160 | F12: 45980 | H12: LAND | I12: 1 | J12: 2 | K12: 45982 | S12: PHME | W12: PENDING FOR ORDERING
A13: GEX 2 | C13: 012144-3501 | D13: B | E13: 320X200 | F13: 45980 | H13: LAND | I13: 1 | J13: 2 | K13: 45985 | S13: PDTMC | W13: PENDING FOR ORDERING
A14: GEX 1 | C14: 12725-503 | D14: B | E14: 280X160 | F14: 45980 | H14: LAND | I14: 1 | J14: 2 | S14: PHME | W14: PENDING FOR ORDERING
A15: GEX 2 | C15: 013794-3511 | D15: B | E15: 355X200 | F15: 45980 | H15: AIR | I15: 1 | J15: 2 | S15: JIANGSU | W15: PENDING FOR ORDERING
A16: GEX 1 | C16: 23555-404 | D16: B | E16: 250X160 | F16: 45980 | H16: AIR | I16: 0 | J16: 0 | S16: JIANGSU | W16: PENDING FOR ORDERING
A17: GEX 1 | C17: 27349-502 | D17: B | E17: 250X160 | F17: 45980 | H17: LAND | I17: 0 | J17: 0 | K17: 45981 | L17: 45982 | O17: 45983 | Q17: 45983 | R17: 112505137 | S17: PHME | T17: 45983 | W17: PENDING FOR ORDERING
A18: GEX 2 | C18: 029117-3502 | D18: B | E18: 400X260 | F18: 45980 | H18: LAND | I18: 1 | J18: 3 | K18: 45982 | L18: 45982 | O18: 45983 | Q18: 45983 | R18: 212501595 | S18: PHME | T18: 45983 | W18: PENDING FOR ORDERING
A19: GEX 2 | C19: 029118-2513 | D19: B | E19: 320X160 | F19: 45980 | H19: LAND | I19: 1 | J19: 2 | K19: 45982 | L19: 45982 | O19: 45983 | Q19: 45983 | R19: 212501595 | S19: PHME | T19: 45983 | W19: PENDING FOR ORDERING
A20: GEX 2 | C20: 029118-2501 | D20: B | E20: 320X160 | F20: 45980 | H20: LAND | I20: 1 | J20: 2 | K20: 45982 | L20: 45982 | O20: 45983 | Q20: 45983 | R20: 212501595 | S20: PHME | T20: 45983 | W20: PENDING FOR ORDERING
A21: GEX 2 | C21: 029663-3502 | D21: B | E21: 355X200 | F21: 45980 | H21: LAND | I21: 1 | J21: 2 | S21: PDTMC | W21: PENDING FOR ORDERING
A22: GEX 1 | C22: 29663-211 | D22: B | E22: 355X200 | F22: 45980 | H22: LAND | I22: 1 | J22: 2 | K22: 45983 | S22: PDTMC | W22: PENDING FOR ORDERING
A23: GEX 1 | C23: 30477-602 | D23: B | E23: 550X250 | F23: 45980 | H23: AIR | I23: 5 | J23: 5 | S23: ALMAX | W23: PENDING FOR ORDERING
A24: GEX 2 | C24: 051111-3507 | D24: B | E24: 450X260 | F24: 45980 | H24: LAND | I24: 3 | J24: 3 | K24: 45982 | L24: 45982 | O24: 45983 | Q24: 45983 | R24: 212501595 | S24: PHME | T24: 45983 | W24: PENDING FOR ORDERING
A25: GEX 2 | C25: 120627-2504 | D25: B | E25: 250X140 | F25: 45980 | H25: LAND | I25: 1 | J25: 2 | K25: 45982 | L25: 45982 | O25: 45983 | Q25: 45983 | R25: 212501595 | S25: PHME | T25: 45983 | W25: PENDING FOR ORDERING
A26: GEX 2 | C26: 120507-2503 | D26: B | E26: 280X165 | F26: 45980 | H26: AIR | I26: 3 | J26: 3 | S26: ALMAX | W26: PENDING FOR ORDERING
A27: GEX 1 | C27: 05188-510 | D27: B | E27: 280X160 | F27: 45983 | H27: LAND | I27: 1 | J27: 2 | S27: PDTMC | W27: PENDING FOR ORDERING
A28: GEX 2 | C28: 010745-2501 | D28: B | E28: 280X160 | F28: 45983 | H28: LAND | I28: 0 | J28: 0 | S28: PDTMC | W28: PENDING FOR ORDERING
A29: GEX 1 | C29: 13212-236 | D29: B | E29: 280X160 | F29: 45983 | H29: AIR | I29: 1 | J29: 2 | S29: EKSTEK | W29: PENDING FOR ORDERING
A30: GEX 1 | C30: 13212-409 | D30: B | E30: 220X160 | F30: 45983 | H30: LAND | I30: 1 | J30: 1 | S30: PDTMC | W30: PENDING FOR ORDERING
A31: GEX 1 | C31: 29596-502 | D31: B | E31: 250X160 | F31: 45983 | H31: LAND | I31: 1 | J31: 2 | S31: PDTMC | W31: PENDING FOR ORDERING
A32: GEX 1 | C32: 29897-201 | D32: B | E32: 355X200 | F32: 45983 | H32: LAND | I32: 1 | J32: 2 | S32: PHME | W32: PENDING FOR ORDERING
A33: GEX 1 | C33: 29897-507 | D33: B | E33: 280X160 | F33: 45983 | H33: LAND | I33: 1 | J33: 1 | S33: PDTMC | W33: PENDING FOR ORDERING
A34: GEX 1 | C34: 120661-607 | D34: B | E34: 450X250 | F34: 45983 | H34: LAND | I34: 3 | J34: 3 | S34: PHME | W34: PENDING FOR ORDERING
A35: GEX 1 | C35: 297285-502 | D35: B | E35: 280X160 | F35: 45985 | H35: LAND | I35: 1 | J35: 1 | S35: PHME | W35: PENDING FOR ORDERING
A36: GEX 1 | C36: 29826-501 | D36: B | E36: 320X160 | F36: 45985 | H36: LAND | I36: 4 | J36: 4 | S36: PDTMC | W36: PENDING FOR ORDERING

Sheet Die Ordering
A2: Plant | B2: Order No | C2: DIE NO | D2: TYPE | E2: Die Size | F2: Die Requested Date | G2: Ordered date | H2: Type of shipment | I2: Mandrels per Cavity | J2: Total Mandrels | K2: Design Received Date | L2: Design Approved Date | M2: Sim | N2: Delay | O2: PR Entry | P2: Oracle Entry | Q2: PR Forwarded date | R2: PR No.: | S2: Supplier | T2: Design saved to EMS FOLDER | U2: Customer of new profile | V2: Remarks | W2: STATUS | X2: OVERALL DELAY | Y2: Design Enhancement | Z2: QD Status | AA2: Finish | AB2: PO | AC2: ETA | AD2: Die received | AE2: Design enhancements | AF2: month | AG2: clm_spoort | AH2: Die size changes | AI2: design changes | AJ2: Column1
A3: GEX 1 | B3: =_xlfn.XLOOKUP(_xlfn.TEXTJOIN("_",TRUE,tbl_die_ordering[[#This Row],[Supplier]],tbl_die_ordering[[#This Row],[DIE NO]]),[1]Tracker!$AQ:$AQ,[1]Tracker!$W:$W,"") -> 7613-25 | C3: INS-25033 | D3: T | E3: 300X100 | F3: 45660 | G3: =_xlfn.XLOOKUP(_xlfn.TEXTJOIN("_",TRUE,tbl_die_ordering[[#This Row],[Supplier]],tbl_die_ordering[[#This Row],[DIE NO]]),[1]Tracker!$AQ:$AQ,[1]Tracker!$V:$V,"") -> 45660 | H3: LAND | I3: 0 | J3: 0 | K3: 45660 | L3: 45660 | N3: =IFERROR(IF(tbl_die_ordering[[#This Row],[Design Approved Date]]<>"",L3-K3,""),"") -> 0 | O3: 45661 | P3: 45661 | Q3: 45661 | R3: 112500030 | S3: PDTMC | T3: 45661 | W3: =_xlfn.LET( _xlpm.dieNo, tbl_die_ordering[[#This Row],[DIE NO]], _xlpm.orderNo, tbl_die_ordering[[#This Row],[Order No]], _xlpm.type, tbl_die_ordering[[#This Row],[TYPE]], _xlpm.designReceived, tbl_die_ordering[[#This Row],[Design Received Date]], _xlpm.designApproved, tbl_die_ordering[[#This Row],[Design Approved Date]], _xlpm.sim, tbl_die_ordering[[#This Row],[Sim]], _xlpm.prEntry, tbl_die_ordering[[#This Row],[PR Entry]], _xlpm.oracleEntry, tbl_die_ordering[[#This Row],[Oracle Entry]], _xlpm.ems, tbl_die_ordering[[#This Row],[Design saved to EMS FOLDER]], IF(_xlpm.dieNo = "", "", IF(_xlpm.orderNo = "", "PENDING FOR ORDERING", IF(_xlpm.type = "C", "CANCELLED", IF(_xlpm.type = "H", "HOLD", IF(_xlpm.designReceived = "", "AWAITING FOR DESIGN", IF(_xlpm.designApproved = "", IF(_xlpm.sim = "YES", "UNDER SIMULATION", "PENDING FOR DESIGN APPROVAL"), IF(_xlpm.prEntry = "", "PENDING FOR PR", IF(_xlpm.oracleEntry = "", "PENDING FOR ORACLE ENTRY", IF(_xlpm.ems = "", "PENDING FOR DESIGN TO EMS", "DONE"))))))))) ) -> DONE | X3: =IF(AND(tbl_die_ordering[[#This Row],[TYPE]]<>"C",tbl_die_ordering[[#This Row],[Design Approved Date]]<>""),tbl_die_ordering[[#This Row],[Design Approved Date]]-tbl_die_ordering[[#This Row],[Die Requested Date]],0) -> 0 | AB3: =_xlfn.XLOOKUP(_xlfn.TEXTJOIN("_",TRUE,tbl_die_ordering[[#This Row],[Supplier]],tbl_die_ordering[[#This Row],[DIE NO]]),[1]Tracker!$AQ:$AQ,[1]Tracker!$Y:$Y,"") -> 142500270 | AC3: =_xlfn.XLOOKUP(_xlfn.TEXTJOIN("_",TRUE,tbl_die_ordering[[#This Row],[Supplier]],tbl_die_ordering[[#This Row],[DIE NO]]),[1]Tracker!$AQ:$AQ,[1]Tracker!$AC:$AC,"") -> 45669 | AF3: =TEXT(tbl_die_ordering[[#This Row],[Die Requested Date]],"mmm") -> Jan | AG3: =_xlfn.TEXTJOIN("_",TRUE,tbl_die_ordering[[#This Row],[Supplier]],tbl_die_ordering[[#This Row],[DIE NO]]) -> PDTMC_INS-25033
A4: GEX 1 | B4: =_xlfn.XLOOKUP(_xlfn.TEXTJOIN("_",TRUE,tbl_die_ordering[[#This Row],[Supplier]],tbl_die_ordering[[#This Row],[DIE NO]]),[1]Tracker!$AQ:$AQ,[1]Tracker!$W:$W,"") -> 7610-25 | C4: 01001-402 | D4: B | E4: 250X160 | F4: 45660 | G4: =_xlfn.XLOOKUP(_xlfn.TEXTJOIN("_",TRUE,tbl_die_ordering[[#This Row],[Supplier]],tbl_die_ordering[[#This Row],[DIE NO]]),[1]Tracker!$AQ:$AQ,[1]Tracker!$V:$V,"") -> 45660 | H4: AIR | I4: 0 | J4: 0 | K4: 45660 | L4: 45661 | N4: =IFERROR(IF(tbl_die_ordering[[#This Row],[Design Approved Date]]<>"",L4-K4,""),"") -> 1 | O4: 45665 | P4: 45666 | Q4: 45665 | R4: 112500093 | S4: EKSTEK | T4: 45665 | W4: =_xlfn.LET( _xlpm.dieNo, tbl_die_ordering[[#This Row],[DIE NO]], _xlpm.orderNo, tbl_die_ordering[[#This Row],[Order No]], _xlpm.type, tbl_die_ordering[[#This Row],[TYPE]], _xlpm.designReceived, tbl_die_ordering[[#This Row],[Design Received Date]], _xlpm.designApproved, tbl_die_ordering[[#This Row],[Design Approved Date]], _xlpm.sim, tbl_die_ordering[[#This Row],[Sim]], _xlpm.prEntry, tbl_die_ordering[[#This Row],[PR Entry]], _xlpm.oracleEntry, tbl_die_ordering[[#This Row],[Oracle Entry]], _xlpm.ems, tbl_die_ordering[[#This Row],[Design saved to EMS FOLDER]], IF(_xlpm.dieNo = "", "", IF(_xlpm.orderNo = "", "PENDING FOR ORDERING", IF(_xlpm.type = "C", "CANCELLED", IF(_xlpm.type = "H", "HOLD", IF(_xlpm.designReceived = "", "AWAITING FOR DESIGN", IF(_xlpm.designApproved = "", IF(_xlpm.sim = "YES", "UNDER SIMULATION", "PENDING FOR DESIGN APPROVAL"), IF(_xlpm.prEntry = "", "PENDING FOR PR", IF(_xlpm.oracleEntry = "", "PENDING FOR ORACLE ENTRY", IF(_xlpm.ems = "", "PENDING FOR DESIGN TO EMS", "DONE"))))))))) ) -> DONE | X4: =IF(AND(tbl_die_ordering[[#This Row],[TYPE]]<>"C",tbl_die_ordering[[#This Row],[Design Approved Date]]<>""),tbl_die_ordering[[#This Row],[Design Approved Date]]-tbl_die_ordering[[#This Row],[Die Requested Date]],0) -> 1 | AB4: =_xlfn.XLOOKUP(_xlfn.TEXTJOIN("_",TRUE,tbl_die_ordering[[#This Row],[Supplier]],tbl_die_ordering[[#This Row],[DIE NO]]),[1]Tracker!$AQ:$AQ,[1]Tracker!$Y:$Y,"") -> 142500488 | AC4: =_xlfn.XLOOKUP(_xlfn.TEXTJOIN("_",TRUE,tbl_die_ordering[[#This Row],[Supplier]],tbl_die_ordering[[#This Row],[DIE NO]]),[1]Tracker!$AQ:$AQ,[1]Tracker!$AC:$AC,"") -> 45681 | AF4: =TEXT(tbl_die_ordering[[#This Row],[Die Requested Date]],"mmm") -> Jan | AG4: =_xlfn.TEXTJOIN("_",TRUE,tbl_die_ordering[[#This Row],[Supplier]],tbl_die_ordering[[#This Row],[DIE NO]]) -> EKSTEK_01001-402
A5: GEX 1 | B5: =_xlfn.XLOOKUP(_xlfn.TEXTJOIN("_",TRUE,tbl_die_ordering[[#This Row],[Supplier]],tbl_die_ordering[[#This Row],[DIE NO]]),[1]Tracker!$AQ:$AQ,[1]Tracker!$W:$W,"") -> 7610-25 | C5: 14940-509 | D5: B | E5: 320X160 | F5: 45660 | G5: =_xlfn.XLOOKUP(_xlfn.TEXTJOIN("_",TRUE,tbl_die_ordering[[#This Row],[Supplier]],tbl_die_ordering[[#This Row],[DIE NO]]),[1]Tracker!$AQ:$AQ,[1]Tracker!$V:$V,"") -> 45660 | H5: AIR | I5: 1 | J5: 1 | K5: 45660 | L5: 45661 | N5: =IFERROR(IF(tbl_die_ordering[[#This Row],[Design Approved Date]]<>"",L5-K5,""),"") -> 1 | O5: 45665 | P5: 45666 | Q5: 45665 | R5: 112500093 | S5: EKSTEK | T5: 45665 | W5: =_xlfn.LET( _xlpm.dieNo, tbl_die_ordering[[#This Row],[DIE NO]], _xlpm.orderNo, tbl_die_ordering[[#This Row],[Order No]], _xlpm.type, tbl_die_ordering[[#This Row],[TYPE]], _xlpm.designReceived, tbl_die_ordering[[#This Row],[Design Received Date]], _xlpm.designApproved, tbl_die_ordering[[#This Row],[Design Approved Date]], _xlpm.sim, tbl_die_ordering[[#This Row],[Sim]], _xlpm.prEntry, tbl_die_ordering[[#This Row],[PR Entry]], _xlpm.oracleEntry, tbl_die_ordering[[#This Row],[Oracle Entry]], _xlpm.ems, tbl_die_ordering[[#This Row],[Design saved to EMS FOLDER]], IF(_xlpm.dieNo = "", "", IF(_xlpm.orderNo = "", "PENDING FOR ORDERING", IF(_xlpm.type = "C", "CANCELLED", IF(_xlpm.type = "H", "HOLD", IF(_xlpm.designReceived = "", "AWAITING FOR DESIGN", IF(_xlpm.designApproved = "", IF(_xlpm.sim = "YES", "UNDER SIMULATION", "PENDING FOR DESIGN APPROVAL"), IF(_xlpm.prEntry = "", "PENDING FOR PR", IF(_xlpm.oracleEntry = "", "PENDING FOR ORACLE ENTRY", IF(_xlpm.ems = "", "PENDING FOR DESIGN TO EMS", "DONE"))))))))) ) -> DONE | X5: =IF(AND(tbl_die_ordering[[#This Row],[TYPE]]<>"C",tbl_die_ordering[[#This Row],[Design Approved Date]]<>""),tbl_die_ordering[[#This Row],[Design Approved Date]]-tbl_die_ordering[[#This Row],[Die Requested Date]],0) -> 1 | AB5: =_xlfn.XLOOKUP(_xlfn.TEXTJOIN("_",TRUE,tbl_die_ordering[[#This Row],[Supplier]],tbl_die_ordering[[#This Row],[DIE NO]]),[1]Tracker!$AQ:$AQ,[1]Tracker!$Y:$Y,"") -> 142500488 | AC5: =_xlfn.XLOOKUP(_xlfn.TEXTJOIN("_",TRUE,tbl_die_ordering[[#This Row],[Supplier]],tbl_die_ordering[[#This Row],[DIE NO]]),[1]Tracker!$AQ:$AQ,[1]Tracker!$AC:$AC,"") -> 45681 | AF5: =TEXT(tbl_die_ordering[[#This Row],[Die Requested Date]],"mmm") -> Jan | AG5: =_xlfn.TEXTJOIN("_",TRUE,tbl_die_ordering[[#This Row],[Supplier]],tbl_die_ordering[[#This Row],[DIE NO]]) -> EKSTEK_14940-509
A6: GEX 1 | B6: =_xlfn.XLOOKUP(_xlfn.TEXTJOIN("_",TRUE,tbl_die_ordering[[#This Row],[Supplier]],tbl_die_ordering[[#This Row],[DIE NO]]),[1]Tracker!$AQ:$AQ,[1]Tracker!$W:$W,"") -> 7612-25 | C6: 27562-502 | D6: B | E6: 320X160 | F6: 45660 | G6: =_xlfn.XLOOKUP(_xlfn.TEXTJOIN("_",TRUE,tbl_die_ordering[[#This Row],[Supplier]],tbl_die_ordering[[#This Row],[DIE NO]]),[1]Tracker!$AQ:$AQ,[1]Tracker!$V:$V,"") -> 45660 | H6: AIR | I6: 0 | J6: 0 | K6: 45660 | L6: 45661 | N6: =IFERROR(IF(tbl_die_ordering[[#This Row],[Design Approved Date]]<>"",L6-K6,""),"") -> 1 | O6: 45665 | P6: 45666 | Q6: 45665 | R6: 112500093 | S6: PHOENIX | T6: 45665 | W6: =_xlfn.LET( _xlpm.dieNo, tbl_die_ordering[[#This Row],[DIE NO]], _xlpm.orderNo, tbl_die_ordering[[#This Row],[Order No]], _xlpm.type, tbl_die_ordering[[#This Row],[TYPE]], _xlpm.designReceived, tbl_die_ordering[[#This Row],[Design Received Date]], _xlpm.designApproved, tbl_die_ordering[[#This Row],[Design Approved Date]], _xlpm.sim, tbl_die_ordering[[#This Row],[Sim]], _xlpm.prEntry, tbl_die_ordering[[#This Row],[PR Entry]], _xlpm.oracleEntry, tbl_die_ordering[[#This Row],[Oracle Entry]], _xlpm.ems, tbl_die_ordering[[#This Row],[Design saved to EMS FOLDER]], IF(_xlpm.dieNo = "", "", IF(_xlpm.orderNo = "", "PENDING FOR ORDERING", IF(_xlpm.type = "C", "CANCELLED", IF(_xlpm.type = "H", "HOLD", IF(_xlpm.designReceived = "", "AWAITING FOR DESIGN", IF(_xlpm.designApproved = "", IF(_xlpm.sim = "YES", "UNDER SIMULATION", "PENDING FOR DESIGN APPROVAL"), IF(_xlpm.prEntry = "", "PENDING FOR PR", IF(_xlpm.oracleEntry = "", "PENDING FOR ORACLE ENTRY", IF(_xlpm.ems = "", "PENDING FOR DESIGN TO EMS", "DONE"))))))))) ) -> DONE | X6: =IF(AND(tbl_die_ordering[[#This Row],[TYPE]]<>"C",tbl_die_ordering[[#This Row],[Design Approved Date]]<>""),tbl_die_ordering[[#This Row],[Design Approved Date]]-tbl_die_ordering[[#This Row],[Die Requested Date]],0) -> 1 | AB6: =_xlfn.XLOOKUP(_xlfn.TEXTJOIN("_",TRUE,tbl_die_ordering[[#This Row],[Supplier]],tbl_die_ordering[[#This Row],[DIE NO]]),[1]Tracker!$AQ:$AQ,[1]Tracker!$Y:$Y,"") -> 142500502 | AC6: =_xlfn.XLOOKUP(_xlfn.TEXTJOIN("_",TRUE,tbl_die_ordering[[#This Row],[Supplier]],tbl_die_ordering[[#This Row],[DIE NO]]),[1]Tracker!$AQ:$AQ,[1]Tracker!$AC:$AC,"") -> 45684 | AF6: =TEXT(tbl_die_ordering[[#This Row],[Die Requested Date]],"mmm") -> Jan | AG6: =_xlfn.TEXTJOIN("_",TRUE,tbl_die_ordering[[#This Row],[Supplier]],tbl_die_ordering[[#This Row],[DIE NO]]) -> PHOENIX _27562-502
A7: GEX 1 | B7: =_xlfn.XLOOKUP(_xlfn.TEXTJOIN("_",TRUE,tbl_die_ordering[[#This Row],[Supplier]],tbl_die_ordering[[#This Row],[DIE NO]]),[1]Tracker!$AQ:$AQ,[1]Tracker!$W:$W,"") -> 7612-25 | C7: 27660-202 | D7: B | E7: 355X200 | F7: 45660 | G7: =_xlfn.XLOOKUP(_xlfn.TEXTJOIN("_",TRUE,tbl_die_ordering[[#This Row],[Supplier]],tbl_die_ordering[[#This Row],[DIE NO]]),[1]Tracker!$AQ:$AQ,[1]Tracker!$V:$V,"") -> 45660 | H7: AIR | I7: 0 | J7: 0 | K7: 45660 | L7: 45661 | N7: =IFERROR(IF(tbl_die_ordering[[#This Row],[Design Approved Date]]<>"",L7-K7,""),"") -> 1 | O7: 45665 | P7: 45666 | Q7: 45665 | R7: 112500093 | S7: PHOENIX | T7: 45665 | W7: =_xlfn.LET( _xlpm.dieNo, tbl_die_ordering[[#This Row],[DIE NO]], _xlpm.orderNo, tbl_die_ordering[[#This Row],[Order No]], _xlpm.type, tbl_die_ordering[[#This Row],[TYPE]], _xlpm.designReceived, tbl_die_ordering[[#This Row],[Design Received Date]], _xlpm.designApproved, tbl_die_ordering[[#This Row],[Design Approved Date]], _xlpm.sim, tbl_die_ordering[[#This Row],[Sim]], _xlpm.prEntry, tbl_die_ordering[[#This Row],[PR Entry]], _xlpm.oracleEntry, tbl_die_ordering[[#This Row],[Oracle Entry]], _xlpm.ems, tbl_die_ordering[[#This Row],[Design saved to EMS FOLDER]], IF(_xlpm.dieNo = "", "", IF(_xlpm.orderNo = "", "PENDING FOR ORDERING", IF(_xlpm.type = "C", "CANCELLED", IF(_xlpm.type = "H", "HOLD", IF(_xlpm.designReceived = "", "AWAITING FOR DESIGN", IF(_xlpm.designApproved = "", IF(_xlpm.sim = "YES", "UNDER SIMULATION", "PENDING FOR DESIGN APPROVAL"), IF(_xlpm.prEntry = "", "PENDING FOR PR", IF(_xlpm.oracleEntry = "", "PENDING FOR ORACLE ENTRY", IF(_xlpm.ems = "", "PENDING FOR DESIGN TO EMS", "DONE"))))))))) ) -> DONE | X7: =IF(AND(tbl_die_ordering[[#This Row],[TYPE]]<>"C",tbl_die_ordering[[#This Row],[Design Approved Date]]<>""),tbl_die_ordering[[#This Row],[Design Approved Date]]-tbl_die_ordering[[#This Row],[Die Requested Date]],0) -> 1 | AB7: =_xlfn.XLOOKUP(_xlfn.TEXTJOIN("_",TRUE,tbl_die_ordering[[#This Row],[Supplier]],tbl_die_ordering[[#This Row],[DIE NO]]),[1]Tracker!$AQ:$AQ,[1]Tracker!$Y:$Y,"") -> 142500502 | AC7: =_xlfn.XLOOKUP(_xlfn.TEXTJOIN("_",TRUE,tbl_die_ordering[[#This Row],[Supplier]],tbl_die_ordering[[#This Row],[DIE NO]]),[1]Tracker!$AQ:$AQ,[1]Tracker!$AC:$AC,"") -> 45684 | AF7: =TEXT(tbl_die_ordering[[#This Row],[Die Requested Date]],"mmm") -> Jan | AG7: =_xlfn.TEXTJOIN("_",TRUE,tbl_die_ordering[[#This Row],[Supplier]],tbl_die_ordering[[#This Row],[DIE NO]]) -> PHOENIX _27660-202
A8: GEX 1 | B8: =_xlfn.XLOOKUP(_xlfn.TEXTJOIN("_",TRUE,tbl_die_ordering[[#This Row],[Supplier]],tbl_die_ordering[[#This Row],[DIE NO]]),[1]Tracker!$AQ:$AQ,[1]Tracker!$W:$W,"") -> 7613-25 | C8: BOL-6-2-B | D8: T | E8: 700X196 | F8: 45660 | G8: =_xlfn.XLOOKUP(_xlfn.TEXTJOIN("_",TRUE,tbl_die_ordering[[#This Row],[Supplier]],tbl_die_ordering[[#This Row],[DIE NO]]),[1]Tracker!$AQ:$AQ,[1]Tracker!$V:$V,"") -> 45660 | H8: LAND | I8: 0 | J8: 0 | K8: 45663 | L8: 45663 | N8: =IFERROR(IF(tbl_die_ordering[[#This Row],[Design Approved Date]]<>"",L8-K8,""),"") -> 0 | O8: 45665 | P8: 45665 | Q8: 45665 | R8: 112500093 | S8: PDTMC | T8: 45667 | W8: =_xlfn.LET( _xlpm.dieNo, tbl_die_ordering[[#This Row],[DIE NO]], _xlpm.orderNo, tbl_die_ordering[[#This Row],[Order No]], _xlpm.type, tbl_die_ordering[[#This Row],[TYPE]], _xlpm.designReceived, tbl_die_ordering[[#This Row],[Design Received Date]], _xlpm.designApproved, tbl_die_ordering[[#This Row],[Design Approved Date]], _xlpm.sim, tbl_die_ordering[[#This Row],[Sim]], _xlpm.prEntry, tbl_die_ordering[[#This Row],[PR Entry]], _xlpm.oracleEntry, tbl_die_ordering[[#This Row],[Oracle Entry]], _xlpm.ems, tbl_die_ordering[[#This Row],[Design saved to EMS FOLDER]], IF(_xlpm.dieNo = "", "", IF(_xlpm.orderNo = "", "PENDING FOR ORDERING", IF(_xlpm.type = "C", "CANCELLED", IF(_xlpm.type = "H", "HOLD", IF(_xlpm.designReceived = "", "AWAITING FOR DESIGN", IF(_xlpm.designApproved = "", IF(_xlpm.sim = "YES", "UNDER SIMULATION", "PENDING FOR DESIGN APPROVAL"), IF(_xlpm.prEntry = "", "PENDING FOR PR", IF(_xlpm.oracleEntry = "", "PENDING FOR ORACLE ENTRY", IF(_xlpm.ems = "", "PENDING FOR DESIGN TO EMS", "DONE"))))))))) ) -> DONE | X8: =IF(AND(tbl_die_ordering[[#This Row],[TYPE]]<>"C",tbl_die_ordering[[#This Row],[Design Approved Date]]<>""),tbl_die_ordering[[#This Row],[Design Approved Date]]-tbl_die_ordering[[#This Row],[Die Requested Date]],0) -> 3 | AB8: =_xlfn.XLOOKUP(_xlfn.TEXTJOIN("_",TRUE,tbl_die_ordering[[#This Row],[Supplier]],tbl_die_ordering[[#This Row],[DIE NO]]),[1]Tracker!$AQ:$AQ,[1]Tracker!$Y:$Y,"") -> 142500499 | AC8: =_xlfn.XLOOKUP(_xlfn.TEXTJOIN("_",TRUE,tbl_die_ordering[[#This Row],[Supplier]],tbl_die_ordering[[#This Row],[DIE NO]]),[1]Tracker!$AQ:$AQ,[1]Tracker!$AC:$AC,"") -> 45762 | AF8: =TEXT(tbl_die_ordering[[#This Row],[Die Requested Date]],"mmm") -> Jan | AG8: =_xlfn.TEXTJOIN("_",TRUE,tbl_die_ordering[[#This Row],[Supplier]],tbl_die_ordering[[#This Row],[DIE NO]]) -> PDTMC_BOL-6-2-B
A9: GEX 1 | B9: =_xlfn.XLOOKUP(_xlfn.TEXTJOIN("_",TRUE,tbl_die_ordering[[#This Row],[Supplier]],tbl_die_ordering[[#This Row],[DIE NO]]),[1]Tracker!$AQ:$AQ,[1]Tracker!$W:$W,"") -> 7611-25 | C9: 10485-501 | D9: B | E9: 220X130 | F9: 45660 | G9: =_xlfn.XLOOKUP(_xlfn.TEXTJOIN("_",TRUE,tbl_die_ordering[[#This Row],[Supplier]],tbl_die_ordering[[#This Row],[DIE NO]]),[1]Tracker!$AQ:$AQ,[1]Tracker!$V:$V,"") -> 45660 | H9: LAND | I9: 0 | J9: 0 | K9: 45665 | L9: 45666 | N9: =IFERROR(IF(tbl_die_ordering[[#This Row],[Design Approved Date]]<>"",L9-K9,""),"") -> 1 | O9: 45667 | P9: 45670 | Q9: 45667 | R9: 112500165 | S9: PDTMC | T9: 45667 | W9: =_xlfn.LET( _xlpm.dieNo, tbl_die_ordering[[#This Row],[DIE NO]], _xlpm.orderNo, tbl_die_ordering[[#This Row],[Order No]], _xlpm.type, tbl_die_ordering[[#This Row],[TYPE]], _xlpm.designReceived, tbl_die_ordering[[#This Row],[Design Received Date]], _xlpm.designApproved, tbl_die_ordering[[#This Row],[Design Approved Date]], _xlpm.sim, tbl_die_ordering[[#This Row],[Sim]], _xlpm.prEntry, tbl_die_ordering[[#This Row],[PR Entry]], _xlpm.oracleEntry, tbl_die_ordering[[#This Row],[Oracle Entry]], _xlpm.ems, tbl_die_ordering[[#This Row],[Design saved to EMS FOLDER]], IF(_xlpm.dieNo = "", "", IF(_xlpm.orderNo = "", "PENDING FOR ORDERING", IF(_xlpm.type = "C", "CANCELLED", IF(_xlpm.type = "H", "HOLD", IF(_xlpm.designReceived = "", "AWAITING FOR DESIGN", IF(_xlpm.designApproved = "", IF(_xlpm.sim = "YES", "UNDER SIMULATION", "PENDING FOR DESIGN APPROVAL"), IF(_xlpm.prEntry = "", "PENDING FOR PR", IF(_xlpm.oracleEntry = "", "PENDING FOR ORACLE ENTRY", IF(_xlpm.ems = "", "PENDING FOR DESIGN TO EMS", "DONE"))))))))) ) -> DONE | X9: =IF(AND(tbl_die_ordering[[#This Row],[TYPE]]<>"C",tbl_die_ordering[[#This Row],[Design Approved Date]]<>""),tbl_die_ordering[[#This Row],[Design Approved Date]]-tbl_die_ordering[[#This Row],[Die Requested Date]],0) -> 6 | AB9: =_xlfn.XLOOKUP(_xlfn.TEXTJOIN("_",TRUE,tbl_die_ordering[[#This Row],[Supplier]],tbl_die_ordering[[#This Row],[DIE NO]]),[1]Tracker!$AQ:$AQ,[1]Tracker!$Y:$Y,"") -> 142500703 | AC9: =_xlfn.XLOOKUP(_xlfn.TEXTJOIN("_",TRUE,tbl_die_ordering[[#This Row],[Supplier]],tbl_die_ordering[[#This Row],[DIE NO]]),[1]Tracker!$AQ:$AQ,[1]Tracker!$AC:$AC,"") -> 45683 | AF9: =TEXT(tbl_die_ordering[[#This Row],[Die Requested Date]],"mmm") -> Jan | AG9: =_xlfn.TEXTJOIN("_",TRUE,tbl_die_ordering[[#This Row],[Supplier]],tbl_die_ordering[[#This Row],[DIE NO]]) -> PDTMC_10485-501
A10: GEX 1 | B10: =_xlfn.XLOOKUP(_xlfn.TEXTJOIN("_",TRUE,tbl_die_ordering[[#This Row],[Supplier]],tbl_die_ordering[[#This Row],[DIE NO]]),[1]Tracker!$AQ:$AQ,[1]Tracker!$W:$W,"") -> 7612-25 | C10: 13640-506 | D10: B | E10: 320X160 | F10: 45660 | G10: =_xlfn.XLOOKUP(_xlfn.TEXTJOIN("_",TRUE,tbl_die_ordering[[#This Row],[Supplier]],tbl_die_ordering[[#This Row],[DIE NO]]),[1]Tracker!$AQ:$AQ,[1]Tracker!$V:$V,"") -> 45660 | H10: AIR | I10: 1 | J10: 2 | K10: 45664 | L10: 45666 | N10: =IFERROR(IF(tbl_die_ordering[[#This Row],[Design Approved Date]]<>"",L10-K10,""),"") -> 2 | O10: 45667 | P10: 45670 | Q10: 45667 | R10: 112500165 | S10: PHOENIX | T10: 45667 | W10: =_xlfn.LET( _xlpm.dieNo, tbl_die_ordering[[#This Row],[DIE NO]], _xlpm.orderNo, tbl_die_ordering[[#This Row],[Order No]], _xlpm.type, tbl_die_ordering[[#This Row],[TYPE]], _xlpm.designReceived, tbl_die_ordering[[#This Row],[Design Received Date]], _xlpm.designApproved, tbl_die_ordering[[#This Row],[Design Approved Date]], _xlpm.sim, tbl_die_ordering[[#This Row],[Sim]], _xlpm.prEntry, tbl_die_ordering[[#This Row],[PR Entry]], _xlpm.oracleEntry, tbl_die_ordering[[#This Row],[Oracle Entry]], _xlpm.ems, tbl_die_ordering[[#This Row],[Design saved to EMS FOLDER]], IF(_xlpm.dieNo = "", "", IF(_xlpm.orderNo = "", "PENDING FOR ORDERING", IF(_xlpm.type = "C", "CANCELLED", IF(_xlpm.type = "H", "HOLD", IF(_xlpm.designReceived = "", "AWAITING FOR DESIGN", IF(_xlpm.designApproved = "", IF(_xlpm.sim = "YES", "UNDER SIMULATION", "PENDING FOR DESIGN APPROVAL"), IF(_xlpm.prEntry = "", "PENDING FOR PR", IF(_xlpm.oracleEntry = "", "PENDING FOR ORACLE ENTRY", IF(_xlpm.ems = "", "PENDING FOR DESIGN TO EMS", "DONE"))))))))) ) -> DONE | X10: =IF(AND(tbl_die_ordering[[#This Row],[TYPE]]<>"C",tbl_die_ordering[[#This Row],[Design Approved Date]]<>""),tbl_die_ordering[[#This Row],[Design Approved Date]]-tbl_die_ordering[[#This Row],[Die Requested Date]],0) -> 6 | AB10: =_xlfn.XLOOKUP(_xlfn.TEXTJOIN("_",TRUE,tbl_die_ordering[[#This Row],[Supplier]],tbl_die_ordering[[#This Row],[DIE NO]]),[1]Tracker!$AQ:$AQ,[1]Tracker!$Y:$Y,"") -> 142500603 | AC10: =_xlfn.XLOOKUP(_xlfn.TEXTJOIN("_",TRUE,tbl_die_ordering[[#This Row],[Supplier]],tbl_die_ordering[[#This Row],[DIE NO]]),[1]Tracker!$AQ:$AQ,[1]Tracker!$AC:$AC,"") -> 45684 | AF10: =TEXT(tbl_die_ordering[[#This Row],[Die Requested Date]],"mmm") -> Jan | AG10: =_xlfn.TEXTJOIN("_",TRUE,tbl_die_ordering[[#This Row],[Supplier]],tbl_die_ordering[[#This Row],[DIE NO]]) -> PHOENIX _13640-506
A11: GEX 1 | B11: =_xlfn.XLOOKUP(_xlfn.TEXTJOIN("_",TRUE,tbl_die_ordering[[#This Row],[Supplier]],tbl_die_ordering[[#This Row],[DIE NO]]),[1]Tracker!$AQ:$AQ,[1]Tracker!$W:$W,"") -> 7612-25 | C11: 14853-204 | D11: B | E11: 280X160 | F11: 45660 | G11: =_xlfn.XLOOKUP(_xlfn.TEXTJOIN("_",TRUE,tbl_die_ordering[[#This Row],[Supplier]],tbl_die_ordering[[#This Row],[DIE NO]]),[1]Tracker!$AQ:$AQ,[1]Tracker!$V:$V,"") -> 45660 | H11: AIR | I11: 4 | J11: 8 | K11: 45664 | L11: 45666 | N11: =IFERROR(IF(tbl_die_ordering[[#This Row],[Design Approved Date]]<>"",L11-K11,""),"") -> 2 | O11: 45667 | P11: 45670 | Q11: 45667 | R11: 112500165 | S11: PHOENIX | T11: 45667 | W11: =_xlfn.LET( _xlpm.dieNo, tbl_die_ordering[[#This Row],[DIE NO]], _xlpm.orderNo, tbl_die_ordering[[#This Row],[Order No]], _xlpm.type, tbl_die_ordering[[#This Row],[TYPE]], _xlpm.designReceived, tbl_die_ordering[[#This Row],[Design Received Date]], _xlpm.designApproved, tbl_die_ordering[[#This Row],[Design Approved Date]], _xlpm.sim, tbl_die_ordering[[#This Row],[Sim]], _xlpm.prEntry, tbl_die_ordering[[#This Row],[PR Entry]], _xlpm.oracleEntry, tbl_die_ordering[[#This Row],[Oracle Entry]], _xlpm.ems, tbl_die_ordering[[#This Row],[Design saved to EMS FOLDER]], IF(_xlpm.dieNo = "", "", IF(_xlpm.orderNo = "", "PENDING FOR ORDERING", IF(_xlpm.type = "C", "CANCELLED", IF(_xlpm.type = "H", "HOLD", IF(_xlpm.designReceived = "", "AWAITING FOR DESIGN", IF(_xlpm.designApproved = "", IF(_xlpm.sim = "YES", "UNDER SIMULATION", "PENDING FOR DESIGN APPROVAL"), IF(_xlpm.prEntry = "", "PENDING FOR PR", IF(_xlpm.oracleEntry = "", "PENDING FOR ORACLE ENTRY", IF(_xlpm.ems = "", "PENDING FOR DESIGN TO EMS", "DONE"))))))))) ) -> DONE | X11: =IF(AND(tbl_die_ordering[[#This Row],[TYPE]]<>"C",tbl_die_ordering[[#This Row],[Design Approved Date]]<>""),tbl_die_ordering[[#This Row],[Design Approved Date]]-tbl_die_ordering[[#This Row],[Die Requested Date]],0) -> 6 | AB11: =_xlfn.XLOOKUP(_xlfn.TEXTJOIN("_",TRUE,tbl_die_ordering[[#This Row],[Supplier]],tbl_die_ordering[[#This Row],[DIE NO]]),[1]Tracker!$AQ:$AQ,[1]Tracker!$Y:$Y,"") -> 142500603 | AC11: =_xlfn.XLOOKUP(_xlfn.TEXTJOIN("_",TRUE,tbl_die_ordering[[#This Row],[Supplier]],tbl_die_ordering[[#This Row],[DIE NO]]),[1]Tracker!$AQ:$AQ,[1]Tracker!$AC:$AC,"") -> 45684 | AF11: =TEXT(tbl_die_ordering[[#This Row],[Die Requested Date]],"mmm") -> Jan | AG11: =_xlfn.TEXTJOIN("_",TRUE,tbl_die_ordering[[#This Row],[Supplier]],tbl_die_ordering[[#This Row],[DIE NO]]) -> PHOENIX _14853-204
A12: GEX 1 | B12: =_xlfn.XLOOKUP(_xlfn.TEXTJOIN("_",TRUE,tbl_die_ordering[[#This Row],[Supplier]],tbl_die_ordering[[#This Row],[DIE NO]]),[1]Tracker!$AQ:$AQ,[1]Tracker!$W:$W,"") -> 7612-25 | C12: 19105-403 | D12: B | E12: 250X160 | F12: 45660 | G12: =_xlfn.XLOOKUP(_xlfn.TEXTJOIN("_",TRUE,tbl_die_ordering[[#This Row],[Supplier]],tbl_die_ordering[[#This Row],[DIE NO]]),[1]Tracker!$AQ:$AQ,[1]Tracker!$V:$V,"") -> 45660 | H12: AIR | I12: 1 | J12: 2 | K12: 45664 | L12: 45666 | N12: =IFERROR(IF(tbl_die_ordering[[#This Row],[Design Approved Date]]<>"",L12-K12,""),"") -> 2 | O12: 45667 | P12: 45670 | Q12: 45667 | R12: 112500165 | S12: PHOENIX | T12: 45667 | W12: =_xlfn.LET( _xlpm.dieNo, tbl_die_ordering[[#This Row],[DIE NO]], _xlpm.orderNo, tbl_die_ordering[[#This Row],[Order No]], _xlpm.type, tbl_die_ordering[[#This Row],[TYPE]], _xlpm.designReceived, tbl_die_ordering[[#This Row],[Design Received Date]], _xlpm.designApproved, tbl_die_ordering[[#This Row],[Design Approved Date]], _xlpm.sim, tbl_die_ordering[[#This Row],[Sim]], _xlpm.prEntry, tbl_die_ordering[[#This Row],[PR Entry]], _xlpm.oracleEntry, tbl_die_ordering[[#This Row],[Oracle Entry]], _xlpm.ems, tbl_die_ordering[[#This Row],[Design saved to EMS FOLDER]], IF(_xlpm.dieNo = "", "", IF(_xlpm.orderNo = "", "PENDING FOR ORDERING", IF(_xlpm.type = "C", "CANCELLED", IF(_xlpm.type = "H", "HOLD", IF(_xlpm.designReceived = "", "AWAITING FOR DESIGN", IF(_xlpm.designApproved = "", IF(_xlpm.sim = "YES", "UNDER SIMULATION", "PENDING FOR DESIGN APPROVAL"), IF(_xlpm.prEntry = "", "PENDING FOR PR", IF(_xlpm.oracleEntry = "", "PENDING FOR ORACLE ENTRY", IF(_xlpm.ems = "", "PENDING FOR DESIGN TO EMS", "DONE"))))))))) ) -> DONE | X12: =IF(AND(tbl_die_ordering[[#This Row],[TYPE]]<>"C",tbl_die_ordering[[#This Row],[Design Approved Date]]<>""),tbl_die_ordering[[#This Row],[Design Approved Date]]-tbl_die_ordering[[#This Row],[Die Requested Date]],0) -> 6 | AB12: =_xlfn.XLOOKUP(_xlfn.TEXTJOIN("_",TRUE,tbl_die_ordering[[#This Row],[Supplier]],tbl_die_ordering[[#This Row],[DIE NO]]),[1]Tracker!$AQ:$AQ,[1]Tracker!$Y:$Y,"") -> 142500603 | AC12: =_xlfn.XLOOKUP(_xlfn.TEXTJOIN("_",TRUE,tbl_die_ordering[[#This Row],[Supplier]],tbl_die_ordering[[#This Row],[DIE NO]]),[1]Tracker!$AQ:$AQ,[1]Tracker!$AC:$AC,"") -> 45684 | AF12: =TEXT(tbl_die_ordering[[#This Row],[Die Requested Date]],"mmm") -> Jan | AG12: =_xlfn.TEXTJOIN("_",TRUE,tbl_die_ordering[[#This Row],[Supplier]],tbl_die_ordering[[#This Row],[DIE NO]]) -> PHOENIX _19105-403
A13: GEX 1 | B13: =_xlfn.XLOOKUP(_xlfn.TEXTJOIN("_",TRUE,tbl_die_ordering[[#This Row],[Supplier]],tbl_die_ordering[[#This Row],[DIE NO]]),[1]Tracker!$AQ:$AQ,[1]Tracker!$W:$W,"") -> 7612-25 | C13: 28424-202 | D13: B | E13: 320X160 | F13: 45660 | G13: =_xlfn.XLOOKUP(_xlfn.TEXTJOIN("_",TRUE,tbl_die_ordering[[#This Row],[Supplier]],tbl_die_ordering[[#This Row],[DIE NO]]),[1]Tracker!$AQ:$AQ,[1]Tracker!$V:$V,"") -> 45660 | H13: AIR | I13: 1 | J13: 1 | K13: 45664 | L13: 45666 | N13: =IFERROR(IF(tbl_die_ordering[[#This Row],[Design Approved Date]]<>"",L13-K13,""),"") -> 2 | O13: 45667 | P13: 45670 | Q13: 45667 | R13: 112500165 | S13: PHOENIX | T13: 45667 | W13: =_xlfn.LET( _xlpm.dieNo, tbl_die_ordering[[#This Row],[DIE NO]], _xlpm.orderNo, tbl_die_ordering[[#This Row],[Order No]], _xlpm.type, tbl_die_ordering[[#This Row],[TYPE]], _xlpm.designReceived, tbl_die_ordering[[#This Row],[Design Received Date]], _xlpm.designApproved, tbl_die_ordering[[#This Row],[Design Approved Date]], _xlpm.sim, tbl_die_ordering[[#This Row],[Sim]], _xlpm.prEntry, tbl_die_ordering[[#This Row],[PR Entry]], _xlpm.oracleEntry, tbl_die_ordering[[#This Row],[Oracle Entry]], _xlpm.ems, tbl_die_ordering[[#This Row],[Design saved to EMS FOLDER]], IF(_xlpm.dieNo = "", "", IF(_xlpm.orderNo = "", "PENDING FOR ORDERING", IF(_xlpm.type = "C", "CANCELLED", IF(_xlpm.type = "H", "HOLD", IF(_xlpm.designReceived = "", "AWAITING FOR DESIGN", IF(_xlpm.designApproved = "", IF(_xlpm.sim = "YES", "UNDER SIMULATION", "PENDING FOR DESIGN APPROVAL"), IF(_xlpm.prEntry = "", "PENDING FOR PR", IF(_xlpm.oracleEntry = "", "PENDING FOR ORACLE ENTRY", IF(_xlpm.ems = "", "PENDING FOR DESIGN TO EMS", "DONE"))))))))) ) -> DONE | X13: =IF(AND(tbl_die_ordering[[#This Row],[TYPE]]<>"C",tbl_die_ordering[[#This Row],[Design Approved Date]]<>""),tbl_die_ordering[[#This Row],[Design Approved Date]]-tbl_die_ordering[[#This Row],[Die Requested Date]],0) -> 6 | AB13: =_xlfn.XLOOKUP(_xlfn.TEXTJOIN("_",TRUE,tbl_die_ordering[[#This Row],[Supplier]],tbl_die_ordering[[#This Row],[DIE NO]]),[1]Tracker!$AQ:$AQ,[1]Tracker!$Y:$Y,"") -> 142500701 | AC13: =_xlfn.XLOOKUP(_xlfn.TEXTJOIN("_",TRUE,tbl_die_ordering[[#This Row],[Supplier]],tbl_die_ordering[[#This Row],[DIE NO]]),[1]Tracker!$AQ:$AQ,[1]Tracker!$AC:$AC,"") -> 45684 | AF13: =TEXT(tbl_die_ordering[[#This Row],[Die Requested Date]],"mmm") -> Jan | AG13: =_xlfn.TEXTJOIN("_",TRUE,tbl_die_ordering[[#This Row],[Supplier]],tbl_die_ordering[[#This Row],[DIE NO]]) -> PHOENIX _28424-202
A14: GEX 1 | B14: =_xlfn.XLOOKUP(_xlfn.TEXTJOIN("_",TRUE,tbl_die_ordering[[#This Row],[Supplier]],tbl_die_ordering[[#This Row],[DIE NO]]),[1]Tracker!$AQ:$AQ,[1]Tracker!$W:$W,"") -> 7610-25 | C14: 12726-503 | D14: B | E14: 280X160 | F14: 45660 | G14: =_xlfn.XLOOKUP(_xlfn.TEXTJOIN("_",TRUE,tbl_die_ordering[[#This Row],[Supplier]],tbl_die_ordering[[#This Row],[DIE NO]]),[1]Tracker!$AQ:$AQ,[1]Tracker!$V:$V,"") -> 45660 | H14: AIR | I14: 1 | J14: 2 | K14: 45660 | L14: 45668 | N14: =IFERROR(IF(tbl_die_ordering[[#This Row],[Design Approved Date]]<>"",L14-K14,""),"") -> 8 | O14: 45670 | P14: 45670 | Q14: 45670 | R14: 112500175 | S14: EKSTEK | T14: 45670 | V14: desigh received on 03/01/2025 similar die is in simulation (14674-427) both dies will be sent for approval together 06/01/2025 | W14: =_xlfn.LET( _xlpm.dieNo, tbl_die_ordering[[#This Row],[DIE NO]], _xlpm.orderNo, tbl_die_ordering[[#This Row],[Order No]], _xlpm.type, tbl_die_ordering[[#This Row],[TYPE]], _xlpm.designReceived, tbl_die_ordering[[#This Row],[Design Received Date]], _xlpm.designApproved, tbl_die_ordering[[#This Row],[Design Approved Date]], _xlpm.sim, tbl_die_ordering[[#This Row],[Sim]], _xlpm.prEntry, tbl_die_ordering[[#This Row],[PR Entry]], _xlpm.oracleEntry, tbl_die_ordering[[#This Row],[Oracle Entry]], _xlpm.ems, tbl_die_ordering[[#This Row],[Design saved to EMS FOLDER]], IF(_xlpm.dieNo = "", "", IF(_xlpm.orderNo = "", "PENDING FOR ORDERING", IF(_xlpm.type = "C", "CANCELLED", IF(_xlpm.type = "H", "HOLD", IF(_xlpm.designReceived = "", "AWAITING FOR DESIGN", IF(_xlpm.designApproved = "", IF(_xlpm.sim = "YES", "UNDER SIMULATION", "PENDING FOR DESIGN APPROVAL"), IF(_xlpm.prEntry = "", "PENDING FOR PR", IF(_xlpm.oracleEntry = "", "PENDING FOR ORACLE ENTRY", IF(_xlpm.ems = "", "PENDING FOR DESIGN TO EMS", "DONE"))))))))) ) -> DONE | X14: =IF(AND(tbl_die_ordering[[#This Row],[TYPE]]<>"C",tbl_die_ordering[[#This Row],[Design Approved Date]]<>""),tbl_die_ordering[[#This Row],[Design Approved Date]]-tbl_die_ordering[[#This Row],[Die Requested Date]],0) -> 8 | AB14: =_xlfn.XLOOKUP(_xlfn.TEXTJOIN("_",TRUE,tbl_die_ordering[[#This Row],[Supplier]],tbl_die_ordering[[#This Row],[DIE NO]]),[1]Tracker!$AQ:$AQ,[1]Tracker!$Y:$Y,"") -> 142500487 | AC14: =_xlfn.XLOOKUP(_xlfn.TEXTJOIN("_",TRUE,tbl_die_ordering[[#This Row],[Supplier]],tbl_die_ordering[[#This Row],[DIE NO]]),[1]Tracker!$AQ:$AQ,[1]Tracker!$AC:$AC,"") -> 45676 | AF14: =TEXT(tbl_die_ordering[[#This Row],[Die Requested Date]],"mmm") -> Jan | AG14: =_xlfn.TEXTJOIN("_",TRUE,tbl_die_ordering[[#This Row],[Supplier]],tbl_die_ordering[[#This Row],[DIE NO]]) -> EKSTEK_12726-503
A15: GEX 1 | B15: =_xlfn.XLOOKUP(_xlfn.TEXTJOIN("_",TRUE,tbl_die_ordering[[#This Row],[Supplier]],tbl_die_ordering[[#This Row],[DIE NO]]),[1]Tracker!$AQ:$AQ,[1]Tracker!$W:$W,"") -> 7611-25 | C15: 05203-201 | D15: B | E15: 250X160 | F15: 45660 | G15: =_xlfn.XLOOKUP(_xlfn.TEXTJOIN("_",TRUE,tbl_die_ordering[[#This Row],[Supplier]],tbl_die_ordering[[#This Row],[DIE NO]]),[1]Tracker!$AQ:$AQ,[1]Tracker!$V:$V,"") -> 45660 | H15: LAND | I15: 1 | J15: 4 | K15: 45670 | L15: 45672 | N15: =IFERROR(IF(tbl_die_ordering[[#This Row],[Design Approved Date]]<>"",L15-K15,""),"") -> 2 | O15: 45673 | P15: 45675 | Q15: 45673 | R15: 112500254 | S15: PDTMC | T15: 45673 | V15: ask for revision 09/01/2025 | W15: =_xlfn.LET( _xlpm.dieNo, tbl_die_ordering[[#This Row],[DIE NO]], _xlpm.orderNo, tbl_die_ordering[[#This Row],[Order No]], _xlpm.type, tbl_die_ordering[[#This Row],[TYPE]], _xlpm.designReceived, tbl_die_ordering[[#This Row],[Design Received Date]], _xlpm.designApproved, tbl_die_ordering[[#This Row],[Design Approved Date]], _xlpm.sim, tbl_die_ordering[[#This Row],[Sim]], _xlpm.prEntry, tbl_die_ordering[[#This Row],[PR Entry]], _xlpm.oracleEntry, tbl_die_ordering[[#This Row],[Oracle Entry]], _xlpm.ems, tbl_die_ordering[[#This Row],[Design saved to EMS FOLDER]], IF(_xlpm.dieNo = "", "", IF(_xlpm.orderNo = "", "PENDING FOR ORDERING", IF(_xlpm.type = "C", "CANCELLED", IF(_xlpm.type = "H", "HOLD", IF(_xlpm.designReceived = "", "AWAITING FOR DESIGN", IF(_xlpm.designApproved = "", IF(_xlpm.sim = "YES", "UNDER SIMULATION", "PENDING FOR DESIGN APPROVAL"), IF(_xlpm.prEntry = "", "PENDING FOR PR", IF(_xlpm.oracleEntry = "", "PENDING FOR ORACLE ENTRY", IF(_xlpm.ems = "", "PENDING FOR DESIGN TO EMS", "DONE"))))))))) ) -> DONE | X15: =IF(AND(tbl_die_ordering[[#This Row],[TYPE]]<>"C",tbl_die_ordering[[#This Row],[Design Approved Date]]<>""),tbl_die_ordering[[#This Row],[Design Approved Date]]-tbl_die_ordering[[#This Row],[Die Requested Date]],0) -> 12 | AB15: =_xlfn.XLOOKUP(_xlfn.TEXTJOIN("_",TRUE,tbl_die_ordering[[#This Row],[Supplier]],tbl_die_ordering[[#This Row],[DIE NO]]),[1]Tracker!$AQ:$AQ,[1]Tracker!$Y:$Y,"") -> 142501911 | AC15: =_xlfn.XLOOKUP(_xlfn.TEXTJOIN("_",TRUE,tbl_die_ordering[[#This Row],[Supplier]],tbl_die_ordering[[#This Row],[DIE NO]]),[1]Tracker!$AQ:$AQ,[1]Tracker!$AC:$AC,"") -> 45719 | AE15: cav increased | AF15: =TEXT(tbl_die_ordering[[#This Row],[Die Requested Date]],"mmm") -> Jan | AG15: =_xlfn.TEXTJOIN("_",TRUE,tbl_die_ordering[[#This Row],[Supplier]],tbl_die_ordering[[#This Row],[DIE NO]]) -> PDTMC_05203-201
A16: GEX 1 | B16: =_xlfn.XLOOKUP(_xlfn.TEXTJOIN("_",TRUE,tbl_die_ordering[[#This Row],[Supplier]],tbl_die_ordering[[#This Row],[DIE NO]]),[1]Tracker!$AQ:$AQ,[1]Tracker!$W:$W,"") -> 7611-25 | C16: 12441-406 | D16: B | E16: 250X160 | F16: 45660 | G16: =_xlfn.XLOOKUP(_xlfn.TEXTJOIN("_",TRUE,tbl_die_ordering[[#This Row],[Supplier]],tbl_die_ordering[[#This Row],[DIE NO]]),[1]Tracker!$AQ:$AQ,[1]Tracker!$V:$V,"") -> 45660 | H16: LAND | I16: 1 | J16: 1 | K16: 45666 | L16: 45673 | N16: =IFERROR(IF(tbl_die_ordering[[#This Row],[Design Approved Date]]<>"",L16-K16,""),"") -> 7 | O16: 45675 | P16: 45675 | Q16: 45675 | R16: 112500275 | S16: PDTMC | T16: 45675 | W16: =_xlfn.LET( _xlpm.dieNo, tbl_die_ordering[[#This Row],[DIE NO]], _xlpm.orderNo, tbl_die_ordering[[#This Row],[Order No]], _xlpm.type, tbl_die_ordering[[#This Row],[TYPE]], _xlpm.designReceived, tbl_die_ordering[[#This Row],[Design Received Date]], _xlpm.designApproved, tbl_die_ordering[[#This Row],[Design Approved Date]], _xlpm.sim, tbl_die_ordering[[#This Row],[Sim]], _xlpm.prEntry, tbl_die_ordering[[#This Row],[PR Entry]], _xlpm.oracleEntry, tbl_die_ordering[[#This Row],[Oracle Entry]], _xlpm.ems, tbl_die_ordering[[#This Row],[Design saved to EMS FOLDER]], IF(_xlpm.dieNo = "", "", IF(_xlpm.orderNo = "", "PENDING FOR ORDERING", IF(_xlpm.type = "C", "CANCELLED", IF(_xlpm.type = "H", "HOLD", IF(_xlpm.designReceived = "", "AWAITING FOR DESIGN", IF(_xlpm.designApproved = "", IF(_xlpm.sim = "YES", "UNDER SIMULATION", "PENDING FOR DESIGN APPROVAL"), IF(_xlpm.prEntry = "", "PENDING FOR PR", IF(_xlpm.oracleEntry = "", "PENDING FOR ORACLE ENTRY", IF(_xlpm.ems = "", "PENDING FOR DESIGN TO EMS", "DONE"))))))))) ) -> DONE | X16: =IF(AND(tbl_die_ordering[[#This Row],[TYPE]]<>"C",tbl_die_ordering[[#This Row],[Design Approved Date]]<>""),tbl_die_ordering[[#This Row],[Design Approved Date]]-tbl_die_ordering[[#This Row],[Die Requested Date]],0) -> 13 | AB16: =_xlfn.XLOOKUP(_xlfn.TEXTJOIN("_",TRUE,tbl_die_ordering[[#This Row],[Supplier]],tbl_die_ordering[[#This Row],[DIE NO]]),[1]Tracker!$AQ:$AQ,[1]Tracker!$Y:$Y,"") -> 142500748 | AC16: =_xlfn.XLOOKUP(_xlfn.TEXTJOIN("_",TRUE,tbl_die_ordering[[#This Row],[Supplier]],tbl_die_ordering[[#This Row],[DIE NO]]),[1]Tracker!$AQ:$AQ,[1]Tracker!$AC:$AC,"") -> 45685 | AF16: =TEXT(tbl_die_ordering[[#This Row],[Die Requested Date]],"mmm") -> Jan | AG16: =_xlfn.TEXTJOIN("_",TRUE,tbl_die_ordering[[#This Row],[Supplier]],tbl_die_ordering[[#This Row],[DIE NO]]) -> PDTMC_12441-406
A17: GEX 1 | B17: =_xlfn.XLOOKUP(_xlfn.TEXTJOIN("_",TRUE,tbl_die_ordering[[#This Row],[Supplier]],tbl_die_ordering[[#This Row],[DIE NO]]),[1]Tracker!$AQ:$AQ,[1]Tracker!$W:$W,"") -> 7612-25 | C17: 14856-203 | D17: B | E17: 280X160 | F17: 45660 | G17: =_xlfn.XLOOKUP(_xlfn.TEXTJOIN("_",TRUE,tbl_die_ordering[[#This Row],[Supplier]],tbl_die_ordering[[#This Row],[DIE NO]]),[1]Tracker!$AQ:$AQ,[1]Tracker!$V:$V,"") -> 45660 | H17: AIR | I17: 1 | J17: 1 | K17: 45665 | L17: 45673 | N17: =IFERROR(IF(tbl_die_ordering[[#This Row],[Design Approved Date]]<>"",L17-K17,""),"") -> 8 | O17: 45675 | P17: 45675 | Q17: 45675 | R17: 112500275 | S17: PHOENIX | T17: 45675 | W17: =_xlfn.LET( _xlpm.dieNo, tbl_die_ordering[[#This Row],[DIE NO]], _xlpm.orderNo, tbl_die_ordering[[#This Row],[Order No]], _xlpm.type, tbl_die_ordering[[#This Row],[TYPE]], _xlpm.designReceived, tbl_die_ordering[[#This Row],[Design Received Date]], _xlpm.designApproved, tbl_die_ordering[[#This Row],[Design Approved Date]], _xlpm.sim, tbl_die_ordering[[#This Row],[Sim]], _xlpm.prEntry, tbl_die_ordering[[#This Row],[PR Entry]], _xlpm.oracleEntry, tbl_die_ordering[[#This Row],[Oracle Entry]], _xlpm.ems, tbl_die_ordering[[#This Row],[Design saved to EMS FOLDER]], IF(_xlpm.dieNo = "", "", IF(_xlpm.orderNo = "", "PENDING FOR ORDERING", IF(_xlpm.type = "C", "CANCELLED", IF(_xlpm.type = "H", "HOLD", IF(_xlpm.designReceived = "", "AWAITING FOR DESIGN", IF(_xlpm.designApproved = "", IF(_xlpm.sim = "YES", "UNDER SIMULATION", "PENDING FOR DESIGN APPROVAL"), IF(_xlpm.prEntry = "", "PENDING FOR PR", IF(_xlpm.oracleEntry = "", "PENDING FOR ORACLE ENTRY", IF(_xlpm.ems = "", "PENDING FOR DESIGN TO EMS", "DONE"))))))))) ) -> DONE | X17: =IF(AND(tbl_die_ordering[[#This Row],[TYPE]]<>"C",tbl_die_ordering[[#This Row],[Design Approved Date]]<>""),tbl_die_ordering[[#This Row],[Design Approved Date]]-tbl_die_ordering[[#This Row],[Die Requested Date]],0) -> 13 | AB17: =_xlfn.XLOOKUP(_xlfn.TEXTJOIN("_",TRUE,tbl_die_ordering[[#This Row],[Supplier]],tbl_die_ordering[[#This Row],[DIE NO]]),[1]Tracker!$AQ:$AQ,[1]Tracker!$Y:$Y,"") -> 142500749 | AC17: =_xlfn.XLOOKUP(_xlfn.TEXTJOIN("_",TRUE,tbl_die_ordering[[#This Row],[Supplier]],tbl_die_ordering[[#This Row],[DIE NO]]),[1]Tracker!$AQ:$AQ,[1]Tracker!$AC:$AC,"") -> 45685 | AF17: =TEXT(tbl_die_ordering[[#This Row],[Die Requested Date]],"mmm") -> Jan | AG17: =_xlfn.TEXTJOIN("_",TRUE,tbl_die_ordering[[#This Row],[Supplier]],tbl_die_ordering[[#This Row],[DIE NO]]) -> PHOENIX _14856-203
A18: GEX 1 | B18: =_xlfn.XLOOKUP(_xlfn.TEXTJOIN("_",TRUE,tbl_die_ordering[[#This Row],[Supplier]],tbl_die_ordering[[#This Row],[DIE NO]]),[1]Tracker!$AQ:$AQ,[1]Tracker!$W:$W,"") -> 7612-25 | C18: 14857-203 | D18: B | E18: 320X160 | F18: 45660 | G18: =_xlfn.XLOOKUP(_xlfn.TEXTJOIN("_",TRUE,tbl_die_ordering[[#This Row],[Supplier]],tbl_die_ordering[[#This Row],[DIE NO]]),[1]Tracker!$AQ:$AQ,[1]Tracker!$V:$V,"") -> 45660 | H18: AIR | I18: 1 | J18: 1 | K18: 45665 | L18: 45673 | N18: =IFERROR(IF(tbl_die_ordering[[#This Row],[Design Approved Date]]<>"",L18-K18,""),"") -> 8 | O18: 45675 | P18: 45675 | Q18: 45675 | R18: 112500275 | S18: PHOENIX | T18: 45675 | W18: =_xlfn.LET( _xlpm.dieNo, tbl_die_ordering[[#This Row],[DIE NO]], _xlpm.orderNo, tbl_die_ordering[[#This Row],[Order No]], _xlpm.type, tbl_die_ordering[[#This Row],[TYPE]], _xlpm.designReceived, tbl_die_ordering[[#This Row],[Design Received Date]], _xlpm.designApproved, tbl_die_ordering[[#This Row],[Design Approved Date]], _xlpm.sim, tbl_die_ordering[[#This Row],[Sim]], _xlpm.prEntry, tbl_die_ordering[[#This Row],[PR Entry]], _xlpm.oracleEntry, tbl_die_ordering[[#This Row],[Oracle Entry]], _xlpm.ems, tbl_die_ordering[[#This Row],[Design saved to EMS FOLDER]], IF(_xlpm.dieNo = "", "", IF(_xlpm.orderNo = "", "PENDING FOR ORDERING", IF(_xlpm.type = "C", "CANCELLED", IF(_xlpm.type = "H", "HOLD", IF(_xlpm.designReceived = "", "AWAITING FOR DESIGN", IF(_xlpm.designApproved = "", IF(_xlpm.sim = "YES", "UNDER SIMULATION", "PENDING FOR DESIGN APPROVAL"), IF(_xlpm.prEntry = "", "PENDING FOR PR", IF(_xlpm.oracleEntry = "", "PENDING FOR ORACLE ENTRY", IF(_xlpm.ems = "", "PENDING FOR DESIGN TO EMS", "DONE"))))))))) ) -> DONE | X18: =IF(AND(tbl_die_ordering[[#This Row],[TYPE]]<>"C",tbl_die_ordering[[#This Row],[Design Approved Date]]<>""),tbl_die_ordering[[#This Row],[Design Approved Date]]-tbl_die_ordering[[#This Row],[Die Requested Date]],0) -> 13 | AB18: =_xlfn.XLOOKUP(_xlfn.TEXTJOIN("_",TRUE,tbl_die_ordering[[#This Row],[Supplier]],tbl_die_ordering[[#This Row],[DIE NO]]),[1]Tracker!$AQ:$AQ,[1]Tracker!$Y:$Y,"") -> 142500749 | AC18: =_xlfn.XLOOKUP(_xlfn.TEXTJOIN("_",TRUE,tbl_die_ordering[[#This Row],[Supplier]],tbl_die_ordering[[#This Row],[DIE NO]]),[1]Tracker!$AQ:$AQ,[1]Tracker!$AC:$AC,"") -> 45685 | AF18: =TEXT(tbl_die_ordering[[#This Row],[Die Requested Date]],"mmm") -> Jan | AG18: =_xlfn.TEXTJOIN("_",TRUE,tbl_die_ordering[[#This Row],[Supplier]],tbl_die_ordering[[#This Row],[DIE NO]]) -> PHOENIX _14857-203
A19: GEX 2 | B19: =_xlfn.XLOOKUP(_xlfn.TEXTJOIN("_",TRUE,tbl_die_ordering[[#This Row],[Supplier]],tbl_die_ordering[[#This Row],[DIE NO]]),[1]Tracker!$AQ:$AQ,[1]Tracker!$W:$W,"") -> 7614-25 | C19: 051137-2501 | D19: N | E19: 280X165 | F19: 45663 | G19: =_xlfn.XLOOKUP(_xlfn.TEXTJOIN("_",TRUE,tbl_die_ordering[[#This Row],[Supplier]],tbl_die_ordering[[#This Row],[DIE NO]]),[1]Tracker!$AQ:$AQ,[1]Tracker!$V:$V,"") -> 45663 | H19: LAND | I19: 1 | J19: 1 | K19: 45665 | L19: 45668 | M19: YES | N19: =IFERROR(IF(tbl_die_ordering[[#This Row],[Design Approved Date]]<>"",L19-K19,""),"") -> 3 | O19: 45671 | P19: 45674 | Q19: 45671 | R19: 1300001099 | S19: PDTMC | T19: 45674 | U19: APT | W19: =_xlfn.LET( _xlpm.dieNo, tbl_die_ordering[[#This Row],[DIE NO]], _xlpm.orderNo, tbl_die_ordering[[#This Row],[Order No]], _xlpm.type, tbl_die_ordering[[#This Row],[TYPE]], _xlpm.designReceived, tbl_die_ordering[[#This Row],[Design Received Date]], _xlpm.designApproved, tbl_die_ordering[[#This Row],[Design Approved Date]], _xlpm.sim, tbl_die_ordering[[#This Row],[Sim]], _xlpm.prEntry, tbl_die_ordering[[#This Row],[PR Entry]], _xlpm.oracleEntry, tbl_die_ordering[[#This Row],[Oracle Entry]], _xlpm.ems, tbl_die_ordering[[#This Row],[Design saved to EMS FOLDER]], IF(_xlpm.dieNo = "", "", IF(_xlpm.orderNo = "", "PENDING FOR ORDERING", IF(_xlpm.type = "C", "CANCELLED", IF(_xlpm.type = "H", "HOLD", IF(_xlpm.designReceived = "", "AWAITING FOR DESIGN", IF(_xlpm.designApproved = "", IF(_xlpm.sim = "YES", "UNDER SIMULATION", "PENDING FOR DESIGN APPROVAL"), IF(_xlpm.prEntry = "", "PENDING FOR PR", IF(_xlpm.oracleEntry = "", "PENDING FOR ORACLE ENTRY", IF(_xlpm.ems = "", "PENDING FOR DESIGN TO EMS", "DONE"))))))))) ) -> DONE | X19: =IF(AND(tbl_die_ordering[[#This Row],[TYPE]]<>"C",tbl_die_ordering[[#This Row],[Design Approved Date]]<>""),tbl_die_ordering[[#This Row],[Design Approved Date]]-tbl_die_ordering[[#This Row],[Die Requested Date]],0) -> 5 | AB19: =_xlfn.XLOOKUP(_xlfn.TEXTJOIN("_",TRUE,tbl_die_ordering[[#This Row],[Supplier]],tbl_die_ordering[[#This Row],[DIE NO]]),[1]Tracker!$AQ:$AQ,[1]Tracker!$Y:$Y,"") -> M124 | AC19: =_xlfn.XLOOKUP(_xlfn.TEXTJOIN("_",TRUE,tbl_die_ordering[[#This Row],[Supplier]],tbl_die_ordering[[#This Row],[DIE NO]]),[1]Tracker!$AQ:$AQ,[1]Tracker!$AC:$AC,"") -> 45693 | AF19: =TEXT(tbl_die_ordering[[#This Row],[Die Requested Date]],"mmm") -> Jan | AG19: =_xlfn.TEXTJOIN("_",TRUE,tbl_die_ordering[[#This Row],[Supplier]],tbl_die_ordering[[#This Row],[DIE NO]]) -> PDTMC_051137-2501
A20: GEX 2 | B20: =_xlfn.XLOOKUP(_xlfn.TEXTJOIN("_",TRUE,tbl_die_ordering[[#This Row],[Supplier]],tbl_die_ordering[[#This Row],[DIE NO]]),[1]Tracker!$AQ:$AQ,[1]Tracker!$W:$W,"") -> 7614-25 | C20: 051138-3501 | D20: N | E20: 350X210 | F20: 45663 | G20: =_xlfn.XLOOKUP(_xlfn.TEXTJOIN("_",TRUE,tbl_die_ordering[[#This Row],[Supplier]],tbl_die_ordering[[#This Row],[DIE NO]]),[1]Tracker!$AQ:$AQ,[1]Tracker!$V:$V,"") -> 45663 | H20: LAND | I20: 1 | J20: 1 | K20: 45665 | L20: 45670 | M20: YES | N20: =IFERROR(IF(tbl_die_ordering[[#This Row],[Design Approved Date]]<>"",L20-K20,""),"") -> 5 | O20: 45671 | P20: 45674 | Q20: 45671 | R20: 1300001099 | S20: PDTMC | T20: 45674 | U20: APT | W20: =_xlfn.LET( _xlpm.dieNo, tbl_die_ordering[[#This Row],[DIE NO]], _xlpm.orderNo, tbl_die_ordering[[#This Row],[Order No]], _xlpm.type, tbl_die_ordering[[#This Row],[TYPE]], _xlpm.designReceived, tbl_die_ordering[[#This Row],[Design Received Date]], _xlpm.designApproved, tbl_die_ordering[[#This Row],[Design Approved Date]], _xlpm.sim, tbl_die_ordering[[#This Row],[Sim]], _xlpm.prEntry, tbl_die_ordering[[#This Row],[PR Entry]], _xlpm.oracleEntry, tbl_die_ordering[[#This Row],[Oracle Entry]], _xlpm.ems, tbl_die_ordering[[#This Row],[Design saved to EMS FOLDER]], IF(_xlpm.dieNo = "", "", IF(_xlpm.orderNo = "", "PENDING FOR ORDERING", IF(_xlpm.type = "C", "CANCELLED", IF(_xlpm.type = "H", "HOLD", IF(_xlpm.designReceived = "", "AWAITING FOR DESIGN", IF(_xlpm.designApproved = "", IF(_xlpm.sim = "YES", "UNDER SIMULATION", "PENDING FOR DESIGN APPROVAL"), IF(_xlpm.prEntry = "", "PENDING FOR PR", IF(_xlpm.oracleEntry = "", "PENDING FOR ORACLE ENTRY", IF(_xlpm.ems = "", "PENDING FOR DESIGN TO EMS", "DONE"))))))))) ) -> DONE | X20: =IF(AND(tbl_die_ordering[[#This Row],[TYPE]]<>"C",tbl_die_ordering[[#This Row],[Design Approved Date]]<>""),tbl_die_ordering[[#This Row],[Design Approved Date]]-tbl_die_ordering[[#This Row],[Die Requested Date]],0) -> 7 | AB20: =_xlfn.XLOOKUP(_xlfn.TEXTJOIN("_",TRUE,tbl_die_ordering[[#This Row],[Supplier]],tbl_die_ordering[[#This Row],[DIE NO]]),[1]Tracker!$AQ:$AQ,[1]Tracker!$Y:$Y,"") -> M124 | AC20: =_xlfn.XLOOKUP(_xlfn.TEXTJOIN("_",TRUE,tbl_die_ordering[[#This Row],[Supplier]],tbl_die_ordering[[#This Row],[DIE NO]]),[1]Tracker!$AQ:$AQ,[1]Tracker!$AC:$AC,"") -> 45693 | AF20: =TEXT(tbl_die_ordering[[#This Row],[Die Requested Date]],"mmm") -> Jan | AG20: =_xlfn.TEXTJOIN("_",TRUE,tbl_die_ordering[[#This Row],[Supplier]],tbl_die_ordering[[#This Row],[DIE NO]]) -> PDTMC_051138-3501
A21: GEX 2 | B21: =_xlfn.XLOOKUP(_xlfn.TEXTJOIN("_",TRUE,tbl_die_ordering[[#This Row],[Supplier]],tbl_die_ordering[[#This Row],[DIE NO]]),[1]Tracker!$AQ:$AQ,[1]Tracker!$W:$W,"") -> 7614-25 | C21: 051139-2501 | D21: N | E21: 280X165 | F21: 45663 | G21: =_xlfn.XLOOKUP(_xlfn.TEXTJOIN("_",TRUE,tbl_die_ordering[[#This Row],[Supplier]],tbl_die_ordering[[#This Row],[DIE NO]]),[1]Tracker!$AQ:$AQ,[1]Tracker!$V:$V,"") -> 45663 | H21: LAND | I21: 1 | J21: 1 | K21: 45666 | L21: 45668 | M21: YES | N21: =IFERROR(IF(tbl_die_ordering[[#This Row],[Design Approved Date]]<>"",L21-K21,""),"") -> 2 | O21: 45671 | P21: 45674 | Q21: 45671 | R21: 1300001099 | S21: PDTMC | T21: 45674 | U21: APT | W21: =_xlfn.LET( _xlpm.dieNo, tbl_die_ordering[[#This Row],[DIE NO]], _xlpm.orderNo, tbl_die_ordering[[#This Row],[Order No]], _xlpm.type, tbl_die_ordering[[#This Row],[TYPE]], _xlpm.designReceived, tbl_die_ordering[[#This Row],[Design Received Date]], _xlpm.designApproved, tbl_die_ordering[[#This Row],[Design Approved Date]], _xlpm.sim, tbl_die_ordering[[#This Row],[Sim]], _xlpm.prEntry, tbl_die_ordering[[#This Row],[PR Entry]], _xlpm.oracleEntry, tbl_die_ordering[[#This Row],[Oracle Entry]], _xlpm.ems, tbl_die_ordering[[#This Row],[Design saved to EMS FOLDER]], IF(_xlpm.dieNo = "", "", IF(_xlpm.orderNo = "", "PENDING FOR ORDERING", IF(_xlpm.type = "C", "CANCELLED", IF(_xlpm.type = "H", "HOLD", IF(_xlpm.designReceived = "", "AWAITING FOR DESIGN", IF(_xlpm.designApproved = "", IF(_xlpm.sim = "YES", "UNDER SIMULATION", "PENDING FOR DESIGN APPROVAL"), IF(_xlpm.prEntry = "", "PENDING FOR PR", IF(_xlpm.oracleEntry = "", "PENDING FOR ORACLE ENTRY", IF(_xlpm.ems = "", "PENDING FOR DESIGN TO EMS", "DONE"))))))))) ) -> DONE | X21: =IF(AND(tbl_die_ordering[[#This Row],[TYPE]]<>"C",tbl_die_ordering[[#This Row],[Design Approved Date]]<>""),tbl_die_ordering[[#This Row],[Design Approved Date]]-tbl_die_ordering[[#This Row],[Die Requested Date]],0) -> 5 | AB21: =_xlfn.XLOOKUP(_xlfn.TEXTJOIN("_",TRUE,tbl_die_ordering[[#This Row],[Supplier]],tbl_die_ordering[[#This Row],[DIE NO]]),[1]Tracker!$AQ:$AQ,[1]Tracker!$Y:$Y,"") -> M124 | AC21: =_xlfn.XLOOKUP(_xlfn.TEXTJOIN("_",TRUE,tbl_die_ordering[[#This Row],[Supplier]],tbl_die_ordering[[#This Row],[DIE NO]]),[1]Tracker!$AQ:$AQ,[1]Tracker!$AC:$AC,"") -> 45693 | AF21: =TEXT(tbl_die_ordering[[#This Row],[Die Requested Date]],"mmm") -> Jan | AG21: =_xlfn.TEXTJOIN("_",TRUE,tbl_die_ordering[[#This Row],[Supplier]],tbl_die_ordering[[#This Row],[DIE NO]]) -> PDTMC_051139-2501
A22: GEX 2 | B22: =_xlfn.XLOOKUP(_xlfn.TEXTJOIN("_",TRUE,tbl_die_ordering[[#This Row],[Supplier]],tbl_die_ordering[[#This Row],[DIE NO]]),[1]Tracker!$AQ:$AQ,[1]Tracker!$W:$W,"") -> 7614-25 | C22: 051140-2501 | D22: N | E22: 280X165 | F22: 45663 | G22: =_xlfn.XLOOKUP(_xlfn.TEXTJOIN("_",TRUE,tbl_die_ordering[[#This Row],[Supplier]],tbl_die_ordering[[#This Row],[DIE NO]]),[1]Tracker!$AQ:$AQ,[1]Tracker!$V:$V,"") -> 45663 | H22: LAND | I22: 1 | J22: 1 | K22: 45665 | L22: 45668 | M22: YES | N22: =IFERROR(IF(tbl_die_ordering[[#This Row],[Design Approved Date]]<>"",L22-K22,""),"") -> 3 | O22: 45671 | P22: 45674 | Q22: 45671 | R22: 1300001099 | S22: PDTMC | T22: 45674 | U22: APT | W22: =_xlfn.LET( _xlpm.dieNo, tbl_die_ordering[[#This Row],[DIE NO]], _xlpm.orderNo, tbl_die_ordering[[#This Row],[Order No]], _xlpm.type, tbl_die_ordering[[#This Row],[TYPE]], _xlpm.designReceived, tbl_die_ordering[[#This Row],[Design Received Date]], _xlpm.designApproved, tbl_die_ordering[[#This Row],[Design Approved Date]], _xlpm.sim, tbl_die_ordering[[#This Row],[Sim]], _xlpm.prEntry, tbl_die_ordering[[#This Row],[PR Entry]], _xlpm.oracleEntry, tbl_die_ordering[[#This Row],[Oracle Entry]], _xlpm.ems, tbl_die_ordering[[#This Row],[Design saved to EMS FOLDER]], IF(_xlpm.dieNo = "", "", IF(_xlpm.orderNo = "", "PENDING FOR ORDERING", IF(_xlpm.type = "C", "CANCELLED", IF(_xlpm.type = "H", "HOLD", IF(_xlpm.designReceived = "", "AWAITING FOR DESIGN", IF(_xlpm.designApproved = "", IF(_xlpm.sim = "YES", "UNDER SIMULATION", "PENDING FOR DESIGN APPROVAL"), IF(_xlpm.prEntry = "", "PENDING FOR PR", IF(_xlpm.oracleEntry = "", "PENDING FOR ORACLE ENTRY", IF(_xlpm.ems = "", "PENDING FOR DESIGN TO EMS", "DONE"))))))))) ) -> DONE | X22: =IF(AND(tbl_die_ordering[[#This Row],[TYPE]]<>"C",tbl_die_ordering[[#This Row],[Design Approved Date]]<>""),tbl_die_ordering[[#This Row],[Design Approved Date]]-tbl_die_ordering[[#This Row],[Die Requested Date]],0) -> 5 | AB22: =_xlfn.XLOOKUP(_xlfn.TEXTJOIN("_",TRUE,tbl_die_ordering[[#This Row],[Supplier]],tbl_die_ordering[[#This Row],[DIE NO]]),[1]Tracker!$AQ:$AQ,[1]Tracker!$Y:$Y,"") -> M124 | AC22: =_xlfn.XLOOKUP(_xlfn.TEXTJOIN("_",TRUE,tbl_die_ordering[[#This Row],[Supplier]],tbl_die_ordering[[#This Row],[DIE NO]]),[1]Tracker!$AQ:$AQ,[1]Tracker!$AC:$AC,"") -> 45693 | AF22: =TEXT(tbl_die_ordering[[#This Row],[Die Requested Date]],"mmm") -> Jan | AG22: =_xlfn.TEXTJOIN("_",TRUE,tbl_die_ordering[[#This Row],[Supplier]],tbl_die_ordering[[#This Row],[DIE NO]]) -> PDTMC_051140-2501
A23: GEX 2 | B23: =_xlfn.XLOOKUP(_xlfn.TEXTJOIN("_",TRUE,tbl_die_ordering[[#This Row],[Supplier]],tbl_die_ordering[[#This Row],[DIE NO]]),[1]Tracker!$AQ:$AQ,[1]Tracker!$W:$W,"") -> 7615-25 | C23: 030188-2501 | D23: N | E23: 250X160 | F23: 45663 | G23: =_xlfn.XLOOKUP(_xlfn.TEXTJOIN("_",TRUE,tbl_die_ordering[[#This Row],[Supplier]],tbl_die_ordering[[#This Row],[DIE NO]]),[1]Tracker!$AQ:$AQ,[1]Tracker!$V:$V,"") -> 45663 | H23: AIR | I23: 1 | J23: 1 | K23: 45664 | L23: 45668 | N23: =IFERROR(IF(tbl_die_ordering[[#This Row],[Design Approved Date]]<>"",L23-K23,""),"") -> 4 | O23: 45671 | P23: 45674 | Q23: 45671 | R23: 1300001099 | S23: EKSTEK | T23: 45675 | U23: M A N S WOODSTOCK GENERAL TRADING L.L.C | W23: =_xlfn.LET( _xlpm.dieNo, tbl_die_ordering[[#This Row],[DIE NO]], _xlpm.orderNo, tbl_die_ordering[[#This Row],[Order No]], _xlpm.type, tbl_die_ordering[[#This Row],[TYPE]], _xlpm.designReceived, tbl_die_ordering[[#This Row],[Design Received Date]], _xlpm.designApproved, tbl_die_ordering[[#This Row],[Design Approved Date]], _xlpm.sim, tbl_die_ordering[[#This Row],[Sim]], _xlpm.prEntry, tbl_die_ordering[[#This Row],[PR Entry]], _xlpm.oracleEntry, tbl_die_ordering[[#This Row],[Oracle Entry]], _xlpm.ems, tbl_die_ordering[[#This Row],[Design saved to EMS FOLDER]], IF(_xlpm.dieNo = "", "", IF(_xlpm.orderNo = "", "PENDING FOR ORDERING", IF(_xlpm.type = "C", "CANCELLED", IF(_xlpm.type = "H", "HOLD", IF(_xlpm.designReceived = "", "AWAITING FOR DESIGN", IF(_xlpm.designApproved = "", IF(_xlpm.sim = "YES", "UNDER SIMULATION", "PENDING FOR DESIGN APPROVAL"), IF(_xlpm.prEntry = "", "PENDING FOR PR", IF(_xlpm.oracleEntry = "", "PENDING FOR ORACLE ENTRY", IF(_xlpm.ems = "", "PENDING FOR DESIGN TO EMS", "DONE"))))))))) ) -> DONE | X23: =IF(AND(tbl_die_ordering[[#This Row],[TYPE]]<>"C",tbl_die_ordering[[#This Row],[Design Approved Date]]<>""),tbl_die_ordering[[#This Row],[Design Approved Date]]-tbl_die_ordering[[#This Row],[Die Requested Date]],0) -> 5 | AB23: =_xlfn.XLOOKUP(_xlfn.TEXTJOIN("_",TRUE,tbl_die_ordering[[#This Row],[Supplier]],tbl_die_ordering[[#This Row],[DIE NO]]),[1]Tracker!$AQ:$AQ,[1]Tracker!$Y:$Y,"") -> M083 | AC23: =_xlfn.XLOOKUP(_xlfn.TEXTJOIN("_",TRUE,tbl_die_ordering[[#This Row],[Supplier]],tbl_die_ordering[[#This Row],[DIE NO]]),[1]Tracker!$AQ:$AQ,[1]Tracker!$AC:$AC,"") -> 45684 | AF23: =TEXT(tbl_die_ordering[[#This Row],[Die Requested Date]],"mmm") -> Jan | AG23: =_xlfn.TEXTJOIN("_",TRUE,tbl_die_ordering[[#This Row],[Supplier]],tbl_die_ordering[[#This Row],[DIE NO]]) -> EKSTEK_030188-2501
A24: GEX 2 | B24: =_xlfn.XLOOKUP(_xlfn.TEXTJOIN("_",TRUE,tbl_die_ordering[[#This Row],[Supplier]],tbl_die_ordering[[#This Row],[DIE NO]]),[1]Tracker!$AQ:$AQ,[1]Tracker!$W:$W,"") -> 7615-25 | C24: 030189-2501 | D24: N | E24: 280X160 | F24: 45663 | G24: =_xlfn.XLOOKUP(_xlfn.TEXTJOIN("_",TRUE,tbl_die_ordering[[#This Row],[Supplier]],tbl_die_ordering[[#This Row],[DIE NO]]),[1]Tracker!$AQ:$AQ,[1]Tracker!$V:$V,"") -> 45663 | H24: AIR | I24: 2 | J24: 2 | K24: 45664 | L24: 45668 | N24: =IFERROR(IF(tbl_die_ordering[[#This Row],[Design Approved Date]]<>"",L24-K24,""),"") -> 4 | O24: 45671 | P24: 45674 | Q24: 45671 | R24: 1300001099 | S24: EKSTEK | T24: 45674 | U24: M A N S WOODSTOCK GENERAL TRADING L.L.C | W24: =_xlfn.LET( _xlpm.dieNo, tbl_die_ordering[[#This Row],[DIE NO]], _xlpm.orderNo, tbl_die_ordering[[#This Row],[Order No]], _xlpm.type, tbl_die_ordering[[#This Row],[TYPE]], _xlpm.designReceived, tbl_die_ordering[[#This Row],[Design Received Date]], _xlpm.designApproved, tbl_die_ordering[[#This Row],[Design Approved Date]], _xlpm.sim, tbl_die_ordering[[#This Row],[Sim]], _xlpm.prEntry, tbl_die_ordering[[#This Row],[PR Entry]], _xlpm.oracleEntry, tbl_die_ordering[[#This Row],[Oracle Entry]], _xlpm.ems, tbl_die_ordering[[#This Row],[Design saved to EMS FOLDER]], IF(_xlpm.dieNo = "", "", IF(_xlpm.orderNo = "", "PENDING FOR ORDERING", IF(_xlpm.type = "C", "CANCELLED", IF(_xlpm.type = "H", "HOLD", IF(_xlpm.designReceived = "", "AWAITING FOR DESIGN", IF(_xlpm.designApproved = "", IF(_xlpm.sim = "YES", "UNDER SIMULATION", "PENDING FOR DESIGN APPROVAL"), IF(_xlpm.prEntry = "", "PENDING FOR PR", IF(_xlpm.oracleEntry = "", "PENDING FOR ORACLE ENTRY", IF(_xlpm.ems = "", "PENDING FOR DESIGN TO EMS", "DONE"))))))))) ) -> DONE | X24: =IF(AND(tbl_die_ordering[[#This Row],[TYPE]]<>"C",tbl_die_ordering[[#This Row],[Design Approved Date]]<>""),tbl_die_ordering[[#This Row],[Design Approved Date]]-tbl_die_ordering[[#This Row],[Die Requested Date]],0) -> 5 | AB24: =_xlfn.XLOOKUP(_xlfn.TEXTJOIN("_",TRUE,tbl_die_ordering[[#This Row],[Supplier]],tbl_die_ordering[[#This Row],[DIE NO]]),[1]Tracker!$AQ:$AQ,[1]Tracker!$Y:$Y,"") -> M083 | AC24: =_xlfn.XLOOKUP(_xlfn.TEXTJOIN("_",TRUE,tbl_die_ordering[[#This Row],[Supplier]],tbl_die_ordering[[#This Row],[DIE NO]]),[1]Tracker!$AQ:$AQ,[1]Tracker!$AC:$AC,"") -> 45684 | AF24: =TEXT(tbl_die_ordering[[#This Row],[Die Requested Date]],"mmm") -> Jan | AG24: =_xlfn.TEXTJOIN("_",TRUE,tbl_die_ordering[[#This Row],[Supplier]],tbl_die_ordering[[#This Row],[DIE NO]]) -> EKSTEK_030189-2501
A25: GEX 1 | B25: =_xlfn.XLOOKUP(_xlfn.TEXTJOIN("_",TRUE,tbl_die_ordering[[#This Row],[Supplier]],tbl_die_ordering[[#This Row],[DIE NO]]),[1]Tracker!$AQ:$AQ,[1]Tracker!$W:$W,"") -> 7616-25 | C25: 30190-601 | D25: N | E25: 550x250 | F25: 45666 | G25: =_xlfn.XLOOKUP(_xlfn.TEXTJOIN("_",TRUE,tbl_die_ordering[[#This Row],[Supplier]],tbl_die_ordering[[#This Row],[DIE NO]]),[1]Tracker!$AQ:$AQ,[1]Tracker!$V:$V,"") -> 45666 | H25: AIR | I25: 1 | J25: 1 | K25: 45666 | L25: 45668 | N25: =IFERROR(IF(tbl_die_ordering[[#This Row],[Design Approved Date]]<>"",L25-K25,""),"") -> 2 | O25: 45670 | P25: 45670 | Q25: 45670 | R25: 112500175 | S25: COMPES | T25: 45670 | U25: Alqusair | W25: =_xlfn.LET( _xlpm.dieNo, tbl_die_ordering[[#This Row],[DIE NO]], _xlpm.orderNo, tbl_die_ordering[[#This Row],[Order No]], _xlpm.type, tbl_die_ordering[[#This Row],[TYPE]], _xlpm.designReceived, tbl_die_ordering[[#This Row],[Design Received Date]], _xlpm.designApproved, tbl_die_ordering[[#This Row],[Design Approved Date]], _xlpm.sim, tbl_die_ordering[[#This Row],[Sim]], _xlpm.prEntry, tbl_die_ordering[[#This Row],[PR Entry]], _xlpm.oracleEntry, tbl_die_ordering[[#This Row],[Oracle Entry]], _xlpm.ems, tbl_die_ordering[[#This Row],[Design saved to EMS FOLDER]], IF(_xlpm.dieNo = "", "", IF(_xlpm.orderNo = "", "PENDING FOR ORDERING", IF(_xlpm.type = "C", "CANCELLED", IF(_xlpm.type = "H", "HOLD", IF(_xlpm.designReceived = "", "AWAITING FOR DESIGN", IF(_xlpm.designApproved = "", IF(_xlpm.sim = "YES", "UNDER SIMULATION", "PENDING FOR DESIGN APPROVAL"), IF(_xlpm.prEntry = "", "PENDING FOR PR", IF(_xlpm.oracleEntry = "", "PENDING FOR ORACLE ENTRY", IF(_xlpm.ems = "", "PENDING FOR DESIGN TO EMS", "DONE"))))))))) ) -> DONE | X25: =IF(AND(tbl_die_ordering[[#This Row],[TYPE]]<>"C",tbl_die_ordering[[#This Row],[Design Approved Date]]<>""),tbl_die_ordering[[#This Row],[Design Approved Date]]-tbl_die_ordering[[#This Row],[Die Requested Date]],0) -> 2 | AA25: MILL | AB25: =_xlfn.XLOOKUP(_xlfn.TEXTJOIN("_",TRUE,tbl_die_ordering[[#This Row],[Supplier]],tbl_die_ordering[[#This Row],[DIE NO]]),[1]Tracker!$AQ:$AQ,[1]Tracker!$Y:$Y,"") -> 142500494 | AC25: =_xlfn.XLOOKUP(_xlfn.TEXTJOIN("_",TRUE,tbl_die_ordering[[#This Row],[Supplier]],tbl_die_ordering[[#This Row],[DIE NO]]),[1]Tracker!$AQ:$AQ,[1]Tracker!$AC:$AC,"") -> 45683 | AF25: =TEXT(tbl_die_ordering[[#This Row],[Die Requested Date]],"mmm") -> Jan | AG25: =_xlfn.TEXTJOIN("_",TRUE,tbl_die_ordering[[#This Row],[Supplier]],tbl_die_ordering[[#This Row],[DIE NO]]) -> COMPES_30190-601
A26: GEX 1 | B26: =_xlfn.XLOOKUP(_xlfn.TEXTJOIN("_",TRUE,tbl_die_ordering[[#This Row],[Supplier]],tbl_die_ordering[[#This Row],[DIE NO]]),[1]Tracker!$AQ:$AQ,[1]Tracker!$W:$W,"") -> 7616-25 | C26: 30191-601 | D26: N | E26: 550x250 | F26: 45666 | G26: =_xlfn.XLOOKUP(_xlfn.TEXTJOIN("_",TRUE,tbl_die_ordering[[#This Row],[Supplier]],tbl_die_ordering[[#This Row],[DIE NO]]),[1]Tracker!$AQ:$AQ,[1]Tracker!$V:$V,"") -> 45666 | H26: AIR | I26: 1 | J26: 3 | K26: 45666 | L26: 45668 | N26: =IFERROR(IF(tbl_die_ordering[[#This Row],[Design Approved Date]]<>"",L26-K26,""),"") -> 2 | O26: 45670 | P26: 45670 | Q26: 45670 | R26: 112500175 | S26: COMPES | T26: 45670 | U26: Alqusair | W26: =_xlfn.LET( _xlpm.dieNo, tbl_die_ordering[[#This Row],[DIE NO]], _xlpm.orderNo, tbl_die_ordering[[#This Row],[Order No]], _xlpm.type, tbl_die_ordering[[#This Row],[TYPE]], _xlpm.designReceived, tbl_die_ordering[[#This Row],[Design Received Date]], _xlpm.designApproved, tbl_die_ordering[[#This Row],[Design Approved Date]], _xlpm.sim, tbl_die_ordering[[#This Row],[Sim]], _xlpm.prEntry, tbl_die_ordering[[#This Row],[PR Entry]], _xlpm.oracleEntry, tbl_die_ordering[[#This Row],[Oracle Entry]], _xlpm.ems, tbl_die_ordering[[#This Row],[Design saved to EMS FOLDER]], IF(_xlpm.dieNo = "", "", IF(_xlpm.orderNo = "", "PENDING FOR ORDERING", IF(_xlpm.type = "C", "CANCELLED", IF(_xlpm.type = "H", "HOLD", IF(_xlpm.designReceived = "", "AWAITING FOR DESIGN", IF(_xlpm.designApproved = "", IF(_xlpm.sim = "YES", "UNDER SIMULATION", "PENDING FOR DESIGN APPROVAL"), IF(_xlpm.prEntry = "", "PENDING FOR PR", IF(_xlpm.oracleEntry = "", "PENDING FOR ORACLE ENTRY", IF(_xlpm.ems = "", "PENDING FOR DESIGN TO EMS", "DONE"))))))))) ) -> DONE | X26: =IF(AND(tbl_die_ordering[[#This Row],[TYPE]]<>"C",tbl_die_ordering[[#This Row],[Design Approved Date]]<>""),tbl_die_ordering[[#This Row],[Design Approved Date]]-tbl_die_ordering[[#This Row],[Die Requested Date]],0) -> 2 | AA26: MILL | AB26: =_xlfn.XLOOKUP(_xlfn.TEXTJOIN("_",TRUE,tbl_die_ordering[[#This Row],[Supplier]],tbl_die_ordering[[#This Row],[DIE NO]]),[1]Tracker!$AQ:$AQ,[1]Tracker!$Y:$Y,"") -> 142500494 | AC26: =_xlfn.XLOOKUP(_xlfn.TEXTJOIN("_",TRUE,tbl_die_ordering[[#This Row],[Supplier]],tbl_die_ordering[[#This Row],[DIE NO]]),[1]Tracker!$AQ:$AQ,[1]Tracker!$AC:$AC,"") -> 45683 | AF26: =TEXT(tbl_die_ordering[[#This Row],[Die Requested Date]],"mmm") -> Jan | AG26: =_xlfn.TEXTJOIN("_",TRUE,tbl_die_ordering[[#This Row],[Supplier]],tbl_die_ordering[[#This Row],[DIE NO]]) -> COMPES_30191-601
A27: GEX 1 | B27: =_xlfn.XLOOKUP(_xlfn.TEXTJOIN("_",TRUE,tbl_die_ordering[[#This Row],[Supplier]],tbl_die_ordering[[#This Row],[DIE NO]]),[1]Tracker!$AQ:$AQ,[1]Tracker!$W:$W,"") -> 7617-25 | C27: 27789-501 | D27: N | E27: 250X160 | F27: 45666 | G27: =_xlfn.XLOOKUP(_xlfn.TEXTJOIN("_",TRUE,tbl_die_ordering[[#This Row],[Supplier]],tbl_die_ordering[[#This Row],[DIE NO]]),[1]Tracker!$AQ:$AQ,[1]Tracker!$V:$V,"") -> 45666 | H27: LAND | I27: 0 | J27: 0 | K27: 45668 | L27: 45668 | N27: =IFERROR(IF(tbl_die_ordering[[#This Row],[Design Approved Date]]<>"",L27-K27,""),"") -> 0 | O27: 45670 | P27: 45670 | Q27: 45670 | R27: 112500175 | S27: PDTMC | T27: 45670 | U27: Insulux Metal | W27: =_xlfn.LET( _xlpm.dieNo, tbl_die_ordering[[#This Row],[DIE NO]], _xlpm.orderNo, tbl_die_ordering[[#This Row],[Order No]], _xlpm.type, tbl_die_ordering[[#This Row],[TYPE]], _xlpm.designReceived, tbl_die_ordering[[#This Row],[Design Received Date]], _xlpm.designApproved, tbl_die_ordering[[#This Row],[Design Approved Date]], _xlpm.sim, tbl_die_ordering[[#This Row],[Sim]], _xlpm.prEntry, tbl_die_ordering[[#This Row],[PR Entry]], _xlpm.oracleEntry, tbl_die_ordering[[#This Row],[Oracle Entry]], _xlpm.ems, tbl_die_ordering[[#This Row],[Design saved to EMS FOLDER]], IF(_xlpm.dieNo = "", "", IF(_xlpm.orderNo = "", "PENDING FOR ORDERING", IF(_xlpm.type = "C", "CANCELLED", IF(_xlpm.type = "H", "HOLD", IF(_xlpm.designReceived = "", "AWAITING FOR DESIGN", IF(_xlpm.designApproved = "", IF(_xlpm.sim = "YES", "UNDER SIMULATION", "PENDING FOR DESIGN APPROVAL"), IF(_xlpm.prEntry = "", "PENDING FOR PR", IF(_xlpm.oracleEntry = "", "PENDING FOR ORACLE ENTRY", IF(_xlpm.ems = "", "PENDING FOR DESIGN TO EMS", "DONE"))))))))) ) -> DONE | X27: =IF(AND(tbl_die_ordering[[#This Row],[TYPE]]<>"C",tbl_die_ordering[[#This Row],[Design Approved Date]]<>""),tbl_die_ordering[[#This Row],[Design Approved Date]]-tbl_die_ordering[[#This Row],[Die Requested Date]],0) -> 2 | AA27: MILL,, POWDER, ANODIZING | AB27: =_xlfn.XLOOKUP(_xlfn.TEXTJOIN("_",TRUE,tbl_die_ordering[[#This Row],[Supplier]],tbl_die_ordering[[#This Row],[DIE NO]]),[1]Tracker!$AQ:$AQ,[1]Tracker!$Y:$Y,"") -> 142500459 | AC27: =_xlfn.XLOOKUP(_xlfn.TEXTJOIN("_",TRUE,tbl_die_ordering[[#This Row],[Supplier]],tbl_die_ordering[[#This Row],[DIE NO]]),[1]Tracker!$AQ:$AQ,[1]Tracker!$AC:$AC,"") -> 45680 | AF27: =TEXT(tbl_die_ordering[[#This Row],[Die Requested Date]],"mmm") -> Jan | AG27: =_xlfn.TEXTJOIN("_",TRUE,tbl_die_ordering[[#This Row],[Supplier]],tbl_die_ordering[[#This Row],[DIE NO]]) -> PDTMC_27789-501
A28: GEX 1 | B28: =_xlfn.XLOOKUP(_xlfn.TEXTJOIN("_",TRUE,tbl_die_ordering[[#This Row],[Supplier]],tbl_die_ordering[[#This Row],[DIE NO]]),[1]Tracker!$AQ:$AQ,[1]Tracker!$W:$W,"") -> 7617-25 | C28: 30195-501 | D28: N | E28: 250X160 | F28: 45666 | G28: =_xlfn.XLOOKUP(_xlfn.TEXTJOIN("_",TRUE,tbl_die_ordering[[#This Row],[Supplier]],tbl_die_ordering[[#This Row],[DIE NO]]),[1]Tracker!$AQ:$AQ,[1]Tracker!$V:$V,"") -> 45666 | H28: LAND | I28: 1 | J28: 4 | K28: 45667 | L28: 45668 | N28: =IFERROR(IF(tbl_die_ordering[[#This Row],[Design Approved Date]]<>"",L28-K28,""),"") -> 1 | O28: 45670 | P28: 45670 | Q28: 45670 | R28: 112500175 | S28: PDTMC | T28: 45670 | U28: Insulux Metal | W28: =_xlfn.LET( _xlpm.dieNo, tbl_die_ordering[[#This Row],[DIE NO]], _xlpm.orderNo, tbl_die_ordering[[#This Row],[Order No]], _xlpm.type, tbl_die_ordering[[#This Row],[TYPE]], _xlpm.designReceived, tbl_die_ordering[[#This Row],[Design Received Date]], _xlpm.designApproved, tbl_die_ordering[[#This Row],[Design Approved Date]], _xlpm.sim, tbl_die_ordering[[#This Row],[Sim]], _xlpm.prEntry, tbl_die_ordering[[#This Row],[PR Entry]], _xlpm.oracleEntry, tbl_die_ordering[[#This Row],[Oracle Entry]], _xlpm.ems, tbl_die_ordering[[#This Row],[Design saved to EMS FOLDER]], IF(_xlpm.dieNo = "", "", IF(_xlpm.orderNo = "", "PENDING FOR ORDERING", IF(_xlpm.type = "C", "CANCELLED", IF(_xlpm.type = "H", "HOLD", IF(_xlpm.designReceived = "", "AWAITING FOR DESIGN", IF(_xlpm.designApproved = "", IF(_xlpm.sim = "YES", "UNDER SIMULATION", "PENDING FOR DESIGN APPROVAL"), IF(_xlpm.prEntry = "", "PENDING FOR PR", IF(_xlpm.oracleEntry = "", "PENDING FOR ORACLE ENTRY", IF(_xlpm.ems = "", "PENDING FOR DESIGN TO EMS", "DONE"))))))))) ) -> DONE | X28: =IF(AND(tbl_die_ordering[[#This Row],[TYPE]]<>"C",tbl_die_ordering[[#This Row],[Design Approved Date]]<>""),tbl_die_ordering[[#This Row],[Design Approved Date]]-tbl_die_ordering[[#This Row],[Die Requested Date]],0) -> 2 | AA28: MILL,, POWDER, ANODIZING | AB28: =_xlfn.XLOOKUP(_xlfn.TEXTJOIN("_",TRUE,tbl_die_ordering[[#This Row],[Supplier]],tbl_die_ordering[[#This Row],[DIE NO]]),[1]Tracker!$AQ:$AQ,[1]Tracker!$Y:$Y,"") -> 142500459 | AC28: =_xlfn.XLOOKUP(_xlfn.TEXTJOIN("_",TRUE,tbl_die_ordering[[#This Row],[Supplier]],tbl_die_ordering[[#This Row],[DIE NO]]),[1]Tracker!$AQ:$AQ,[1]Tracker!$AC:$AC,"") -> 45680 | AF28: =TEXT(tbl_die_ordering[[#This Row],[Die Requested Date]],"mmm") -> Jan | AG28: =_xlfn.TEXTJOIN("_",TRUE,tbl_die_ordering[[#This Row],[Supplier]],tbl_die_ordering[[#This Row],[DIE NO]]) -> PDTMC_30195-501
A29: GEX 1 | B29: =_xlfn.XLOOKUP(_xlfn.TEXTJOIN("_",TRUE,tbl_die_ordering[[#This Row],[Supplier]],tbl_die_ordering[[#This Row],[DIE NO]]),[1]Tracker!$AQ:$AQ,[1]Tracker!$W:$W,"") -> 7617-25 | C29: 30192-201 | D29: N | E29: 355X200 | F29: 45666 | G29: =_xlfn.XLOOKUP(_xlfn.TEXTJOIN("_",TRUE,tbl_die_ordering[[#This Row],[Supplier]],tbl_die_ordering[[#This Row],[DIE NO]]),[1]Tracker!$AQ:$AQ,[1]Tracker!$V:$V,"") -> 45666 | H29: LAND | I29: 1 | J29: 1 | K29: 45670 | L29: 45672 | N29: =IFERROR(IF(tbl_die_ordering[[#This Row],[Design Approved Date]]<>"",L29-K29,""),"") -> 2 | O29: 45673 | P29: 45675 | Q29: 45673 | R29: 112500258 | S29: PDTMC | T29: 45673 | U29: Insulux Metal | W29: =_xlfn.LET( _xlpm.dieNo, tbl_die_ordering[[#This Row],[DIE NO]], _xlpm.orderNo, tbl_die_ordering[[#This Row],[Order No]], _xlpm.type, tbl_die_ordering[[#This Row],[TYPE]], _xlpm.designReceived, tbl_die_ordering[[#This Row],[Design Received Date]], _xlpm.designApproved, tbl_die_ordering[[#This Row],[Design Approved Date]], _xlpm.sim, tbl_die_ordering[[#This Row],[Sim]], _xlpm.prEntry, tbl_die_ordering[[#This Row],[PR Entry]], _xlpm.oracleEntry, tbl_die_ordering[[#This Row],[Oracle Entry]], _xlpm.ems, tbl_die_ordering[[#This Row],[Design saved to EMS FOLDER]], IF(_xlpm.dieNo = "", "", IF(_xlpm.orderNo = "", "PENDING FOR ORDERING", IF(_xlpm.type = "C", "CANCELLED", IF(_xlpm.type = "H", "HOLD", IF(_xlpm.designReceived = "", "AWAITING FOR DESIGN", IF(_xlpm.designApproved = "", IF(_xlpm.sim = "YES", "UNDER SIMULATION", "PENDING FOR DESIGN APPROVAL"), IF(_xlpm.prEntry = "", "PENDING FOR PR", IF(_xlpm.oracleEntry = "", "PENDING FOR ORACLE ENTRY", IF(_xlpm.ems = "", "PENDING FOR DESIGN TO EMS", "DONE"))))))))) ) -> DONE | X29: =IF(AND(tbl_die_ordering[[#This Row],[TYPE]]<>"C",tbl_die_ordering[[#This Row],[Design Approved Date]]<>""),tbl_die_ordering[[#This Row],[Design Approved Date]]-tbl_die_ordering[[#This Row],[Die Requested Date]],0) -> 6 | AA29: MILL,, POWDER, ANODIZING | AB29: =_xlfn.XLOOKUP(_xlfn.TEXTJOIN("_",TRUE,tbl_die_ordering[[#This Row],[Supplier]],tbl_die_ordering[[#This Row],[DIE NO]]),[1]Tracker!$AQ:$AQ,[1]Tracker!$Y:$Y,"") -> 142500534 | AC29: =_xlfn.XLOOKUP(_xlfn.TEXTJOIN("_",TRUE,tbl_die_ordering[[#This Row],[Supplier]],tbl_die_ordering[[#This Row],[DIE NO]]),[1]Tracker!$AQ:$AQ,[1]Tracker!$AC:$AC,"") -> 45683 | AF29: =TEXT(tbl_die_ordering[[#This Row],[Die Requested Date]],"mmm") -> Jan | AG29: =_xlfn.TEXTJOIN("_",TRUE,tbl_die_ordering[[#This Row],[Supplier]],tbl_die_ordering[[#This Row],[DIE NO]]) -> PDTMC_30192-201
A30: GEX 1 | B30: =_xlfn.XLOOKUP(_xlfn.TEXTJOIN("_",TRUE,tbl_die_ordering[[#This Row],[Supplier]],tbl_die_ordering[[#This Row],[DIE NO]]),[1]Tracker!$AQ:$AQ,[1]Tracker!$W:$W,"") -> 7617-25 | C30: 30196-201 | D30: N | E30: 320X160 | F30: 45666 | G30: =_xlfn.XLOOKUP(_xlfn.TEXTJOIN("_",TRUE,tbl_die_ordering[[#This Row],[Supplier]],tbl_die_ordering[[#This Row],[DIE NO]]),[1]Tracker!$AQ:$AQ,[1]Tracker!$V:$V,"") -> 45666 | H30: LAND | I30: 1 | J30: 2 | K30: 45670 | L30: 45673 | M30: YES | N30: =IFERROR(IF(tbl_die_ordering[[#This Row],[Design Approved Date]]<>"",L30-K30,""),"") -> 3 | O30: 45673 | P30: 45675 | Q30: 45673 | R30: 112500258 | S30: PDTMC | T30: 45673 | U30: Insulux Metal | W30: =_xlfn.LET( _xlpm.dieNo, tbl_die_ordering[[#This Row],[DIE NO]], _xlpm.orderNo, tbl_die_ordering[[#This Row],[Order No]], _xlpm.type, tbl_die_ordering[[#This Row],[TYPE]], _xlpm.designReceived, tbl_die_ordering[[#This Row],[Design Received Date]], _xlpm.designApproved, tbl_die_ordering[[#This Row],[Design Approved Date]], _xlpm.sim, tbl_die_ordering[[#This Row],[Sim]], _xlpm.prEntry, tbl_die_ordering[[#This Row],[PR Entry]], _xlpm.oracleEntry, tbl_die_ordering[[#This Row],[Oracle Entry]], _xlpm.ems, tbl_die_ordering[[#This Row],[Design saved to EMS FOLDER]], IF(_xlpm.dieNo = "", "", IF(_xlpm.orderNo = "", "PENDING FOR ORDERING", IF(_xlpm.type = "C", "CANCELLED", IF(_xlpm.type = "H", "HOLD", IF(_xlpm.designReceived = "", "AWAITING FOR DESIGN", IF(_xlpm.designApproved = "", IF(_xlpm.sim = "YES", "UNDER SIMULATION", "PENDING FOR DESIGN APPROVAL"), IF(_xlpm.prEntry = "", "PENDING FOR PR", IF(_xlpm.oracleEntry = "", "PENDING FOR ORACLE ENTRY", IF(_xlpm.ems = "", "PENDING FOR DESIGN TO EMS", "DONE"))))))))) ) -> DONE | X30: =IF(AND(tbl_die_ordering[[#This Row],[TYPE]]<>"C",tbl_die_ordering[[#This Row],[Design Approved Date]]<>""),tbl_die_ordering[[#This Row],[Design Approved Date]]-tbl_die_ordering[[#This Row],[Die Requested Date]],0) -> 7 | AA30: MILL,, POWDER, ANODIZING | AB30: =_xlfn.XLOOKUP(_xlfn.TEXTJOIN("_",TRUE,tbl_die_ordering[[#This Row],[Supplier]],tbl_die_ordering[[#This Row],[DIE NO]]),[1]Tracker!$AQ:$AQ,[1]Tracker!$Y:$Y,"") -> 142500534 | AC30: =_xlfn.XLOOKUP(_xlfn.TEXTJOIN("_",TRUE,tbl_die_ordering[[#This Row],[Supplier]],tbl_die_ordering[[#This Row],[DIE NO]]),[1]Tracker!$AQ:$AQ,[1]Tracker!$AC:$AC,"") -> 45683 | AF30: =TEXT(tbl_die_ordering[[#This Row],[Die Requested Date]],"mmm") -> Jan | AG30: =_xlfn.TEXTJOIN("_",TRUE,tbl_die_ordering[[#This Row],[Supplier]],tbl_die_ordering[[#This Row],[DIE NO]]) -> PDTMC_30196-201
A31: GEX 1 | B31: =_xlfn.XLOOKUP(_xlfn.TEXTJOIN("_",TRUE,tbl_die_ordering[[#This Row],[Supplier]],tbl_die_ordering[[#This Row],[DIE NO]]),[1]Tracker!$AQ:$AQ,[1]Tracker!$W:$W,"") -> 7617-25 | C31: 30197-201 | D31: N | E31: 320X160 | F31: 45666 | G31: =_xlfn.XLOOKUP(_xlfn.TEXTJOIN("_",TRUE,tbl_die_ordering[[#This Row],[Supplier]],tbl_die_ordering[[#This Row],[DIE NO]]),[1]Tracker!$AQ:$AQ,[1]Tracker!$V:$V,"") -> 45666 | H31: LAND | I31: 1 | J31: 1 | K31: 45670 | L31: 45672 | N31: =IFERROR(IF(tbl_die_ordering[[#This Row],[Design Approved Date]]<>"",L31-K31,""),"") -> 2 | O31: 45673 | P31: 45675 | Q31: 45673 | R31: 112500258 | S31: PDTMC | T31: 45673 | U31: Insulux Metal | W31: =_xlfn.LET( _xlpm.dieNo, tbl_die_ordering[[#This Row],[DIE NO]], _xlpm.orderNo, tbl_die_ordering[[#This Row],[Order No]], _xlpm.type, tbl_die_ordering[[#This Row],[TYPE]], _xlpm.designReceived, tbl_die_ordering[[#This Row],[Design Received Date]], _xlpm.designApproved, tbl_die_ordering[[#This Row],[Design Approved Date]], _xlpm.sim, tbl_die_ordering[[#This Row],[Sim]], _xlpm.prEntry, tbl_die_ordering[[#This Row],[PR Entry]], _xlpm.oracleEntry, tbl_die_ordering[[#This Row],[Oracle Entry]], _xlpm.ems, tbl_die_ordering[[#This Row],[Design saved to EMS FOLDER]], IF(_xlpm.dieNo = "", "", IF(_xlpm.orderNo = "", "PENDING FOR ORDERING", IF(_xlpm.type = "C", "CANCELLED", IF(_xlpm.type = "H", "HOLD", IF(_xlpm.designReceived = "", "AWAITING FOR DESIGN", IF(_xlpm.designApproved = "", IF(_xlpm.sim = "YES", "UNDER SIMULATION", "PENDING FOR DESIGN APPROVAL"), IF(_xlpm.prEntry = "", "PENDING FOR PR", IF(_xlpm.oracleEntry = "", "PENDING FOR ORACLE ENTRY", IF(_xlpm.ems = "", "PENDING FOR DESIGN TO EMS", "DONE"))))))))) ) -> DONE | X31: =IF(AND(tbl_die_ordering[[#This Row],[TYPE]]<>"C",tbl_die_ordering[[#This Row],[Design Approved Date]]<>""),tbl_die_ordering[[#This Row],[Design Approved Date]]-tbl_die_ordering[[#This Row],[Die Requested Date]],0) -> 6 | AA31: MILL,, POWDER, ANODIZING | AB31: =_xlfn.XLOOKUP(_xlfn.TEXTJOIN("_",TRUE,tbl_die_ordering[[#This Row],[Supplier]],tbl_die_ordering[[#This Row],[DIE NO]]),[1]Tracker!$AQ:$AQ,[1]Tracker!$Y:$Y,"") -> 142500534 | AC31: =_xlfn.XLOOKUP(_xlfn.TEXTJOIN("_",TRUE,tbl_die_ordering[[#This Row],[Supplier]],tbl_die_ordering[[#This Row],[DIE NO]]),[1]Tracker!$AQ:$AQ,[1]Tracker!$AC:$AC,"") -> 45683 | AF31: =TEXT(tbl_die_ordering[[#This Row],[Die Requested Date]],"mmm") -> Jan | AG31: =_xlfn.TEXTJOIN("_",TRUE,tbl_die_ordering[[#This Row],[Supplier]],tbl_die_ordering[[#This Row],[DIE NO]]) -> PDTMC_30197-201
A32: GEX 1 | B32: =_xlfn.XLOOKUP(_xlfn.TEXTJOIN("_",TRUE,tbl_die_ordering[[#This Row],[Supplier]],tbl_die_ordering[[#This Row],[DIE NO]]),[1]Tracker!$AQ:$AQ,[1]Tracker!$W:$W,"") -> 7617-25 | C32: 30193-601 | D32: N | E32: 355X200 | F32: 45666 | G32: =_xlfn.XLOOKUP(_xlfn.TEXTJOIN("_",TRUE,tbl_die_ordering[[#This Row],[Supplier]],tbl_die_ordering[[#This Row],[DIE NO]]),[1]Tracker!$AQ:$AQ,[1]Tracker!$V:$V,"") -> 45666 | H32: LAND | I32: 1 | J32: 2 | K32: 45670 | L32: 45673 | M32: YES | N32: =IFERROR(IF(tbl_die_ordering[[#This Row],[Design Approved Date]]<>"",L32-K32,""),"") -> 3 | O32: 45675 | P32: 45675 | Q32: 45675 | R32: 112500275 | S32: PDTMC | T32: 45675 | U32: Insulux Metal | W32: =_xlfn.LET( _xlpm.dieNo, tbl_die_ordering[[#This Row],[DIE NO]], _xlpm.orderNo, tbl_die_ordering[[#This Row],[Order No]], _xlpm.type, tbl_die_ordering[[#This Row],[TYPE]], _xlpm.designReceived, tbl_die_ordering[[#This Row],[Design Received Date]], _xlpm.designApproved, tbl_die_ordering[[#This Row],[Design Approved Date]], _xlpm.sim, tbl_die_ordering[[#This Row],[Sim]], _xlpm.prEntry, tbl_die_ordering[[#This Row],[PR Entry]], _xlpm.oracleEntry, tbl_die_ordering[[#This Row],[Oracle Entry]], _xlpm.ems, tbl_die_ordering[[#This Row],[Design saved to EMS FOLDER]], IF(_xlpm.dieNo = "", "", IF(_xlpm.orderNo = "", "PENDING FOR ORDERING", IF(_xlpm.type = "C", "CANCELLED", IF(_xlpm.type = "H", "HOLD", IF(_xlpm.designReceived = "", "AWAITING FOR DESIGN", IF(_xlpm.designApproved = "", IF(_xlpm.sim = "YES", "UNDER SIMULATION", "PENDING FOR DESIGN APPROVAL"), IF(_xlpm.prEntry = "", "PENDING FOR PR", IF(_xlpm.oracleEntry = "", "PENDING FOR ORACLE ENTRY", IF(_xlpm.ems = "", "PENDING FOR DESIGN TO EMS", "DONE"))))))))) ) -> DONE | X32: =IF(AND(tbl_die_ordering[[#This Row],[TYPE]]<>"C",tbl_die_ordering[[#This Row],[Design Approved Date]]<>""),tbl_die_ordering[[#This Row],[Design Approved Date]]-tbl_die_ordering[[#This Row],[Die Requested Date]],0) -> 7 | AA32: MILL,, POWDER, ANODIZING | AB32: =_xlfn.XLOOKUP(_xlfn.TEXTJOIN("_",TRUE,tbl_die_ordering[[#This Row],[Supplier]],tbl_die_ordering[[#This Row],[DIE NO]]),[1]Tracker!$AQ:$AQ,[1]Tracker!$Y:$Y,"") -> 142500608 | AC32: =_xlfn.XLOOKUP(_xlfn.TEXTJOIN("_",TRUE,tbl_die_ordering[[#This Row],[Supplier]],tbl_die_ordering[[#This Row],[DIE NO]]),[1]Tracker!$AQ:$AQ,[1]Tracker!$AC:$AC,"") -> 45681 | AF32: =TEXT(tbl_die_ordering[[#This Row],[Die Requested Date]],"mmm") -> Jan | AG32: =_xlfn.TEXTJOIN("_",TRUE,tbl_die_ordering[[#This Row],[Supplier]],tbl_die_ordering[[#This Row],[DIE NO]]) -> PDTMC_30193-601
A33: GEX 1 | B33: =_xlfn.XLOOKUP(_xlfn.TEXTJOIN("_",TRUE,tbl_die_ordering[[#This Row],[Supplier]],tbl_die_ordering[[#This Row],[DIE NO]]),[1]Tracker!$AQ:$AQ,[1]Tracker!$W:$W,"") -> 7617-25 | C33: 30194-201 | D33: N | E33: 320X160 | F33: 45666 | G33: =_xlfn.XLOOKUP(_xlfn.TEXTJOIN("_",TRUE,tbl_die_ordering[[#This Row],[Supplier]],tbl_die_ordering[[#This Row],[DIE NO]]),[1]Tracker!$AQ:$AQ,[1]Tracker!$V:$V,"") -> 45666 | H33: LAND | I33: 1 | J33: 1 | K33: 45672 | L33: 45673 | N33: =IFERROR(IF(tbl_die_ordering[[#This Row],[Design Approved Date]]<>"",L33-K33,""),"") -> 1 | O33: 45675 | P33: 45675 | Q33: 45675 | R33: 112500275 | S33: PDTMC | T33: 45675 | U33: Insulux Metal | V33: desgn received 13/01/2025 ask for revision 15/01/2025 | W33: =_xlfn.LET( _xlpm.dieNo, tbl_die_ordering[[#This Row],[DIE NO]], _xlpm.orderNo, tbl_die_ordering[[#This Row],[Order No]], _xlpm.type, tbl_die_ordering[[#This Row],[TYPE]], _xlpm.designReceived, tbl_die_ordering[[#This Row],[Design Received Date]], _xlpm.designApproved, tbl_die_ordering[[#This Row],[Design Approved Date]], _xlpm.sim, tbl_die_ordering[[#This Row],[Sim]], _xlpm.prEntry, tbl_die_ordering[[#This Row],[PR Entry]], _xlpm.oracleEntry, tbl_die_ordering[[#This Row],[Oracle Entry]], _xlpm.ems, tbl_die_ordering[[#This Row],[Design saved to EMS FOLDER]], IF(_xlpm.dieNo = "", "", IF(_xlpm.orderNo = "", "PENDING FOR ORDERING", IF(_xlpm.type = "C", "CANCELLED", IF(_xlpm.type = "H", "HOLD", IF(_xlpm.designReceived = "", "AWAITING FOR DESIGN", IF(_xlpm.designApproved = "", IF(_xlpm.sim = "YES", "UNDER SIMULATION", "PENDING FOR DESIGN APPROVAL"), IF(_xlpm.prEntry = "", "PENDING FOR PR", IF(_xlpm.oracleEntry = "", "PENDING FOR ORACLE ENTRY", IF(_xlpm.ems = "", "PENDING FOR DESIGN TO EMS", "DONE"))))))))) ) -> DONE | X33: =IF(AND(tbl_die_ordering[[#This Row],[TYPE]]<>"C",tbl_die_ordering[[#This Row],[Design Approved Date]]<>""),tbl_die_ordering[[#This Row],[Design Approved Date]]-tbl_die_ordering[[#This Row],[Die Requested Date]],0) -> 7 | AA33: MILL,, POWDER, ANODIZING | AB33: =_xlfn.XLOOKUP(_xlfn.TEXTJOIN("_",TRUE,tbl_die_ordering[[#This Row],[Supplier]],tbl_die_ordering[[#This Row],[DIE NO]]),[1]Tracker!$AQ:$AQ,[1]Tracker!$Y:$Y,"") -> 142500608 | AC33: =_xlfn.XLOOKUP(_xlfn.TEXTJOIN("_",TRUE,tbl_die_ordering[[#This Row],[Supplier]],tbl_die_ordering[[#This Row],[DIE NO]]),[1]Tracker!$AQ:$AQ,[1]Tracker!$AC:$AC,"") -> 45681 | AF33: =TEXT(tbl_die_ordering[[#This Row],[Die Requested Date]],"mmm") -> Jan | AG33: =_xlfn.TEXTJOIN("_",TRUE,tbl_die_ordering[[#This Row],[Supplier]],tbl_die_ordering[[#This Row],[DIE NO]]) -> PDTMC_30194-201
A34: GEX 1 | B34: =_xlfn.XLOOKUP(_xlfn.TEXTJOIN("_",TRUE,tbl_die_ordering[[#This Row],[Supplier]],tbl_die_ordering[[#This Row],[DIE NO]]),[1]Tracker!$AQ:$AQ,[1]Tracker!$W:$W,"") -> 7622-25 | C34: 30199-601 | D34: C | E34: 550x300 | F34: 45667 | G34: =_xlfn.XLOOKUP(_xlfn.TEXTJOIN("_",TRUE,tbl_die_ordering[[#This Row],[Supplier]],tbl_die_ordering[[#This Row],[DIE NO]]),[1]Tracker!$AQ:$AQ,[1]Tracker!$V:$V,"") -> 45667 | H34: AIR | I34: 6 | J34: 6 | K34: 45674 | L34: NA | M34: YES | N34: =IFERROR(IF(tbl_die_ordering[[#This Row],[Design Approved Date]]<>"",L34-K34,""),"") | O34: NA | P34: NA | Q34: NA | R34: NA | S34: COMPES | T34: NA | U34: Dural System | V34: die size revised 16/01/205. design received 17/01/2025 asked for 3d 18/01/2025. stp received 23/01. simulation resut not good and ask rev 24/01/25. remind sent to supplier 29/01/2025.design received 29/01.simulation result not satisfiable and we asked. supplier for an online meeting.30/01/2025. dsgn rcvd with simulatin resutl by supplier. result not satisfactery.05/02/2025 . | W34: =_xlfn.LET( _xlpm.dieNo, tbl_die_ordering[[#This Row],[DIE NO]], _xlpm.orderNo, tbl_die_ordering[[#This Row],[Order No]], _xlpm.type, tbl_die_ordering[[#This Row],[TYPE]], _xlpm.designReceived, tbl_die_ordering[[#This Row],[Design Received Date]], _xlpm.designApproved, tbl_die_ordering[[#This Row],[Design Approved Date]], _xlpm.sim, tbl_die_ordering[[#This Row],[Sim]], _xlpm.prEntry, tbl_die_ordering[[#This Row],[PR Entry]], _xlpm.oracleEntry, tbl_die_ordering[[#This Row],[Oracle Entry]], _xlpm.ems, tbl_die_ordering[[#This Row],[Design saved to EMS FOLDER]], IF(_xlpm.dieNo = "", "", IF(_xlpm.orderNo = "", "PENDING FOR ORDERING", IF(_xlpm.type = "C", "CANCELLED", IF(_xlpm.type = "H", "HOLD", IF(_xlpm.designReceived = "", "AWAITING FOR DESIGN", IF(_xlpm.designApproved = "", IF(_xlpm.sim = "YES", "UNDER SIMULATION", "PENDING FOR DESIGN APPROVAL"), IF(_xlpm.prEntry = "", "PENDING FOR PR", IF(_xlpm.oracleEntry = "", "PENDING FOR ORACLE ENTRY", IF(_xlpm.ems = "", "PENDING FOR DESIGN TO EMS", "DONE"))))))))) ) -> CANCELLED | X34: =IF(AND(tbl_die_ordering[[#This Row],[TYPE]]<>"C",tbl_die_ordering[[#This Row],[Design Approved Date]]<>""),tbl_die_ordering[[#This Row],[Design Approved Date]]-tbl_die_ordering[[#This Row],[Die Requested Date]],0) -> 0 | AA34: Anodizing | AB34: =_xlfn.XLOOKUP(_xlfn.TEXTJOIN("_",TRUE,tbl_die_ordering[[#This Row],[Supplier]],tbl_die_ordering[[#This Row],[DIE NO]]),[1]Tracker!$AQ:$AQ,[1]Tracker!$Y:$Y,"") -> 0 | AC34: =_xlfn.XLOOKUP(_xlfn.TEXTJOIN("_",TRUE,tbl_die_ordering[[#This Row],[Supplier]],tbl_die_ordering[[#This Row],[DIE NO]]),[1]Tracker!$AQ:$AQ,[1]Tracker!$AC:$AC,"") -> 0 | AF34: =TEXT(tbl_die_ordering[[#This Row],[Die Requested Date]],"mmm") -> Jan | AG34: =_xlfn.TEXTJOIN("_",TRUE,tbl_die_ordering[[#This Row],[Supplier]],tbl_die_ordering[[#This Row],[DIE NO]]) -> COMPES_30199-601
A35: GEX 1 | B35: =_xlfn.XLOOKUP(_xlfn.TEXTJOIN("_",TRUE,tbl_die_ordering[[#This Row],[Supplier]],tbl_die_ordering[[#This Row],[DIE NO]]),[1]Tracker!$AQ:$AQ,[1]Tracker!$W:$W,"") -> 7618-25 | C35: 09153-204 | D35: B | E35: 320x160 | F35: 45667 | G35: =_xlfn.XLOOKUP(_xlfn.TEXTJOIN("_",TRUE,tbl_die_ordering[[#This Row],[Supplier]],tbl_die_ordering[[#This Row],[DIE NO]]),[1]Tracker!$AQ:$AQ,[1]Tracker!$V:$V,"") -> 45667 | H35: AIR | I35: 0 | J35: 0 | K35: 45670 | L35: 45672 | N35: =IFERROR(IF(tbl_die_ordering[[#This Row],[Design Approved Date]]<>"",L35-K35,""),"") -> 2 | O35: 45673 | P35: 45675 | Q35: 45673 | R35: 112500258 | S35: PHOENIX | T35: 45673 | W35: =_xlfn.LET( _xlpm.dieNo, tbl_die_ordering[[#This Row],[DIE NO]], _xlpm.orderNo, tbl_die_ordering[[#This Row],[Order No]], _xlpm.type, tbl_die_ordering[[#This Row],[TYPE]], _xlpm.designReceived, tbl_die_ordering[[#This Row],[Design Received Date]], _xlpm.designApproved, tbl_die_ordering[[#This Row],[Design Approved Date]], _xlpm.sim, tbl_die_ordering[[#This Row],[Sim]], _xlpm.prEntry, tbl_die_ordering[[#This Row],[PR Entry]], _xlpm.oracleEntry, tbl_die_ordering[[#This Row],[Oracle Entry]], _xlpm.ems, tbl_die_ordering[[#This Row],[Design saved to EMS FOLDER]], IF(_xlpm.dieNo = "", "", IF(_xlpm.orderNo = "", "PENDING FOR ORDERING", IF(_xlpm.type = "C", "CANCELLED", IF(_xlpm.type = "H", "HOLD", IF(_xlpm.designReceived = "", "AWAITING FOR DESIGN", IF(_xlpm.designApproved = "", IF(_xlpm.sim = "YES", "UNDER SIMULATION", "PENDING FOR DESIGN APPROVAL"), IF(_xlpm.prEntry = "", "PENDING FOR PR", IF(_xlpm.oracleEntry = "", "PENDING FOR ORACLE ENTRY", IF(_xlpm.ems = "", "PENDING FOR DESIGN TO EMS", "DONE"))))))))) ) -> DONE | X35: =IF(AND(tbl_die_ordering[[#This Row],[TYPE]]<>"C",tbl_die_ordering[[#This Row],[Design Approved Date]]<>""),tbl_die_ordering[[#This Row],[Design Approved Date]]-tbl_die_ordering[[#This Row],[Die Requested Date]],0) -> 5 | AB35: =_xlfn.XLOOKUP(_xlfn.TEXTJOIN("_",TRUE,tbl_die_ordering[[#This Row],[Supplier]],tbl_die_ordering[[#This Row],[DIE NO]]),[1]Tracker!$AQ:$AQ,[1]Tracker!$Y:$Y,"") -> 142500695 | AC35: =_xlfn.XLOOKUP(_xlfn.TEXTJOIN("_",TRUE,tbl_die_ordering[[#This Row],[Supplier]],tbl_die_ordering[[#This Row],[DIE NO]]),[1]Tracker!$AQ:$AQ,[1]Tracker!$AC:$AC,"") -> 45685 | AF35: =TEXT(tbl_die_ordering[[#This Row],[Die Requested Date]],"mmm") -> Jan | AG35: =_xlfn.TEXTJOIN("_",TRUE,tbl_die_ordering[[#This Row],[Supplier]],tbl_die_ordering[[#This Row],[DIE NO]]) -> PHOENIX _09153-204
A36: GEX 1 | B36: =_xlfn.XLOOKUP(_xlfn.TEXTJOIN("_",TRUE,tbl_die_ordering[[#This Row],[Supplier]],tbl_die_ordering[[#This Row],[DIE NO]]),[1]Tracker!$AQ:$AQ,[1]Tracker!$W:$W,"") -> 7620-25 | C36: 13794-621 | D36: B | E36: 355x200 | F36: 45667 | G36: =_xlfn.XLOOKUP(_xlfn.TEXTJOIN("_",TRUE,tbl_die_ordering[[#This Row],[Supplier]],tbl_die_ordering[[#This Row],[DIE NO]]),[1]Tracker!$AQ:$AQ,[1]Tracker!$V:$V,"") -> 45667 | H36: AIR | I36: 1 | J36: 2 | K36: 45667 | L36: 45672 | N36: =IFERROR(IF(tbl_die_ordering[[#This Row],[Design Approved Date]]<>"",L36-K36,""),"") -> 5 | O36: 45673 | P36: 45675 | Q36: 45673 | R36: 112500258 | S36: EKSTEK | T36: 45673 | W36: =_xlfn.LET( _xlpm.dieNo, tbl_die_ordering[[#This Row],[DIE NO]], _xlpm.orderNo, tbl_die_ordering[[#This Row],[Order No]], _xlpm.type, tbl_die_ordering[[#This Row],[TYPE]], _xlpm.designReceived, tbl_die_ordering[[#This Row],[Design Received Date]], _xlpm.designApproved, tbl_die_ordering[[#This Row],[Design Approved Date]], _xlpm.sim, tbl_die_ordering[[#This Row],[Sim]], _xlpm.prEntry, tbl_die_ordering[[#This Row],[PR Entry]], _xlpm.oracleEntry, tbl_die_ordering[[#This Row],[Oracle Entry]], _xlpm.ems, tbl_die_ordering[[#This Row],[Design saved to EMS FOLDER]], IF(_xlpm.dieNo = "", "", IF(_xlpm.orderNo = "", "PENDING FOR ORDERING", IF(_xlpm.type = "C", "CANCELLED", IF(_xlpm.type = "H", "HOLD", IF(_xlpm.designReceived = "", "AWAITING FOR DESIGN", IF(_xlpm.designApproved = "", IF(_xlpm.sim = "YES", "UNDER SIMULATION", "PENDING FOR DESIGN APPROVAL"), IF(_xlpm.prEntry = "", "PENDING FOR PR", IF(_xlpm.oracleEntry = "", "PENDING FOR ORACLE ENTRY", IF(_xlpm.ems = "", "PENDING FOR DESIGN TO EMS", "DONE"))))))))) ) -> DONE | X36: =IF(AND(tbl_die_ordering[[#This Row],[TYPE]]<>"C",tbl_die_ordering[[#This Row],[Design Approved Date]]<>""),tbl_die_ordering[[#This Row],[Design Approved Date]]-tbl_die_ordering[[#This Row],[Die Requested Date]],0) -> 5 | AB36: =_xlfn.XLOOKUP(_xlfn.TEXTJOIN("_",TRUE,tbl_die_ordering[[#This Row],[Supplier]],tbl_die_ordering[[#This Row],[DIE NO]]),[1]Tracker!$AQ:$AQ,[1]Tracker!$Y:$Y,"") -> 142500744 | AC36: =_xlfn.XLOOKUP(_xlfn.TEXTJOIN("_",TRUE,tbl_die_ordering[[#This Row],[Supplier]],tbl_die_ordering[[#This Row],[DIE NO]]),[1]Tracker!$AQ:$AQ,[1]Tracker!$AC:$AC,"") -> 45685 | AF36: =TEXT(tbl_die_ordering[[#This Row],[Die Requested Date]],"mmm") -> Jan | AG36: =_xlfn.TEXTJOIN("_",TRUE,tbl_die_ordering[[#This Row],[Supplier]],tbl_die_ordering[[#This Row],[DIE NO]]) -> EKSTEK_13794-621
A37: GEX 1 | B37: =_xlfn.XLOOKUP(_xlfn.TEXTJOIN("_",TRUE,tbl_die_ordering[[#This Row],[Supplier]],tbl_die_ordering[[#This Row],[DIE NO]]),[1]Tracker!$AQ:$AQ,[1]Tracker!$W:$W,"") -> 7623-25 | C37: 30200-601 | D37: N | E37: 355X200 | F37: 45667 | G37: =_xlfn.XLOOKUP(_xlfn.TEXTJOIN("_",TRUE,tbl_die_ordering[[#This Row],[Supplier]],tbl_die_ordering[[#This Row],[DIE NO]]),[1]Tracker!$AQ:$AQ,[1]Tracker!$V:$V,"") -> 45667 | H37: LAND | I37: 6 | J37: 6 | K37: 45670 | L37: 45672 | N37: =IFERROR(IF(tbl_die_ordering[[#This Row],[Design Approved Date]]<>"",L37-K37,""),"") -> 2 | O37: 45673 | P37: 45675 | Q37: 45673 | R37: 112500258 | S37: PHME | T37: 45673 | U37: VERTIV GULF LLC OPC | W37: =_xlfn.LET( _xlpm.dieNo, tbl_die_ordering[[#This Row],[DIE NO]], _xlpm.orderNo, tbl_die_ordering[[#This Row],[Order No]], _xlpm.type, tbl_die_ordering[[#This Row],[TYPE]], _xlpm.designReceived, tbl_die_ordering[[#This Row],[Design Received Date]], _xlpm.designApproved, tbl_die_ordering[[#This Row],[Design Approved Date]], _xlpm.sim, tbl_die_ordering[[#This Row],[Sim]], _xlpm.prEntry, tbl_die_ordering[[#This Row],[PR Entry]], _xlpm.oracleEntry, tbl_die_ordering[[#This Row],[Oracle Entry]], _xlpm.ems, tbl_die_ordering[[#This Row],[Design saved to EMS FOLDER]], IF(_xlpm.dieNo = "", "", IF(_xlpm.orderNo = "", "PENDING FOR ORDERING", IF(_xlpm.type = "C", "CANCELLED", IF(_xlpm.type = "H", "HOLD", IF(_xlpm.designReceived = "", "AWAITING FOR DESIGN", IF(_xlpm.designApproved = "", IF(_xlpm.sim = "YES", "UNDER SIMULATION", "PENDING FOR DESIGN APPROVAL"), IF(_xlpm.prEntry = "", "PENDING FOR PR", IF(_xlpm.oracleEntry = "", "PENDING FOR ORACLE ENTRY", IF(_xlpm.ems = "", "PENDING FOR DESIGN TO EMS", "DONE"))))))))) ) -> DONE | X37: =IF(AND(tbl_die_ordering[[#This Row],[TYPE]]<>"C",tbl_die_ordering[[#This Row],[Design Approved Date]]<>""),tbl_die_ordering[[#This Row],[Design Approved Date]]-tbl_die_ordering[[#This Row],[Die Requested Date]],0) -> 5 | AA37: Mill, powder | AB37: =_xlfn.XLOOKUP(_xlfn.TEXTJOIN("_",TRUE,tbl_die_ordering[[#This Row],[Supplier]],tbl_die_ordering[[#This Row],[DIE NO]]),[1]Tracker!$AQ:$AQ,[1]Tracker!$Y:$Y,"") -> 142500574 | AC37: =_xlfn.XLOOKUP(_xlfn.TEXTJOIN("_",TRUE,tbl_die_ordering[[#This Row],[Supplier]],tbl_die_ordering[[#This Row],[DIE NO]]),[1]Tracker!$AQ:$AQ,[1]Tracker!$AC:$AC,"") -> 45683 | AF37: =TEXT(tbl_die_ordering[[#This Row],[Die Requested Date]],"mmm") -> Jan | AG37: =_xlfn.TEXTJOIN("_",TRUE,tbl_die_ordering[[#This Row],[Supplier]],tbl_die_ordering[[#This Row],[DIE NO]]) -> PHME_30200-601
A38: GEX 1 | B38: =_xlfn.XLOOKUP(_xlfn.TEXTJOIN("_",TRUE,tbl_die_ordering[[#This Row],[Supplier]],tbl_die_ordering[[#This Row],[DIE NO]]),[1]Tracker!$AQ:$AQ,[1]Tracker!$W:$W,"") -> 7623-25 | C38: 30201-601 | D38: N | E38: 450X250 | F38: 45667 | G38: =_xlfn.XLOOKUP(_xlfn.TEXTJOIN("_",TRUE,tbl_die_ordering[[#This Row],[Supplier]],tbl_die_ordering[[#This Row],[DIE NO]]),[1]Tracker!$AQ:$AQ,[1]Tracker!$V:$V,"") -> 45667 | H38: LAND | I38: 7 | J38: 7 | K38: 45670 | L38: 45672 | N38: =IFERROR(IF(tbl_die_ordering[[#This Row],[Design Approved Date]]<>"",L38-K38,""),"") -> 2 | O38: 45673 | P38: 45675 | Q38: 45673 | R38: 112500258 | S38: PHME | T38: 45673 | U38: VERTIV GULF LLC OPC | W38: =_xlfn.LET( _xlpm.dieNo, tbl_die_ordering[[#This Row],[DIE NO]], _xlpm.orderNo, tbl_die_ordering[[#This Row],[Order No]], _xlpm.type, tbl_die_ordering[[#This Row],[TYPE]], _xlpm.designReceived, tbl_die_ordering[[#This Row],[Design Received Date]], _xlpm.designApproved, tbl_die_ordering[[#This Row],[Design Approved Date]], _xlpm.sim, tbl_die_ordering[[#This Row],[Sim]], _xlpm.prEntry, tbl_die_ordering[[#This Row],[PR Entry]], _xlpm.oracleEntry, tbl_die_ordering[[#This Row],[Oracle Entry]], _xlpm.ems, tbl_die_ordering[[#This Row],[Design saved to EMS FOLDER]], IF(_xlpm.dieNo = "", "", IF(_xlpm.orderNo = "", "PENDING FOR ORDERING", IF(_xlpm.type = "C", "CANCELLED", IF(_xlpm.type = "H", "HOLD", IF(_xlpm.designReceived = "", "AWAITING FOR DESIGN", IF(_xlpm.designApproved = "", IF(_xlpm.sim = "YES", "UNDER SIMULATION", "PENDING FOR DESIGN APPROVAL"), IF(_xlpm.prEntry = "", "PENDING FOR PR", IF(_xlpm.oracleEntry = "", "PENDING FOR ORACLE ENTRY", IF(_xlpm.ems = "", "PENDING FOR DESIGN TO EMS", "DONE"))))))))) ) -> DONE | X38: =IF(AND(tbl_die_ordering[[#This Row],[TYPE]]<>"C",tbl_die_ordering[[#This Row],[Design Approved Date]]<>""),tbl_die_ordering[[#This Row],[Design Approved Date]]-tbl_die_ordering[[#This Row],[Die Requested Date]],0) -> 5 | AA38: Mill, powder | AB38: =_xlfn.XLOOKUP(_xlfn.TEXTJOIN("_",TRUE,tbl_die_ordering[[#This Row],[Supplier]],tbl_die_ordering[[#This Row],[DIE NO]]),[1]Tracker!$AQ:$AQ,[1]Tracker!$Y:$Y,"") -> 142500574 | AC38: =_xlfn.XLOOKUP(_xlfn.TEXTJOIN("_",TRUE,tbl_die_ordering[[#This Row],[Supplier]],tbl_die_ordering[[#This Row],[DIE NO]]),[1]Tracker!$AQ:$AQ,[1]Tracker!$AC:$AC,"") -> 45683 | AF38: =TEXT(tbl_die_ordering[[#This Row],[Die Requested Date]],"mmm") -> Jan | AG38: =_xlfn.TEXTJOIN("_",TRUE,tbl_die_ordering[[#This Row],[Supplier]],tbl_die_ordering[[#This Row],[DIE NO]]) -> PHME_30201-601
A39: GEX 1 | B39: =_xlfn.XLOOKUP(_xlfn.TEXTJOIN("_",TRUE,tbl_die_ordering[[#This Row],[Supplier]],tbl_die_ordering[[#This Row],[DIE NO]]),[1]Tracker!$AQ:$AQ,[1]Tracker!$W:$W,"") -> 7622-25 | C39: 30198-601 | D39: N | E39: 550x250 | F39: 45667 | G39: =_xlfn.XLOOKUP(_xlfn.TEXTJOIN("_",TRUE,tbl_die_ordering[[#This Row],[Supplier]],tbl_die_ordering[[#This Row],[DIE NO]]),[1]Tracker!$AQ:$AQ,[1]Tracker!$V:$V,"") -> 45667 | H39: AIR | I39: 1 | J39: 1 | K39: 45673 | L39: 45673 | N39: =IFERROR(IF(tbl_die_ordering[[#This Row],[Design Approved Date]]<>"",L39-K39,""),"") -> 0 | O39: 45675 | P39: 45675 | Q39: 45675 | R39: 112500275 | S39: COMPES | T39: 45675 | U39: Dural System | W39: =_xlfn.LET( _xlpm.dieNo, tbl_die_ordering[[#This Row],[DIE NO]], _xlpm.orderNo, tbl_die_ordering[[#This Row],[Order No]], _xlpm.type, tbl_die_ordering[[#This Row],[TYPE]], _xlpm.designReceived, tbl_die_ordering[[#This Row],[Design Received Date]], _xlpm.designApproved, tbl_die_ordering[[#This Row],[Design Approved Date]], _xlpm.sim, tbl_die_ordering[[#This Row],[Sim]], _xlpm.prEntry, tbl_die_ordering[[#This Row],[PR Entry]], _xlpm.oracleEntry, tbl_die_ordering[[#This Row],[Oracle Entry]], _xlpm.ems, tbl_die_ordering[[#This Row],[Design saved to EMS FOLDER]], IF(_xlpm.dieNo = "", "", IF(_xlpm.orderNo = "", "PENDING FOR ORDERING", IF(_xlpm.type = "C", "CANCELLED", IF(_xlpm.type = "H", "HOLD", IF(_xlpm.designReceived = "", "AWAITING FOR DESIGN", IF(_xlpm.designApproved = "", IF(_xlpm.sim = "YES", "UNDER SIMULATION", "PENDING FOR DESIGN APPROVAL"), IF(_xlpm.prEntry = "", "PENDING FOR PR", IF(_xlpm.oracleEntry = "", "PENDING FOR ORACLE ENTRY", IF(_xlpm.ems = "", "PENDING FOR DESIGN TO EMS", "DONE"))))))))) ) -> DONE | X39: =IF(AND(tbl_die_ordering[[#This Row],[TYPE]]<>"C",tbl_die_ordering[[#This Row],[Design Approved Date]]<>""),tbl_die_ordering[[#This Row],[Design Approved Date]]-tbl_die_ordering[[#This Row],[Die Requested Date]],0) -> 6 | Z39: Gex-1 | AA39: Anodizing | AB39: =_xlfn.XLOOKUP(_xlfn.TEXTJOIN("_",TRUE,tbl_die_ordering[[#This Row],[Supplier]],tbl_die_ordering[[#This Row],[DIE NO]]),[1]Tracker!$AQ:$AQ,[1]Tracker!$Y:$Y,"") -> 142500747 | AC39: =_xlfn.XLOOKUP(_xlfn.TEXTJOIN("_",TRUE,tbl_die_ordering[[#This Row],[Supplier]],tbl_die_ordering[[#This Row],[DIE NO]]),[1]Tracker!$AQ:$AQ,[1]Tracker!$AC:$AC,"") -> 45693 | AF39: =TEXT(tbl_die_ordering[[#This Row],[Die Requested Date]],"mmm") -> Jan | AG39: =_xlfn.TEXTJOIN("_",TRUE,tbl_die_ordering[[#This Row],[Supplier]],tbl_die_ordering[[#This Row],[DIE NO]]) -> COMPES_30198-601
A40: GEX 1 | B40: =_xlfn.XLOOKUP(_xlfn.TEXTJOIN("_",TRUE,tbl_die_ordering[[#This Row],[Supplier]],tbl_die_ordering[[#This Row],[DIE NO]]),[1]Tracker!$AQ:$AQ,[1]Tracker!$W:$W,"") -> 7619-25 | C40: 05225-605 | D40: B | E40: 700x400 | F40: 45667 | G40: =_xlfn.XLOOKUP(_xlfn.TEXTJOIN("_",TRUE,tbl_die_ordering[[#This Row],[Supplier]],tbl_die_ordering[[#This Row],[DIE NO]]),[1]Tracker!$AQ:$AQ,[1]Tracker!$V:$V,"") -> 45667 | H40: AIR | I40: 1 | J40: 1 | K40: 45680 | L40: 45681 | N40: =IFERROR(IF(tbl_die_ordering[[#This Row],[Design Approved Date]]<>"",L40-K40,""),"") -> 1 | O40: 45682 | P40: 45684 | Q40: 45682 | R40: 112500378 | S40: ADEX | T40: 45682 | W40: =_xlfn.LET( _xlpm.dieNo, tbl_die_ordering[[#This Row],[DIE NO]], _xlpm.orderNo, tbl_die_ordering[[#This Row],[Order No]], _xlpm.type, tbl_die_ordering[[#This Row],[TYPE]], _xlpm.designReceived, tbl_die_ordering[[#This Row],[Design Received Date]], _xlpm.designApproved, tbl_die_ordering[[#This Row],[Design Approved Date]], _xlpm.sim, tbl_die_ordering[[#This Row],[Sim]], _xlpm.prEntry, tbl_die_ordering[[#This Row],[PR Entry]], _xlpm.oracleEntry, tbl_die_ordering[[#This Row],[Oracle Entry]], _xlpm.ems, tbl_die_ordering[[#This Row],[Design saved to EMS FOLDER]], IF(_xlpm.dieNo = "", "", IF(_xlpm.orderNo = "", "PENDING FOR ORDERING", IF(_xlpm.type = "C", "CANCELLED", IF(_xlpm.type = "H", "HOLD", IF(_xlpm.designReceived = "", "AWAITING FOR DESIGN", IF(_xlpm.designApproved = "", IF(_xlpm.sim = "YES", "UNDER SIMULATION", "PENDING FOR DESIGN APPROVAL"), IF(_xlpm.prEntry = "", "PENDING FOR PR", IF(_xlpm.oracleEntry = "", "PENDING FOR ORACLE ENTRY", IF(_xlpm.ems = "", "PENDING FOR DESIGN TO EMS", "DONE"))))))))) ) -> DONE | X40: =IF(AND(tbl_die_ordering[[#This Row],[TYPE]]<>"C",tbl_die_ordering[[#This Row],[Design Approved Date]]<>""),tbl_die_ordering[[#This Row],[Design Approved Date]]-tbl_die_ordering[[#This Row],[Die Requested Date]],0) -> 14 | AB40: =_xlfn.XLOOKUP(_xlfn.TEXTJOIN("_",TRUE,tbl_die_ordering[[#This Row],[Supplier]],tbl_die_ordering[[#This Row],[DIE NO]]),[1]Tracker!$AQ:$AQ,[1]Tracker!$Y:$Y,"") -> 142500934 | AC40: =_xlfn.XLOOKUP(_xlfn.TEXTJOIN("_",TRUE,tbl_die_ordering[[#This Row],[Supplier]],tbl_die_ordering[[#This Row],[DIE NO]]),[1]Tracker!$AQ:$AQ,[1]Tracker!$AC:$AC,"") -> 45692 | AF40: =TEXT(tbl_die_ordering[[#This Row],[Die Requested Date]],"mmm") -> Jan | AG40: =_xlfn.TEXTJOIN("_",TRUE,tbl_die_ordering[[#This Row],[Supplier]],tbl_die_ordering[[#This Row],[DIE NO]]) -> ADEX_05225-605
A41: GEX 1 | B41: =_xlfn.XLOOKUP(_xlfn.TEXTJOIN("_",TRUE,tbl_die_ordering[[#This Row],[Supplier]],tbl_die_ordering[[#This Row],[DIE NO]]),[1]Tracker!$AQ:$AQ,[1]Tracker!$W:$W,"") -> 7618-25 | C41: 14674-515 | D41: B | E41: 320x160 | F41: 45667 | G41: =_xlfn.XLOOKUP(_xlfn.TEXTJOIN("_",TRUE,tbl_die_ordering[[#This Row],[Supplier]],tbl_die_ordering[[#This Row],[DIE NO]]),[1]Tracker!$AQ:$AQ,[1]Tracker!$V:$V,"") -> 45667 | H41: AIR | I41: 1 | J41: 3 | K41: 45687 | L41: 45688 | M41: YES | N41: =IFERROR(IF(tbl_die_ordering[[#This Row],[Design Approved Date]]<>"",L41-K41,""),"") -> 1 | O41: 45689 | P41: 45694 | Q41: 45689 | R41: 112500467 | S41: PHOENIX | T41: 45689 | V41: des rec 13/01. simulatin asked 16/01. simulation came 17/01. entry dia more 207, revised simulation and 2d design received 18/01. simulation rest not good 22/01. ask for revision 22/01 rev rec 22/01/25 7.45 Pm under simulation.simulation result not good aske for revision and chang conventional design istead of mono brigd 28/01. design received 30/01 | W41: =_xlfn.LET( _xlpm.dieNo, tbl_die_ordering[[#This Row],[DIE NO]], _xlpm.orderNo, tbl_die_ordering[[#This Row],[Order No]], _xlpm.type, tbl_die_ordering[[#This Row],[TYPE]], _xlpm.designReceived, tbl_die_ordering[[#This Row],[Design Received Date]], _xlpm.designApproved, tbl_die_ordering[[#This Row],[Design Approved Date]], _xlpm.sim, tbl_die_ordering[[#This Row],[Sim]], _xlpm.prEntry, tbl_die_ordering[[#This Row],[PR Entry]], _xlpm.oracleEntry, tbl_die_ordering[[#This Row],[Oracle Entry]], _xlpm.ems, tbl_die_ordering[[#This Row],[Design saved to EMS FOLDER]], IF(_xlpm.dieNo = "", "", IF(_xlpm.orderNo = "", "PENDING FOR ORDERING", IF(_xlpm.type = "C", "CANCELLED", IF(_xlpm.type = "H", "HOLD", IF(_xlpm.designReceived = "", "AWAITING FOR DESIGN", IF(_xlpm.designApproved = "", IF(_xlpm.sim = "YES", "UNDER SIMULATION", "PENDING FOR DESIGN APPROVAL"), IF(_xlpm.prEntry = "", "PENDING FOR PR", IF(_xlpm.oracleEntry = "", "PENDING FOR ORACLE ENTRY", IF(_xlpm.ems = "", "PENDING FOR DESIGN TO EMS", "DONE"))))))))) ) -> DONE | X41: =IF(AND(tbl_die_ordering[[#This Row],[TYPE]]<>"C",tbl_die_ordering[[#This Row],[Design Approved Date]]<>""),tbl_die_ordering[[#This Row],[Design Approved Date]]-tbl_die_ordering[[#This Row],[Die Requested Date]],0) -> 21 | Z41: Gex-1 | AB41: =_xlfn.XLOOKUP(_xlfn.TEXTJOIN("_",TRUE,tbl_die_ordering[[#This Row],[Supplier]],tbl_die_ordering[[#This Row],[DIE NO]]),[1]Tracker!$AQ:$AQ,[1]Tracker!$Y:$Y,"") -> 142501303 | AC41: =_xlfn.XLOOKUP(_xlfn.TEXTJOIN("_",TRUE,tbl_die_ordering[[#This Row],[Supplier]],tbl_die_ordering[[#This Row],[DIE NO]]),[1]Tracker!$AQ:$AQ,[1]Tracker!$AC:$AC,"") -> 45702 | AF41: =TEXT(tbl_die_ordering[[#This Row],[Die Requested Date]],"mmm") -> Jan | AG41: =_xlfn.TEXTJOIN("_",TRUE,tbl_die_ordering[[#This Row],[Supplier]],tbl_die_ordering[[#This Row],[DIE NO]]) -> PHOENIX _14674-515
A42: GEX 1 | B42: =_xlfn.XLOOKUP(_xlfn.TEXTJOIN("_",TRUE,tbl_die_ordering[[#This Row],[Supplier]],tbl_die_ordering[[#This Row],[DIE NO]]),[1]Tracker!$AQ:$AQ,[1]Tracker!$W:$W,"") -> 7618-25 | C42: INS-05019 | D42: B | E42: 300x100 | F42: 45667 | G42: =_xlfn.XLOOKUP(_xlfn.TEXTJOIN("_",TRUE,tbl_die_ordering[[#This Row],[Supplier]],tbl_die_ordering[[#This Row],[DIE NO]]),[1]Tracker!$AQ:$AQ,[1]Tracker!$V:$V,"") -> 45667 | H42: AIR | I42: 0 | J42: 0 | K42: 45681 | L42: 45685 | N42: =IFERROR(IF(tbl_die_ordering[[#This Row],[Design Approved Date]]<>"",L42-K42,""),"") -> 4 | O42: 45689 | P42: 45694 | Q42: 45689 | R42: 112500468 | S42: PHOENIX | T42: 45689 | W42: =_xlfn.LET( _xlpm.dieNo, tbl_die_ordering[[#This Row],[DIE NO]], _xlpm.orderNo, tbl_die_ordering[[#This Row],[Order No]], _xlpm.type, tbl_die_ordering[[#This Row],[TYPE]], _xlpm.designReceived, tbl_die_ordering[[#This Row],[Design Received Date]], _xlpm.designApproved, tbl_die_ordering[[#This Row],[Design Approved Date]], _xlpm.sim, tbl_die_ordering[[#This Row],[Sim]], _xlpm.prEntry, tbl_die_ordering[[#This Row],[PR Entry]], _xlpm.oracleEntry, tbl_die_ordering[[#This Row],[Oracle Entry]], _xlpm.ems, tbl_die_ordering[[#This Row],[Design saved to EMS FOLDER]], IF(_xlpm.dieNo = "", "", IF(_xlpm.orderNo = "", "PENDING FOR ORDERING", IF(_xlpm.type = "C", "CANCELLED", IF(_xlpm.type = "H", "HOLD", IF(_xlpm.designReceived = "", "AWAITING FOR DESIGN", IF(_xlpm.designApproved = "", IF(_xlpm.sim = "YES", "UNDER SIMULATION", "PENDING FOR DESIGN APPROVAL"), IF(_xlpm.prEntry = "", "PENDING FOR PR", IF(_xlpm.oracleEntry = "", "PENDING FOR ORACLE ENTRY", IF(_xlpm.ems = "", "PENDING FOR DESIGN TO EMS", "DONE"))))))))) ) -> DONE | X42: =IF(AND(tbl_die_ordering[[#This Row],[TYPE]]<>"C",tbl_die_ordering[[#This Row],[Design Approved Date]]<>""),tbl_die_ordering[[#This Row],[Design Approved Date]]-tbl_die_ordering[[#This Row],[Die Requested Date]],0) -> 18 | AB42: =_xlfn.XLOOKUP(_xlfn.TEXTJOIN("_",TRUE,tbl_die_ordering[[#This Row],[Supplier]],tbl_die_ordering[[#This Row],[DIE NO]]),[1]Tracker!$AQ:$AQ,[1]Tracker!$Y:$Y,"") -> 142501247 | AC42: =_xlfn.XLOOKUP(_xlfn.TEXTJOIN("_",TRUE,tbl_die_ordering[[#This Row],[Supplier]],tbl_die_ordering[[#This Row],[DIE NO]]),[1]Tracker!$AQ:$AQ,[1]Tracker!$AC:$AC,"") -> 45700 | AF42: =TEXT(tbl_die_ordering[[#This Row],[Die Requested Date]],"mmm") -> Jan | AG42: =_xlfn.TEXTJOIN("_",TRUE,tbl_die_ordering[[#This Row],[Supplier]],tbl_die_ordering[[#This Row],[DIE NO]]) -> PHOENIX _INS-05019
A43: GEX 1 | B43: =_xlfn.XLOOKUP(_xlfn.TEXTJOIN("_",TRUE,tbl_die_ordering[[#This Row],[Supplier]],tbl_die_ordering[[#This Row],[DIE NO]]),[1]Tracker!$AQ:$AQ,[1]Tracker!$W:$W,"") -> 7618-25 | C43: 13212-601 | D43: B | E43: 355x200 | F43: 45667 | G43: =_xlfn.XLOOKUP(_xlfn.TEXTJOIN("_",TRUE,tbl_die_ordering[[#This Row],[Supplier]],tbl_die_ordering[[#This Row],[DIE NO]]),[1]Tracker!$AQ:$AQ,[1]Tracker!$V:$V,"") -> 45667 | H43: AIR | I43: 1 | J43: 3 | K43: 45681 | L43: 45685 | M43: YES | N43: =IFERROR(IF(tbl_die_ordering[[#This Row],[Design Approved Date]]<>"",L43-K43,""),"") -> 4 | O43: 45696 | P43: 45694 | Q43: 45696 | R43: 112500588 | S43: PHOENIX | T43: 45689 | V43: design received 16/1. 3d model awaited 16/01/2025. revision aske 17/01/25. stp receive and ask for die size changes 20/01/2025 simulation result not good ask for revi 23/01/2025.revi received 24/01/2025 4:22 Pm in the evining. evining under simulation 27/01/2025.Wrong PR-112500468 | W43: =_xlfn.LET( _xlpm.dieNo, tbl_die_ordering[[#This Row],[DIE NO]], _xlpm.orderNo, tbl_die_ordering[[#This Row],[Order No]], _xlpm.type, tbl_die_ordering[[#This Row],[TYPE]], _xlpm.designReceived, tbl_die_ordering[[#This Row],[Design Received Date]], _xlpm.designApproved, tbl_die_ordering[[#This Row],[Design Approved Date]], _xlpm.sim, tbl_die_ordering[[#This Row],[Sim]], _xlpm.prEntry, tbl_die_ordering[[#This Row],[PR Entry]], _xlpm.oracleEntry, tbl_die_ordering[[#This Row],[Oracle Entry]], _xlpm.ems, tbl_die_ordering[[#This Row],[Design saved to EMS FOLDER]], IF(_xlpm.dieNo = "", "", IF(_xlpm.orderNo = "", "PENDING FOR ORDERING", IF(_xlpm.type = "C", "CANCELLED", IF(_xlpm.type = "H", "HOLD", IF(_xlpm.designReceived = "", "AWAITING FOR DESIGN", IF(_xlpm.designApproved = "", IF(_xlpm.sim = "YES", "UNDER SIMULATION", "PENDING FOR DESIGN APPROVAL"), IF(_xlpm.prEntry = "", "PENDING FOR PR", IF(_xlpm.oracleEntry = "", "PENDING FOR ORACLE ENTRY", IF(_xlpm.ems = "", "PENDING FOR DESIGN TO EMS", "DONE"))))))))) ) -> DONE | X43: =IF(AND(tbl_die_ordering[[#This Row],[TYPE]]<>"C",tbl_die_ordering[[#This Row],[Design Approved Date]]<>""),tbl_die_ordering[[#This Row],[Design Approved Date]]-tbl_die_ordering[[#This Row],[Die Requested Date]],0) -> 18 | AB43: =_xlfn.XLOOKUP(_xlfn.TEXTJOIN("_",TRUE,tbl_die_ordering[[#This Row],[Supplier]],tbl_die_ordering[[#This Row],[DIE NO]]),[1]Tracker!$AQ:$AQ,[1]Tracker!$Y:$Y,"") -> 142501306 | AC43: =_xlfn.XLOOKUP(_xlfn.TEXTJOIN("_",TRUE,tbl_die_ordering[[#This Row],[Supplier]],tbl_die_ordering[[#This Row],[DIE NO]]),[1]Tracker!$AQ:$AQ,[1]Tracker!$AC:$AC,"") -> 45702 | AE43: cav increased | AF43: =TEXT(tbl_die_ordering[[#This Row],[Die Requested Date]],"mmm") -> Jan | AG43: =_xlfn.TEXTJOIN("_",TRUE,tbl_die_ordering[[#This Row],[Supplier]],tbl_die_ordering[[#This Row],[DIE NO]]) -> PHOENIX _13212-601
A44: GEX 1 | B44: =_xlfn.XLOOKUP(_xlfn.TEXTJOIN("_",TRUE,tbl_die_ordering[[#This Row],[Supplier]],tbl_die_ordering[[#This Row],[DIE NO]]),[1]Tracker!$AQ:$AQ,[1]Tracker!$W:$W,"") -> 7621-25 | C44: 14854-204 | D44: B | E44: 320x160 | F44: 45667 | G44: =_xlfn.XLOOKUP(_xlfn.TEXTJOIN("_",TRUE,tbl_die_ordering[[#This Row],[Supplier]],tbl_die_ordering[[#This Row],[DIE NO]]),[1]Tracker!$AQ:$AQ,[1]Tracker!$V:$V,"") -> 45667 | H44: AIR | I44: 3 | J44: 3 | K44: 45693 | L44: 45699 | M44: YES | N44: =IFERROR(IF(tbl_die_ordering[[#This Row],[Design Approved Date]]<>"",L44-K44,""),"") -> 6 | O44: 45700 | P44: 45703 | Q44: 45700 | R44: 112500644 | S44: COMPES | T44: 45700 | V44: des rec 16/01/2025 ask for simu 17/1 simulation corupt 18/01 rivs stp rec 20/1. simulatio result not good ask rev 24/01/2025.rvs design recved 28/01/2025 under simulation , 3d model received 05.02.2025 | W44: =_xlfn.LET( _xlpm.dieNo, tbl_die_ordering[[#This Row],[DIE NO]], _xlpm.orderNo, tbl_die_ordering[[#This Row],[Order No]], _xlpm.type, tbl_die_ordering[[#This Row],[TYPE]], _xlpm.designReceived, tbl_die_ordering[[#This Row],[Design Received Date]], _xlpm.designApproved, tbl_die_ordering[[#This Row],[Design Approved Date]], _xlpm.sim, tbl_die_ordering[[#This Row],[Sim]], _xlpm.prEntry, tbl_die_ordering[[#This Row],[PR Entry]], _xlpm.oracleEntry, tbl_die_ordering[[#This Row],[Oracle Entry]], _xlpm.ems, tbl_die_ordering[[#This Row],[Design saved to EMS FOLDER]], IF(_xlpm.dieNo = "", "", IF(_xlpm.orderNo = "", "PENDING FOR ORDERING", IF(_xlpm.type = "C", "CANCELLED", IF(_xlpm.type = "H", "HOLD", IF(_xlpm.designReceived = "", "AWAITING FOR DESIGN", IF(_xlpm.designApproved = "", IF(_xlpm.sim = "YES", "UNDER SIMULATION", "PENDING FOR DESIGN APPROVAL"), IF(_xlpm.prEntry = "", "PENDING FOR PR", IF(_xlpm.oracleEntry = "", "PENDING FOR ORACLE ENTRY", IF(_xlpm.ems = "", "PENDING FOR DESIGN TO EMS", "DONE"))))))))) ) -> DONE | X44: =IF(AND(tbl_die_ordering[[#This Row],[TYPE]]<>"C",tbl_die_ordering[[#This Row],[Design Approved Date]]<>""),tbl_die_ordering[[#This Row],[Design Approved Date]]-tbl_die_ordering[[#This Row],[Die Requested Date]],0) -> 32 | AB44: =_xlfn.XLOOKUP(_xlfn.TEXTJOIN("_",TRUE,tbl_die_ordering[[#This Row],[Supplier]],tbl_die_ordering[[#This Row],[DIE NO]]),[1]Tracker!$AQ:$AQ,[1]Tracker!$Y:$Y,"") -> 142501559 | AC44: =_xlfn.XLOOKUP(_xlfn.TEXTJOIN("_",TRUE,tbl_die_ordering[[#This Row],[Supplier]],tbl_die_ordering[[#This Row],[DIE NO]]),[1]Tracker!$AQ:$AQ,[1]Tracker!$AC:$AC,"") -> 45719 | AF44: =TEXT(tbl_die_ordering[[#This Row],[Die Requested Date]],"mmm") -> Jan | AG44: =_xlfn.TEXTJOIN("_",TRUE,tbl_die_ordering[[#This Row],[Supplier]],tbl_die_ordering[[#This Row],[DIE NO]]) -> COMPES_14854-204
A45: GEX 1 | B45: =_xlfn.XLOOKUP(_xlfn.TEXTJOIN("_",TRUE,tbl_die_ordering[[#This Row],[Supplier]],tbl_die_ordering[[#This Row],[DIE NO]]),[1]Tracker!$AQ:$AQ,[1]Tracker!$W:$W,"") -> 7628-25 | C45: 29979-602 | D45: C | E45: 700X500 | F45: 45670 | G45: =_xlfn.XLOOKUP(_xlfn.TEXTJOIN("_",TRUE,tbl_die_ordering[[#This Row],[Supplier]],tbl_die_ordering[[#This Row],[DIE NO]]),[1]Tracker!$AQ:$AQ,[1]Tracker!$V:$V,"") -> 45670 | H45: AIR | I45: 4 | J45: 4 | K45: NA | L45: NA | N45: =IFERROR(IF(tbl_die_ordering[[#This Row],[Design Approved Date]]<>"",L45-K45,""),"") | O45: NA | P45: NA | Q45: NA | R45: NA | S45: ADEX | W45: =_xlfn.LET( _xlpm.dieNo, tbl_die_ordering[[#This Row],[DIE NO]], _xlpm.orderNo, tbl_die_ordering[[#This Row],[Order No]], _xlpm.type, tbl_die_ordering[[#This Row],[TYPE]], _xlpm.designReceived, tbl_die_ordering[[#This Row],[Design Received Date]], _xlpm.designApproved, tbl_die_ordering[[#This Row],[Design Approved Date]], _xlpm.sim, tbl_die_ordering[[#This Row],[Sim]], _xlpm.prEntry, tbl_die_ordering[[#This Row],[PR Entry]], _xlpm.oracleEntry, tbl_die_ordering[[#This Row],[Oracle Entry]], _xlpm.ems, tbl_die_ordering[[#This Row],[Design saved to EMS FOLDER]], IF(_xlpm.dieNo = "", "", IF(_xlpm.orderNo = "", "PENDING FOR ORDERING", IF(_xlpm.type = "C", "CANCELLED", IF(_xlpm.type = "H", "HOLD", IF(_xlpm.designReceived = "", "AWAITING FOR DESIGN", IF(_xlpm.designApproved = "", IF(_xlpm.sim = "YES", "UNDER SIMULATION", "PENDING FOR DESIGN APPROVAL"), IF(_xlpm.prEntry = "", "PENDING FOR PR", IF(_xlpm.oracleEntry = "", "PENDING FOR ORACLE ENTRY", IF(_xlpm.ems = "", "PENDING FOR DESIGN TO EMS", "DONE"))))))))) ) -> CANCELLED | X45: =IF(AND(tbl_die_ordering[[#This Row],[TYPE]]<>"C",tbl_die_ordering[[#This Row],[Design Approved Date]]<>""),tbl_die_ordering[[#This Row],[Design Approved Date]]-tbl_die_ordering[[#This Row],[Die Requested Date]],0) -> 0 | AB45: =_xlfn.XLOOKUP(_xlfn.TEXTJOIN("_",TRUE,tbl_die_ordering[[#This Row],[Supplier]],tbl_die_ordering[[#This Row],[DIE NO]]),[1]Tracker!$AQ:$AQ,[1]Tracker!$Y:$Y,"") -> 0 | AC45: =_xlfn.XLOOKUP(_xlfn.TEXTJOIN("_",TRUE,tbl_die_ordering[[#This Row],[Supplier]],tbl_die_ordering[[#This Row],[DIE NO]]),[1]Tracker!$AQ:$AQ,[1]Tracker!$AC:$AC,"") -> 0 | AF45: =TEXT(tbl_die_ordering[[#This Row],[Die Requested Date]],"mmm") -> Jan | AG45: =_xlfn.TEXTJOIN("_",TRUE,tbl_die_ordering[[#This Row],[Supplier]],tbl_die_ordering[[#This Row],[DIE NO]]) -> ADEX_29979-602
A46: GEX 1 | B46: =_xlfn.XLOOKUP(_xlfn.TEXTJOIN("_",TRUE,tbl_die_ordering[[#This Row],[Supplier]],tbl_die_ordering[[#This Row],[DIE NO]]),[1]Tracker!$AQ:$AQ,[1]Tracker!$W:$W,"") -> 7626-25 | C46: 13212-408 | D46: B | E46: 220X130 | F46: 45670 | G46: =_xlfn.XLOOKUP(_xlfn.TEXTJOIN("_",TRUE,tbl_die_ordering[[#This Row],[Supplier]],tbl_die_ordering[[#This Row],[DIE NO]]),[1]Tracker!$AQ:$AQ,[1]Tracker!$V:$V,"") -> 45670 | H46: LAND | I46: 1 | J46: 1 | K46: 45670 | L46: 45672 | N46: =IFERROR(IF(tbl_die_ordering[[#This Row],[Design Approved Date]]<>"",L46-K46,""),"") -> 2 | O46: 45673 | P46: 45675 | Q46: 45673 | R46: 112500258 | S46: PDTMC | T46: 45673 | W46: =_xlfn.LET( _xlpm.dieNo, tbl_die_ordering[[#This Row],[DIE NO]], _xlpm.orderNo, tbl_die_ordering[[#This Row],[Order No]], _xlpm.type, tbl_die_ordering[[#This Row],[TYPE]], _xlpm.designReceived, tbl_die_ordering[[#This Row],[Design Received Date]], _xlpm.designApproved, tbl_die_ordering[[#This Row],[Design Approved Date]], _xlpm.sim, tbl_die_ordering[[#This Row],[Sim]], _xlpm.prEntry, tbl_die_ordering[[#This Row],[PR Entry]], _xlpm.oracleEntry, tbl_die_ordering[[#This Row],[Oracle Entry]], _xlpm.ems, tbl_die_ordering[[#This Row],[Design saved to EMS FOLDER]], IF(_xlpm.dieNo = "", "", IF(_xlpm.orderNo = "", "PENDING FOR ORDERING", IF(_xlpm.type = "C", "CANCELLED", IF(_xlpm.type = "H", "HOLD", IF(_xlpm.designReceived = "", "AWAITING FOR DESIGN", IF(_xlpm.designApproved = "", IF(_xlpm.sim = "YES", "UNDER SIMULATION", "PENDING FOR DESIGN APPROVAL"), IF(_xlpm.prEntry = "", "PENDING FOR PR", IF(_xlpm.oracleEntry = "", "PENDING FOR ORACLE ENTRY", IF(_xlpm.ems = "", "PENDING FOR DESIGN TO EMS", "DONE"))))))))) ) -> DONE | X46: =IF(AND(tbl_die_ordering[[#This Row],[TYPE]]<>"C",tbl_die_ordering[[#This Row],[Design Approved Date]]<>""),tbl_die_ordering[[#This Row],[Design Approved Date]]-tbl_die_ordering[[#This Row],[Die Requested Date]],0) -> 2 | AB46: =_xlfn.XLOOKUP(_xlfn.TEXTJOIN("_",TRUE,tbl_die_ordering[[#This Row],[Supplier]],tbl_die_ordering[[#This Row],[DIE NO]]),[1]Tracker!$AQ:$AQ,[1]Tracker!$Y:$Y,"") -> 142500742 | AC46: =_xlfn.XLOOKUP(_xlfn.TEXTJOIN("_",TRUE,tbl_die_ordering[[#This Row],[Supplier]],tbl_die_ordering[[#This Row],[DIE NO]]),[1]Tracker!$AQ:$AQ,[1]Tracker!$AC:$AC,"") -> 45692 | AF46: =TEXT(tbl_die_ordering[[#This Row],[Die Requested Date]],"mmm") -> Jan | AG46: =_xlfn.TEXTJOIN("_",TRUE,tbl_die_ordering[[#This Row],[Supplier]],tbl_die_ordering[[#This Row],[DIE NO]]) -> PDTMC_13212-408
A47: GEX 1 | B47: =_xlfn.XLOOKUP(_xlfn.TEXTJOIN("_",TRUE,tbl_die_ordering[[#This Row],[Supplier]],tbl_die_ordering[[#This Row],[DIE NO]]),[1]Tracker!$AQ:$AQ,[1]Tracker!$W:$W,"") -> 7626-25 | C47: 16124-210 | D47: B | E47: 355X200 | F47: 45670 | G47: =_xlfn.XLOOKUP(_xlfn.TEXTJOIN("_",TRUE,tbl_die_ordering[[#This Row],[Supplier]],tbl_die_ordering[[#This Row],[DIE NO]]),[1]Tracker!$AQ:$AQ,[1]Tracker!$V:$V,"") -> 45670 | H47: LAND | I47: 1 | J47: 1 | K47: 45670 | L47: 45672 | N47: =IFERROR(IF(tbl_die_ordering[[#This Row],[Design Approved Date]]<>"",L47-K47,""),"") -> 2 | O47: 45673 | P47: 45675 | Q47: 45673 | R47: 112500258 | S47: PDTMC | T47: 45673 | W47: =_xlfn.LET( _xlpm.dieNo, tbl_die_ordering[[#This Row],[DIE NO]], _xlpm.orderNo, tbl_die_ordering[[#This Row],[Order No]], _xlpm.type, tbl_die_ordering[[#This Row],[TYPE]], _xlpm.designReceived, tbl_die_ordering[[#This Row],[Design Received Date]], _xlpm.designApproved, tbl_die_ordering[[#This Row],[Design Approved Date]], _xlpm.sim, tbl_die_ordering[[#This Row],[Sim]], _xlpm.prEntry, tbl_die_ordering[[#This Row],[PR Entry]], _xlpm.oracleEntry, tbl_die_ordering[[#This Row],[Oracle Entry]], _xlpm.ems, tbl_die_ordering[[#This Row],[Design saved to EMS FOLDER]], IF(_xlpm.dieNo = "", "", IF(_xlpm.orderNo = "", "PENDING FOR ORDERING", IF(_xlpm.type = "C", "CANCELLED", IF(_xlpm.type = "H", "HOLD", IF(_xlpm.designReceived = "", "AWAITING FOR DESIGN", IF(_xlpm.designApproved = "", IF(_xlpm.sim = "YES", "UNDER SIMULATION", "PENDING FOR DESIGN APPROVAL"), IF(_xlpm.prEntry = "", "PENDING FOR PR", IF(_xlpm.oracleEntry = "", "PENDING FOR ORACLE ENTRY", IF(_xlpm.ems = "", "PENDING FOR DESIGN TO EMS", "DONE"))))))))) ) -> DONE | X47: =IF(AND(tbl_die_ordering[[#This Row],[TYPE]]<>"C",tbl_die_ordering[[#This Row],[Design Approved Date]]<>""),tbl_die_ordering[[#This Row],[Design Approved Date]]-tbl_die_ordering[[#This Row],[Die Requested Date]],0) -> 2 | AB47: =_xlfn.XLOOKUP(_xlfn.TEXTJOIN("_",TRUE,tbl_die_ordering[[#This Row],[Supplier]],tbl_die_ordering[[#This Row],[DIE NO]]),[1]Tracker!$AQ:$AQ,[1]Tracker!$Y:$Y,"") -> 142500742 | AC47: =_xlfn.XLOOKUP(_xlfn.TEXTJOIN("_",TRUE,tbl_die_ordering[[#This Row],[Supplier]],tbl_die_ordering[[#This Row],[DIE NO]]),[1]Tracker!$AQ:$AQ,[1]Tracker!$AC:$AC,"") -> 45692 | AF47: =TEXT(tbl_die_ordering[[#This Row],[Die Requested Date]],"mmm") -> Jan | AG47: =_xlfn.TEXTJOIN("_",TRUE,tbl_die_ordering[[#This Row],[Supplier]],tbl_die_ordering[[#This Row],[DIE NO]]) -> PDTMC_16124-210
A48: GEX 1 | B48: =_xlfn.XLOOKUP(_xlfn.TEXTJOIN("_",TRUE,tbl_die_ordering[[#This Row],[Supplier]],tbl_die_ordering[[#This Row],[DIE NO]]),[1]Tracker!$AQ:$AQ,[1]Tracker!$W:$W,"") -> 7626-25 | C48: 29663-208 | D48: B | E48: 355X200 | F48: 45670 | G48: =_xlfn.XLOOKUP(_xlfn.TEXTJOIN("_",TRUE,tbl_die_ordering[[#This Row],[Supplier]],tbl_die_ordering[[#This Row],[DIE NO]]),[1]Tracker!$AQ:$AQ,[1]Tracker!$V:$V,"") -> 45670 | H48: LAND | I48: 1 | J48: 2 | K48: 45670 | L48: 45672 | N48: =IFERROR(IF(tbl_die_ordering[[#This Row],[Design Approved Date]]<>"",L48-K48,""),"") -> 2 | O48: 45673 | P48: 45675 | Q48: 45673 | R48: 112500258 | S48: PDTMC | T48: 45673 | W48: =_xlfn.LET( _xlpm.dieNo, tbl_die_ordering[[#This Row],[DIE NO]], _xlpm.orderNo, tbl_die_ordering[[#This Row],[Order No]], _xlpm.type, tbl_die_ordering[[#This Row],[TYPE]], _xlpm.designReceived, tbl_die_ordering[[#This Row],[Design Received Date]], _xlpm.designApproved, tbl_die_ordering[[#This Row],[Design Approved Date]], _xlpm.sim, tbl_die_ordering[[#This Row],[Sim]], _xlpm.prEntry, tbl_die_ordering[[#This Row],[PR Entry]], _xlpm.oracleEntry, tbl_die_ordering[[#This Row],[Oracle Entry]], _xlpm.ems, tbl_die_ordering[[#This Row],[Design saved to EMS FOLDER]], IF(_xlpm.dieNo = "", "", IF(_xlpm.orderNo = "", "PENDING FOR ORDERING", IF(_xlpm.type = "C", "CANCELLED", IF(_xlpm.type = "H", "HOLD", IF(_xlpm.designReceived = "", "AWAITING FOR DESIGN", IF(_xlpm.designApproved = "", IF(_xlpm.sim = "YES", "UNDER SIMULATION", "PENDING FOR DESIGN APPROVAL"), IF(_xlpm.prEntry = "", "PENDING FOR PR", IF(_xlpm.oracleEntry = "", "PENDING FOR ORACLE ENTRY", IF(_xlpm.ems = "", "PENDING FOR DESIGN TO EMS", "DONE"))))))))) ) -> DONE | X48: =IF(AND(tbl_die_ordering[[#This Row],[TYPE]]<>"C",tbl_die_ordering[[#This Row],[Design Approved Date]]<>""),tbl_die_ordering[[#This Row],[Design Approved Date]]-tbl_die_ordering[[#This Row],[Die Requested Date]],0) -> 2 | AB48: =_xlfn.XLOOKUP(_xlfn.TEXTJOIN("_",TRUE,tbl_die_ordering[[#This Row],[Supplier]],tbl_die_ordering[[#This Row],[DIE NO]]),[1]Tracker!$AQ:$AQ,[1]Tracker!$Y:$Y,"") -> 142500742 | AC48: =_xlfn.XLOOKUP(_xlfn.TEXTJOIN("_",TRUE,tbl_die_ordering[[#This Row],[Supplier]],tbl_die_ordering[[#This Row],[DIE NO]]),[1]Tracker!$AQ:$AQ,[1]Tracker!$AC:$AC,"") -> 45692 | AF48: =TEXT(tbl_die_ordering[[#This Row],[Die Requested Date]],"mmm") -> Jan | AG48: =_xlfn.TEXTJOIN("_",TRUE,tbl_die_ordering[[#This Row],[Supplier]],tbl_die_ordering[[#This Row],[DIE NO]]) -> PDTMC_29663-208
A49: GEX 1 | B49: =_xlfn.XLOOKUP(_xlfn.TEXTJOIN("_",TRUE,tbl_die_ordering[[#This Row],[Supplier]],tbl_die_ordering[[#This Row],[DIE NO]]),[1]Tracker!$AQ:$AQ,[1]Tracker!$W:$W,"") -> 7629-25 | C49: 13794-622 | D49: B | E49: 355X200 | F49: 45670 | G49: =_xlfn.XLOOKUP(_xlfn.TEXTJOIN("_",TRUE,tbl_die_ordering[[#This Row],[Supplier]],tbl_die_ordering[[#This Row],[DIE NO]]),[1]Tracker!$AQ:$AQ,[1]Tracker!$V:$V,"") -> 45670 | H49: AIR | I49: 1 | J49: 2 | K49: 45670 | L49: 45672 | N49: =IFERROR(IF(tbl_die_ordering[[#This Row],[Design Approved Date]]<>"",L49-K49,""),"") -> 2 | O49: 45673 | P49: 45675 | Q49: 45673 | R49: 112500258 | S49: PHOENIX | T49: 45673 | W49: =_xlfn.LET( _xlpm.dieNo, tbl_die_ordering[[#This Row],[DIE NO]], _xlpm.orderNo, tbl_die_ordering[[#This Row],[Order No]], _xlpm.type, tbl_die_ordering[[#This Row],[TYPE]], _xlpm.designReceived, tbl_die_ordering[[#This Row],[Design Received Date]], _xlpm.designApproved, tbl_die_ordering[[#This Row],[Design Approved Date]], _xlpm.sim, tbl_die_ordering[[#This Row],[Sim]], _xlpm.prEntry, tbl_die_ordering[[#This Row],[PR Entry]], _xlpm.oracleEntry, tbl_die_ordering[[#This Row],[Oracle Entry]], _xlpm.ems, tbl_die_ordering[[#This Row],[Design saved to EMS FOLDER]], IF(_xlpm.dieNo = "", "", IF(_xlpm.orderNo = "", "PENDING FOR ORDERING", IF(_xlpm.type = "C", "CANCELLED", IF(_xlpm.type = "H", "HOLD", IF(_xlpm.designReceived = "", "AWAITING FOR DESIGN", IF(_xlpm.designApproved = "", IF(_xlpm.sim = "YES", "UNDER SIMULATION", "PENDING FOR DESIGN APPROVAL"), IF(_xlpm.prEntry = "", "PENDING FOR PR", IF(_xlpm.oracleEntry = "", "PENDING FOR ORACLE ENTRY", IF(_xlpm.ems = "", "PENDING FOR DESIGN TO EMS", "DONE"))))))))) ) -> DONE | X49: =IF(AND(tbl_die_ordering[[#This Row],[TYPE]]<>"C",tbl_die_ordering[[#This Row],[Design Approved Date]]<>""),tbl_die_ordering[[#This Row],[Design Approved Date]]-tbl_die_ordering[[#This Row],[Die Requested Date]],0) -> 2 | AB49: =_xlfn.XLOOKUP(_xlfn.TEXTJOIN("_",TRUE,tbl_die_ordering[[#This Row],[Supplier]],tbl_die_ordering[[#This Row],[DIE NO]]),[1]Tracker!$AQ:$AQ,[1]Tracker!$Y:$Y,"") -> 142500535 | AC49: =_xlfn.XLOOKUP(_xlfn.TEXTJOIN("_",TRUE,tbl_die_ordering[[#This Row],[Supplier]],tbl_die_ordering[[#This Row],[DIE NO]]),[1]Tracker!$AQ:$AQ,[1]Tracker!$AC:$AC,"") -> 45684 | AF49: =TEXT(tbl_die_ordering[[#This Row],[Die Requested Date]],"mmm") -> Jan | AG49: =_xlfn.TEXTJOIN("_",TRUE,tbl_die_ordering[[#This Row],[Supplier]],tbl_die_ordering[[#This Row],[DIE NO]]) -> PHOENIX _13794-622
A50: GEX 1 | B50: =_xlfn.XLOOKUP(_xlfn.TEXTJOIN("_",TRUE,tbl_die_ordering[[#This Row],[Supplier]],tbl_die_ordering[[#This Row],[DIE NO]]),[1]Tracker!$AQ:$AQ,[1]Tracker!$W:$W,"") -> 7629-25 | C50: 23556-502 | D50: B | E50: 220X130 | F50: 45670 | G50: =_xlfn.XLOOKUP(_xlfn.TEXTJOIN("_",TRUE,tbl_die_ordering[[#This Row],[Supplier]],tbl_die_ordering[[#This Row],[DIE NO]]),[1]Tracker!$AQ:$AQ,[1]Tracker!$V:$V,"") -> 45670 | H50: AIR | I50: 0 | J50: 0 | K50: 45670 | L50: 45671 | N50: =IFERROR(IF(tbl_die_ordering[[#This Row],[Design Approved Date]]<>"",L50-K50,""),"") -> 1 | O50: 45673 | P50: 45675 | Q50: 45673 | R50: 112500258 | S50: PHOENIX | T50: 45673 | W50: =_xlfn.LET( _xlpm.dieNo, tbl_die_ordering[[#This Row],[DIE NO]], _xlpm.orderNo, tbl_die_ordering[[#This Row],[Order No]], _xlpm.type, tbl_die_ordering[[#This Row],[TYPE]], _xlpm.designReceived, tbl_die_ordering[[#This Row],[Design Received Date]], _xlpm.designApproved, tbl_die_ordering[[#This Row],[Design Approved Date]], _xlpm.sim, tbl_die_ordering[[#This Row],[Sim]], _xlpm.prEntry, tbl_die_ordering[[#This Row],[PR Entry]], _xlpm.oracleEntry, tbl_die_ordering[[#This Row],[Oracle Entry]], _xlpm.ems, tbl_die_ordering[[#This Row],[Design saved to EMS FOLDER]], IF(_xlpm.dieNo = "", "", IF(_xlpm.orderNo = "", "PENDING FOR ORDERING", IF(_xlpm.type = "C", "CANCELLED", IF(_xlpm.type = "H", "HOLD", IF(_xlpm.designReceived = "", "AWAITING FOR DESIGN", IF(_xlpm.designApproved = "", IF(_xlpm.sim = "YES", "UNDER SIMULATION", "PENDING FOR DESIGN APPROVAL"), IF(_xlpm.prEntry = "", "PENDING FOR PR", IF(_xlpm.oracleEntry = "", "PENDING FOR ORACLE ENTRY", IF(_xlpm.ems = "", "PENDING FOR DESIGN TO EMS", "DONE"))))))))) ) -> DONE | X50: =IF(AND(tbl_die_ordering[[#This Row],[TYPE]]<>"C",tbl_die_ordering[[#This Row],[Design Approved Date]]<>""),tbl_die_ordering[[#This Row],[Design Approved Date]]-tbl_die_ordering[[#This Row],[Die Requested Date]],0) -> 1 | AB50: =_xlfn.XLOOKUP(_xlfn.TEXTJOIN("_",TRUE,tbl_die_ordering[[#This Row],[Supplier]],tbl_die_ordering[[#This Row],[DIE NO]]),[1]Tracker!$AQ:$AQ,[1]Tracker!$Y:$Y,"") -> 142500535 | AC50: =_xlfn.XLOOKUP(_xlfn.TEXTJOIN("_",TRUE,tbl_die_ordering[[#This Row],[Supplier]],tbl_die_ordering[[#This Row],[DIE NO]]),[1]Tracker!$AQ:$AQ,[1]Tracker!$AC:$AC,"") -> 45684 | AF50: =TEXT(tbl_die_ordering[[#This Row],[Die Requested Date]],"mmm") -> Jan | AG50: =_xlfn.TEXTJOIN("_",TRUE,tbl_die_ordering[[#This Row],[Supplier]],tbl_die_ordering[[#This Row],[DIE NO]]) -> PHOENIX _23556-502
A51: GEX 1 | B51: =_xlfn.XLOOKUP(_xlfn.TEXTJOIN("_",TRUE,tbl_die_ordering[[#This Row],[Supplier]],tbl_die_ordering[[#This Row],[DIE NO]]),[1]Tracker!$AQ:$AQ,[1]Tracker!$W:$W,"") -> 7627-25 | C51: 29780-515 | D51: B | E51: 440X250 | F51: 45670 | G51: =_xlfn.XLOOKUP(_xlfn.TEXTJOIN("_",TRUE,tbl_die_ordering[[#This Row],[Supplier]],tbl_die_ordering[[#This Row],[DIE NO]]),[1]Tracker!$AQ:$AQ,[1]Tracker!$V:$V,"") -> 45670 | H51: AIR | I51: 2 | J51: 8 | K51: 45673 | L51: 45674 | N51: =IFERROR(IF(tbl_die_ordering[[#This Row],[Design Approved Date]]<>"",L51-K51,""),"") -> 1 | O51: 45675 | P51: 45678 | Q51: 45675 | R51: 112500277 | S51: PHOENIX | T51: 45675 | W51: =_xlfn.LET( _xlpm.dieNo, tbl_die_ordering[[#This Row],[DIE NO]], _xlpm.orderNo, tbl_die_ordering[[#This Row],[Order No]], _xlpm.type, tbl_die_ordering[[#This Row],[TYPE]], _xlpm.designReceived, tbl_die_ordering[[#This Row],[Design Received Date]], _xlpm.designApproved, tbl_die_ordering[[#This Row],[Design Approved Date]], _xlpm.sim, tbl_die_ordering[[#This Row],[Sim]], _xlpm.prEntry, tbl_die_ordering[[#This Row],[PR Entry]], _xlpm.oracleEntry, tbl_die_ordering[[#This Row],[Oracle Entry]], _xlpm.ems, tbl_die_ordering[[#This Row],[Design saved to EMS FOLDER]], IF(_xlpm.dieNo = "", "", IF(_xlpm.orderNo = "", "PENDING FOR ORDERING", IF(_xlpm.type = "C", "CANCELLED", IF(_xlpm.type = "H", "HOLD", IF(_xlpm.designReceived = "", "AWAITING FOR DESIGN", IF(_xlpm.designApproved = "", IF(_xlpm.sim = "YES", "UNDER SIMULATION", "PENDING FOR DESIGN APPROVAL"), IF(_xlpm.prEntry = "", "PENDING FOR PR", IF(_xlpm.oracleEntry = "", "PENDING FOR ORACLE ENTRY", IF(_xlpm.ems = "", "PENDING FOR DESIGN TO EMS", "DONE"))))))))) ) -> DONE | X51: =IF(AND(tbl_die_ordering[[#This Row],[TYPE]]<>"C",tbl_die_ordering[[#This Row],[Design Approved Date]]<>""),tbl_die_ordering[[#This Row],[Design Approved Date]]-tbl_die_ordering[[#This Row],[Die Requested Date]],0) -> 4 | AB51: =_xlfn.XLOOKUP(_xlfn.TEXTJOIN("_",TRUE,tbl_die_ordering[[#This Row],[Supplier]],tbl_die_ordering[[#This Row],[DIE NO]]),[1]Tracker!$AQ:$AQ,[1]Tracker!$Y:$Y,"") -> 142500921 | AC51: =_xlfn.XLOOKUP(_xlfn.TEXTJOIN("_",TRUE,tbl_die_ordering[[#This Row],[Supplier]],tbl_die_ordering[[#This Row],[DIE NO]]),[1]Tracker!$AQ:$AQ,[1]Tracker!$AC:$AC,"") -> 45694 | AF51: =TEXT(tbl_die_ordering[[#This Row],[Die Requested Date]],"mmm") -> Jan | AG51: =_xlfn.TEXTJOIN("_",TRUE,tbl_die_ordering[[#This Row],[Supplier]],tbl_die_ordering[[#This Row],[DIE NO]]) -> PHOENIX _29780-515
A52: GEX 1 | B52: =_xlfn.XLOOKUP(_xlfn.TEXTJOIN("_",TRUE,tbl_die_ordering[[#This Row],[Supplier]],tbl_die_ordering[[#This Row],[DIE NO]]),[1]Tracker!$AQ:$AQ,[1]Tracker!$W:$W,"") -> 7627-25 | C52: 29780-516 | D52: B | E52: 440X250 | F52: 45670 | G52: =_xlfn.XLOOKUP(_xlfn.TEXTJOIN("_",TRUE,tbl_die_ordering[[#This Row],[Supplier]],tbl_die_ordering[[#This Row],[DIE NO]]),[1]Tracker!$AQ:$AQ,[1]Tracker!$V:$V,"") -> 45670 | H52: AIR | I52: 2 | J52: 8 | K52: 45673 | L52: 45674 | N52: =IFERROR(IF(tbl_die_ordering[[#This Row],[Design Approved Date]]<>"",L52-K52,""),"") -> 1 | O52: 45675 | P52: 45678 | Q52: 45675 | R52: 112500277 | S52: PHOENIX | T52: 45675 | W52: =_xlfn.LET( _xlpm.dieNo, tbl_die_ordering[[#This Row],[DIE NO]], _xlpm.orderNo, tbl_die_ordering[[#This Row],[Order No]], _xlpm.type, tbl_die_ordering[[#This Row],[TYPE]], _xlpm.designReceived, tbl_die_ordering[[#This Row],[Design Received Date]], _xlpm.designApproved, tbl_die_ordering[[#This Row],[Design Approved Date]], _xlpm.sim, tbl_die_ordering[[#This Row],[Sim]], _xlpm.prEntry, tbl_die_ordering[[#This Row],[PR Entry]], _xlpm.oracleEntry, tbl_die_ordering[[#This Row],[Oracle Entry]], _xlpm.ems, tbl_die_ordering[[#This Row],[Design saved to EMS FOLDER]], IF(_xlpm.dieNo = "", "", IF(_xlpm.orderNo = "", "PENDING FOR ORDERING", IF(_xlpm.type = "C", "CANCELLED", IF(_xlpm.type = "H", "HOLD", IF(_xlpm.designReceived = "", "AWAITING FOR DESIGN", IF(_xlpm.designApproved = "", IF(_xlpm.sim = "YES", "UNDER SIMULATION", "PENDING FOR DESIGN APPROVAL"), IF(_xlpm.prEntry = "", "PENDING FOR PR", IF(_xlpm.oracleEntry = "", "PENDING FOR ORACLE ENTRY", IF(_xlpm.ems = "", "PENDING FOR DESIGN TO EMS", "DONE"))))))))) ) -> DONE | X52: =IF(AND(tbl_die_ordering[[#This Row],[TYPE]]<>"C",tbl_die_ordering[[#This Row],[Design Approved Date]]<>""),tbl_die_ordering[[#This Row],[Design Approved Date]]-tbl_die_ordering[[#This Row],[Die Requested Date]],0) -> 4 | AB52: =_xlfn.XLOOKUP(_xlfn.TEXTJOIN("_",TRUE,tbl_die_ordering[[#This Row],[Supplier]],tbl_die_ordering[[#This Row],[DIE NO]]),[1]Tracker!$AQ:$AQ,[1]Tracker!$Y:$Y,"") -> 142500921 | AC52: =_xlfn.XLOOKUP(_xlfn.TEXTJOIN("_",TRUE,tbl_die_ordering[[#This Row],[Supplier]],tbl_die_ordering[[#This Row],[DIE NO]]),[1]Tracker!$AQ:$AQ,[1]Tracker!$AC:$AC,"") -> 45694 | AF52: =TEXT(tbl_die_ordering[[#This Row],[Die Requested Date]],"mmm") -> Jan | AG52: =_xlfn.TEXTJOIN("_",TRUE,tbl_die_ordering[[#This Row],[Supplier]],tbl_die_ordering[[#This Row],[DIE NO]]) -> PHOENIX _29780-516
A53: GEX 1 | B53: =_xlfn.XLOOKUP(_xlfn.TEXTJOIN("_",TRUE,tbl_die_ordering[[#This Row],[Supplier]],tbl_die_ordering[[#This Row],[DIE NO]]),[1]Tracker!$AQ:$AQ,[1]Tracker!$W:$W,"") -> 7629-25 | C53: 27596-501 | D53: B | E53: 280X160 | F53: 45670 | G53: =_xlfn.XLOOKUP(_xlfn.TEXTJOIN("_",TRUE,tbl_die_ordering[[#This Row],[Supplier]],tbl_die_ordering[[#This Row],[DIE NO]]),[1]Tracker!$AQ:$AQ,[1]Tracker!$V:$V,"") -> 45670 | H53: AIR | I53: 0 | J53: 0 | K53: 45678 | L53: 45679 | M53: YES | N53: =IFERROR(IF(tbl_die_ordering[[#This Row],[Design Approved Date]]<>"",L53-K53,""),"") -> 1 | O53: 45680 | P53: 45684 | Q53: 45680 | R53: 112500330 | S53: EKSTEK | T53: 45680 | V53: des rec 16/01/2025 rev asked with3d model 17/01/2025 simulation resut sent to supplier and asked for revised design and 3d for re simulation. | W53: =_xlfn.LET( _xlpm.dieNo, tbl_die_ordering[[#This Row],[DIE NO]], _xlpm.orderNo, tbl_die_ordering[[#This Row],[Order No]], _xlpm.type, tbl_die_ordering[[#This Row],[TYPE]], _xlpm.designReceived, tbl_die_ordering[[#This Row],[Design Received Date]], _xlpm.designApproved, tbl_die_ordering[[#This Row],[Design Approved Date]], _xlpm.sim, tbl_die_ordering[[#This Row],[Sim]], _xlpm.prEntry, tbl_die_ordering[[#This Row],[PR Entry]], _xlpm.oracleEntry, tbl_die_ordering[[#This Row],[Oracle Entry]], _xlpm.ems, tbl_die_ordering[[#This Row],[Design saved to EMS FOLDER]], IF(_xlpm.dieNo = "", "", IF(_xlpm.orderNo = "", "PENDING FOR ORDERING", IF(_xlpm.type = "C", "CANCELLED", IF(_xlpm.type = "H", "HOLD", IF(_xlpm.designReceived = "", "AWAITING FOR DESIGN", IF(_xlpm.designApproved = "", IF(_xlpm.sim = "YES", "UNDER SIMULATION", "PENDING FOR DESIGN APPROVAL"), IF(_xlpm.prEntry = "", "PENDING FOR PR", IF(_xlpm.oracleEntry = "", "PENDING FOR ORACLE ENTRY", IF(_xlpm.ems = "", "PENDING FOR DESIGN TO EMS", "DONE"))))))))) ) -> DONE | X53: =IF(AND(tbl_die_ordering[[#This Row],[TYPE]]<>"C",tbl_die_ordering[[#This Row],[Design Approved Date]]<>""),tbl_die_ordering[[#This Row],[Design Approved Date]]-tbl_die_ordering[[#This Row],[Die Requested Date]],0) -> 9 | AB53: =_xlfn.XLOOKUP(_xlfn.TEXTJOIN("_",TRUE,tbl_die_ordering[[#This Row],[Supplier]],tbl_die_ordering[[#This Row],[DIE NO]]),[1]Tracker!$AQ:$AQ,[1]Tracker!$Y:$Y,"") -> 142500932 | AC53: =_xlfn.XLOOKUP(_xlfn.TEXTJOIN("_",TRUE,tbl_die_ordering[[#This Row],[Supplier]],tbl_die_ordering[[#This Row],[DIE NO]]),[1]Tracker!$AQ:$AQ,[1]Tracker!$AC:$AC,"") -> 45690 | AF53: =TEXT(tbl_die_ordering[[#This Row],[Die Requested Date]],"mmm") -> Jan | AG53: =_xlfn.TEXTJOIN("_",TRUE,tbl_die_ordering[[#This Row],[Supplier]],tbl_die_ordering[[#This Row],[DIE NO]]) -> EKSTEK_27596-501
A54: GEX 1 | B54: =_xlfn.XLOOKUP(_xlfn.TEXTJOIN("_",TRUE,tbl_die_ordering[[#This Row],[Supplier]],tbl_die_ordering[[#This Row],[DIE NO]]),[1]Tracker!$AQ:$AQ,[1]Tracker!$W:$W,"") -> 7630-25 | C54: 16124-209 | D54: B | E54: 355X200 | F54: 45670 | G54: =_xlfn.XLOOKUP(_xlfn.TEXTJOIN("_",TRUE,tbl_die_ordering[[#This Row],[Supplier]],tbl_die_ordering[[#This Row],[DIE NO]]),[1]Tracker!$AQ:$AQ,[1]Tracker!$V:$V,"") -> 45670 | H54: AIR | I54: 1 | J54: 1 | K54: 45672 | L54: 45677 | N54: =IFERROR(IF(tbl_die_ordering[[#This Row],[Design Approved Date]]<>"",L54-K54,""),"") -> 5 | O54: 45680 | P54: 45684 | Q54: 45680 | R54: 112500330 | S54: COMPES | T54: 45680 | W54: =_xlfn.LET( _xlpm.dieNo, tbl_die_ordering[[#This Row],[DIE NO]], _xlpm.orderNo, tbl_die_ordering[[#This Row],[Order No]], _xlpm.type, tbl_die_ordering[[#This Row],[TYPE]], _xlpm.designReceived, tbl_die_ordering[[#This Row],[Design Received Date]], _xlpm.designApproved, tbl_die_ordering[[#This Row],[Design Approved Date]], _xlpm.sim, tbl_die_ordering[[#This Row],[Sim]], _xlpm.prEntry, tbl_die_ordering[[#This Row],[PR Entry]], _xlpm.oracleEntry, tbl_die_ordering[[#This Row],[Oracle Entry]], _xlpm.ems, tbl_die_ordering[[#This Row],[Design saved to EMS FOLDER]], IF(_xlpm.dieNo = "", "", IF(_xlpm.orderNo = "", "PENDING FOR ORDERING", IF(_xlpm.type = "C", "CANCELLED", IF(_xlpm.type = "H", "HOLD", IF(_xlpm.designReceived = "", "AWAITING FOR DESIGN", IF(_xlpm.designApproved = "", IF(_xlpm.sim = "YES", "UNDER SIMULATION", "PENDING FOR DESIGN APPROVAL"), IF(_xlpm.prEntry = "", "PENDING FOR PR", IF(_xlpm.oracleEntry = "", "PENDING FOR ORACLE ENTRY", IF(_xlpm.ems = "", "PENDING FOR DESIGN TO EMS", "DONE"))))))))) ) -> DONE | X54: =IF(AND(tbl_die_ordering[[#This Row],[TYPE]]<>"C",tbl_die_ordering[[#This Row],[Design Approved Date]]<>""),tbl_die_ordering[[#This Row],[Design Approved Date]]-tbl_die_ordering[[#This Row],[Die Requested Date]],0) -> 7 | AB54: =_xlfn.XLOOKUP(_xlfn.TEXTJOIN("_",TRUE,tbl_die_ordering[[#This Row],[Supplier]],tbl_die_ordering[[#This Row],[DIE NO]]),[1]Tracker!$AQ:$AQ,[1]Tracker!$Y:$Y,"") -> 142500925 | AC54: =_xlfn.XLOOKUP(_xlfn.TEXTJOIN("_",TRUE,tbl_die_ordering[[#This Row],[Supplier]],tbl_die_ordering[[#This Row],[DIE NO]]),[1]Tracker!$AQ:$AQ,[1]Tracker!$AC:$AC,"") -> 45691 | AE54: cav increased | AF54: =TEXT(tbl_die_ordering[[#This Row],[Die Requested Date]],"mmm") -> Jan | AG54: =_xlfn.TEXTJOIN("_",TRUE,tbl_die_ordering[[#This Row],[Supplier]],tbl_die_ordering[[#This Row],[DIE NO]]) -> COMPES_16124-209
A55: GEX 1 | B55: =_xlfn.XLOOKUP(_xlfn.TEXTJOIN("_",TRUE,tbl_die_ordering[[#This Row],[Supplier]],tbl_die_ordering[[#This Row],[DIE NO]]),[1]Tracker!$AQ:$AQ,[1]Tracker!$W:$W,"") -> 7632-25 | C55: 05422-601 | D55: N | E55: 550x300 | F55: 45670 | G55: =_xlfn.XLOOKUP(_xlfn.TEXTJOIN("_",TRUE,tbl_die_ordering[[#This Row],[Supplier]],tbl_die_ordering[[#This Row],[DIE NO]]),[1]Tracker!$AQ:$AQ,[1]Tracker!$V:$V,"") -> 45670 | H55: LAND | I55: 1 | J55: 1 | K55: 45677 | L55: 45678 | N55: =IFERROR(IF(tbl_die_ordering[[#This Row],[Design Approved Date]]<>"",L55-K55,""),"") -> 1 | O55: 45680 | P55: 45684 | Q55: 45680 | R55: 112500335 | S55: PDTMC | T55: 45680 | U55: New Broadway(For gulfex) | V55: (7597-24)This die was order on 26.12.2024 to ADEX,Die order cancel from adex and send it to PDTMC by Purchage dept ON 13..01.2025_Dinesh.design received 18/01/2025 asked for revised design 18/01/2025 | W55: =_xlfn.LET( _xlpm.dieNo, tbl_die_ordering[[#This Row],[DIE NO]], _xlpm.orderNo, tbl_die_ordering[[#This Row],[Order No]], _xlpm.type, tbl_die_ordering[[#This Row],[TYPE]], _xlpm.designReceived, tbl_die_ordering[[#This Row],[Design Received Date]], _xlpm.designApproved, tbl_die_ordering[[#This Row],[Design Approved Date]], _xlpm.sim, tbl_die_ordering[[#This Row],[Sim]], _xlpm.prEntry, tbl_die_ordering[[#This Row],[PR Entry]], _xlpm.oracleEntry, tbl_die_ordering[[#This Row],[Oracle Entry]], _xlpm.ems, tbl_die_ordering[[#This Row],[Design saved to EMS FOLDER]], IF(_xlpm.dieNo = "", "", IF(_xlpm.orderNo = "", "PENDING FOR ORDERING", IF(_xlpm.type = "C", "CANCELLED", IF(_xlpm.type = "H", "HOLD", IF(_xlpm.designReceived = "", "AWAITING FOR DESIGN", IF(_xlpm.designApproved = "", IF(_xlpm.sim = "YES", "UNDER SIMULATION", "PENDING FOR DESIGN APPROVAL"), IF(_xlpm.prEntry = "", "PENDING FOR PR", IF(_xlpm.oracleEntry = "", "PENDING FOR ORACLE ENTRY", IF(_xlpm.ems = "", "PENDING FOR DESIGN TO EMS", "DONE"))))))))) ) -> DONE | X55: =IF(AND(tbl_die_ordering[[#This Row],[TYPE]]<>"C",tbl_die_ordering[[#This Row],[Design Approved Date]]<>""),tbl_die_ordering[[#This Row],[Design Approved Date]]-tbl_die_ordering[[#This Row],[Die Requested Date]],0) -> 8 | AB55: =_xlfn.XLOOKUP(_xlfn.TEXTJOIN("_",TRUE,tbl_die_ordering[[#This Row],[Supplier]],tbl_die_ordering[[#This Row],[DIE NO]]),[1]Tracker!$AQ:$AQ,[1]Tracker!$Y:$Y,"") -> 142500938 | AC55: =_xlfn.XLOOKUP(_xlfn.TEXTJOIN("_",TRUE,tbl_die_ordering[[#This Row],[Supplier]],tbl_die_ordering[[#This Row],[DIE NO]]),[1]Tracker!$AQ:$AQ,[1]Tracker!$AC:$AC,"") -> 45695 | AF55: =TEXT(tbl_die_ordering[[#This Row],[Die Requested Date]],"mmm") -> Jan | AG55: =_xlfn.TEXTJOIN("_",TRUE,tbl_die_ordering[[#This Row],[Supplier]],tbl_die_ordering[[#This Row],[DIE NO]]) -> PDTMC_05422-601
A56: GEX 1 | B56: =_xlfn.XLOOKUP(_xlfn.TEXTJOIN("_",TRUE,tbl_die_ordering[[#This Row],[Supplier]],tbl_die_ordering[[#This Row],[DIE NO]]),[1]Tracker!$AQ:$AQ,[1]Tracker!$W:$W,"") -> 7627-25 | C56: 120241-210 | D56: B | E56: 320X160 | F56: 45670 | G56: =_xlfn.XLOOKUP(_xlfn.TEXTJOIN("_",TRUE,tbl_die_ordering[[#This Row],[Supplier]],tbl_die_ordering[[#This Row],[DIE NO]]),[1]Tracker!$AQ:$AQ,[1]Tracker!$V:$V,"") -> 45670 | H56: AIR | I56: 2 | J56: 8 | K56: 45687 | L56: 45688 | M56: YES | N56: =IFERROR(IF(tbl_die_ordering[[#This Row],[Design Approved Date]]<>"",L56-K56,""),"") -> 1 | O56: 45689 | P56: 45694 | Q56: 45689 | R56: 112500467 | S56: PHOENIX | T56: 45689 | V56: design rcd 15/01/25 ask for 3d 18/01/25 3d recived 20/01/25. Die corrector not aggreed to this design. We should go for Jiangsu design. | W56: =_xlfn.LET( _xlpm.dieNo, tbl_die_ordering[[#This Row],[DIE NO]], _xlpm.orderNo, tbl_die_ordering[[#This Row],[Order No]], _xlpm.type, tbl_die_ordering[[#This Row],[TYPE]], _xlpm.designReceived, tbl_die_ordering[[#This Row],[Design Received Date]], _xlpm.designApproved, tbl_die_ordering[[#This Row],[Design Approved Date]], _xlpm.sim, tbl_die_ordering[[#This Row],[Sim]], _xlpm.prEntry, tbl_die_ordering[[#This Row],[PR Entry]], _xlpm.oracleEntry, tbl_die_ordering[[#This Row],[Oracle Entry]], _xlpm.ems, tbl_die_ordering[[#This Row],[Design saved to EMS FOLDER]], IF(_xlpm.dieNo = "", "", IF(_xlpm.orderNo = "", "PENDING FOR ORDERING", IF(_xlpm.type = "C", "CANCELLED", IF(_xlpm.type = "H", "HOLD", IF(_xlpm.designReceived = "", "AWAITING FOR DESIGN", IF(_xlpm.designApproved = "", IF(_xlpm.sim = "YES", "UNDER SIMULATION", "PENDING FOR DESIGN APPROVAL"), IF(_xlpm.prEntry = "", "PENDING FOR PR", IF(_xlpm.oracleEntry = "", "PENDING FOR ORACLE ENTRY", IF(_xlpm.ems = "", "PENDING FOR DESIGN TO EMS", "DONE"))))))))) ) -> DONE | X56: =IF(AND(tbl_die_ordering[[#This Row],[TYPE]]<>"C",tbl_die_ordering[[#This Row],[Design Approved Date]]<>""),tbl_die_ordering[[#This Row],[Design Approved Date]]-tbl_die_ordering[[#This Row],[Die Requested Date]],0) -> 18 | AB56: =_xlfn.XLOOKUP(_xlfn.TEXTJOIN("_",TRUE,tbl_die_ordering[[#This Row],[Supplier]],tbl_die_ordering[[#This Row],[DIE NO]]),[1]Tracker!$AQ:$AQ,[1]Tracker!$Y:$Y,"") -> 142501320 | AC56: =_xlfn.XLOOKUP(_xlfn.TEXTJOIN("_",TRUE,tbl_die_ordering[[#This Row],[Supplier]],tbl_die_ordering[[#This Row],[DIE NO]]),[1]Tracker!$AQ:$AQ,[1]Tracker!$AC:$AC,"") -> 45705 | AF56: =TEXT(tbl_die_ordering[[#This Row],[Die Requested Date]],"mmm") -> Jan | AG56: =_xlfn.TEXTJOIN("_",TRUE,tbl_die_ordering[[#This Row],[Supplier]],tbl_die_ordering[[#This Row],[DIE NO]]) -> PHOENIX _120241-210
A57: GEX 1 | B57: =_xlfn.XLOOKUP(_xlfn.TEXTJOIN("_",TRUE,tbl_die_ordering[[#This Row],[Supplier]],tbl_die_ordering[[#This Row],[DIE NO]]),[1]Tracker!$AQ:$AQ,[1]Tracker!$W:$W,"") -> 7627-25 | C57: 29779-501 | D57: B | E57: 320X160 | F57: 45670 | G57: =_xlfn.XLOOKUP(_xlfn.TEXTJOIN("_",TRUE,tbl_die_ordering[[#This Row],[Supplier]],tbl_die_ordering[[#This Row],[DIE NO]]),[1]Tracker!$AQ:$AQ,[1]Tracker!$V:$V,"") -> 45670 | H57: AIR | I57: 1 | J57: 3 | K57: 45687 | L57: 45688 | M57: YES | N57: =IFERROR(IF(tbl_die_ordering[[#This Row],[Design Approved Date]]<>"",L57-K57,""),"") -> 1 | O57: 45689 | P57: 45694 | Q57: 45689 | R57: 112500467 | S57: PHOENIX | T57: 45689 | V57: design receive 17/1 waiting for 14674-515 simulation resut. Simulation result not good. Ask for reivesed design. rev rcd 23/01/2025. 5:38 pm under simulation. Simulation not good ask for revison with conventional bridge 28/01/2025. | W57: =_xlfn.LET( _xlpm.dieNo, tbl_die_ordering[[#This Row],[DIE NO]], _xlpm.orderNo, tbl_die_ordering[[#This Row],[Order No]], _xlpm.type, tbl_die_ordering[[#This Row],[TYPE]], _xlpm.designReceived, tbl_die_ordering[[#This Row],[Design Received Date]], _xlpm.designApproved, tbl_die_ordering[[#This Row],[Design Approved Date]], _xlpm.sim, tbl_die_ordering[[#This Row],[Sim]], _xlpm.prEntry, tbl_die_ordering[[#This Row],[PR Entry]], _xlpm.oracleEntry, tbl_die_ordering[[#This Row],[Oracle Entry]], _xlpm.ems, tbl_die_ordering[[#This Row],[Design saved to EMS FOLDER]], IF(_xlpm.dieNo = "", "", IF(_xlpm.orderNo = "", "PENDING FOR ORDERING", IF(_xlpm.type = "C", "CANCELLED", IF(_xlpm.type = "H", "HOLD", IF(_xlpm.designReceived = "", "AWAITING FOR DESIGN", IF(_xlpm.designApproved = "", IF(_xlpm.sim = "YES", "UNDER SIMULATION", "PENDING FOR DESIGN APPROVAL"), IF(_xlpm.prEntry = "", "PENDING FOR PR", IF(_xlpm.oracleEntry = "", "PENDING FOR ORACLE ENTRY", IF(_xlpm.ems = "", "PENDING FOR DESIGN TO EMS", "DONE"))))))))) ) -> DONE | X57: =IF(AND(tbl_die_ordering[[#This Row],[TYPE]]<>"C",tbl_die_ordering[[#This Row],[Design Approved Date]]<>""),tbl_die_ordering[[#This Row],[Design Approved Date]]-tbl_die_ordering[[#This Row],[Die Requested Date]],0) -> 18 | AB57: =_xlfn.XLOOKUP(_xlfn.TEXTJOIN("_",TRUE,tbl_die_ordering[[#This Row],[Supplier]],tbl_die_ordering[[#This Row],[DIE NO]]),[1]Tracker!$AQ:$AQ,[1]Tracker!$Y:$Y,"") -> 142501320 | AC57: =_xlfn.XLOOKUP(_xlfn.TEXTJOIN("_",TRUE,tbl_die_ordering[[#This Row],[Supplier]],tbl_die_ordering[[#This Row],[DIE NO]]),[1]Tracker!$AQ:$AQ,[1]Tracker!$AC:$AC,"") -> 45705 | AF57: =TEXT(tbl_die_ordering[[#This Row],[Die Requested Date]],"mmm") -> Jan | AG57: =_xlfn.TEXTJOIN("_",TRUE,tbl_die_ordering[[#This Row],[Supplier]],tbl_die_ordering[[#This Row],[DIE NO]]) -> PHOENIX _29779-501
A58: GEX 1 | B58: =_xlfn.XLOOKUP(_xlfn.TEXTJOIN("_",TRUE,tbl_die_ordering[[#This Row],[Supplier]],tbl_die_ordering[[#This Row],[DIE NO]]),[1]Tracker!$AQ:$AQ,[1]Tracker!$W:$W,"") -> 7627-25 | C58: 24817-501 | D58: B | E58: 280x160 | F58: 45670 | G58: =_xlfn.XLOOKUP(_xlfn.TEXTJOIN("_",TRUE,tbl_die_ordering[[#This Row],[Supplier]],tbl_die_ordering[[#This Row],[DIE NO]]),[1]Tracker!$AQ:$AQ,[1]Tracker!$V:$V,"") -> 45670 | H58: AIR | I58: 0 | J58: 0 | K58: 45679 | L58: 45699 | M58: YES | N58: =IFERROR(IF(tbl_die_ordering[[#This Row],[Design Approved Date]]<>"",L58-K58,""),"") -> 20 | O58: 45700 | P58: 45703 | Q58: 45700 | R58: 112500644 | S58: PHOENIX | T58: 45700 | V58: des received 22/01/2025 under simulation. Simulation result not good ask for revision 29/01/25, revision 3d model received 07.02.2025 | W58: =_xlfn.LET( _xlpm.dieNo, tbl_die_ordering[[#This Row],[DIE NO]], _xlpm.orderNo, tbl_die_ordering[[#This Row],[Order No]], _xlpm.type, tbl_die_ordering[[#This Row],[TYPE]], _xlpm.designReceived, tbl_die_ordering[[#This Row],[Design Received Date]], _xlpm.designApproved, tbl_die_ordering[[#This Row],[Design Approved Date]], _xlpm.sim, tbl_die_ordering[[#This Row],[Sim]], _xlpm.prEntry, tbl_die_ordering[[#This Row],[PR Entry]], _xlpm.oracleEntry, tbl_die_ordering[[#This Row],[Oracle Entry]], _xlpm.ems, tbl_die_ordering[[#This Row],[Design saved to EMS FOLDER]], IF(_xlpm.dieNo = "", "", IF(_xlpm.orderNo = "", "PENDING FOR ORDERING", IF(_xlpm.type = "C", "CANCELLED", IF(_xlpm.type = "H", "HOLD", IF(_xlpm.designReceived = "", "AWAITING FOR DESIGN", IF(_xlpm.designApproved = "", IF(_xlpm.sim = "YES", "UNDER SIMULATION", "PENDING FOR DESIGN APPROVAL"), IF(_xlpm.prEntry = "", "PENDING FOR PR", IF(_xlpm.oracleEntry = "", "PENDING FOR ORACLE ENTRY", IF(_xlpm.ems = "", "PENDING FOR DESIGN TO EMS", "DONE"))))))))) ) -> DONE | X58: =IF(AND(tbl_die_ordering[[#This Row],[TYPE]]<>"C",tbl_die_ordering[[#This Row],[Design Approved Date]]<>""),tbl_die_ordering[[#This Row],[Design Approved Date]]-tbl_die_ordering[[#This Row],[Die Requested Date]],0) -> 29 | AB58: =_xlfn.XLOOKUP(_xlfn.TEXTJOIN("_",TRUE,tbl_die_ordering[[#This Row],[Supplier]],tbl_die_ordering[[#This Row],[DIE NO]]),[1]Tracker!$AQ:$AQ,[1]Tracker!$Y:$Y,"") -> 142501617 | AC58: =_xlfn.XLOOKUP(_xlfn.TEXTJOIN("_",TRUE,tbl_die_ordering[[#This Row],[Supplier]],tbl_die_ordering[[#This Row],[DIE NO]]),[1]Tracker!$AQ:$AQ,[1]Tracker!$AC:$AC,"") -> 45719 | AE58: cav increased | AF58: =TEXT(tbl_die_ordering[[#This Row],[Die Requested Date]],"mmm") -> Jan | AG58: =_xlfn.TEXTJOIN("_",TRUE,tbl_die_ordering[[#This Row],[Supplier]],tbl_die_ordering[[#This Row],[DIE NO]]) -> PHOENIX _24817-501
A59: GEX 1 | B59: =_xlfn.XLOOKUP(_xlfn.TEXTJOIN("_",TRUE,tbl_die_ordering[[#This Row],[Supplier]],tbl_die_ordering[[#This Row],[DIE NO]]),[1]Tracker!$AQ:$AQ,[1]Tracker!$W:$W,"") -> 7627-25 | C59: 29663-601 | D59: B | E59: 450X250 | F59: 45670 | G59: =_xlfn.XLOOKUP(_xlfn.TEXTJOIN("_",TRUE,tbl_die_ordering[[#This Row],[Supplier]],tbl_die_ordering[[#This Row],[DIE NO]]),[1]Tracker!$AQ:$AQ,[1]Tracker!$V:$V,"") -> 45670 | H59: AIR | I59: 1 | J59: 3 | K59: 45687 | L59: 45699 | M59: YES | N59: =IFERROR(IF(tbl_die_ordering[[#This Row],[Design Approved Date]]<>"",L59-K59,""),"") -> 12 | O59: 45700 | P59: 45703 | Q59: 45700 | R59: 112500644 | S59: PHOENIX | T59: 45700 | V59: design receive 17/01/25 asked revi 20/01/2025. rev rcd 22/01/25. 7:9 pm. Under simulation. simulation result not satisfiable ask for revision 28/1 rev and stp received on 29/01/2025. under simulation. | W59: =_xlfn.LET( _xlpm.dieNo, tbl_die_ordering[[#This Row],[DIE NO]], _xlpm.orderNo, tbl_die_ordering[[#This Row],[Order No]], _xlpm.type, tbl_die_ordering[[#This Row],[TYPE]], _xlpm.designReceived, tbl_die_ordering[[#This Row],[Design Received Date]], _xlpm.designApproved, tbl_die_ordering[[#This Row],[Design Approved Date]], _xlpm.sim, tbl_die_ordering[[#This Row],[Sim]], _xlpm.prEntry, tbl_die_ordering[[#This Row],[PR Entry]], _xlpm.oracleEntry, tbl_die_ordering[[#This Row],[Oracle Entry]], _xlpm.ems, tbl_die_ordering[[#This Row],[Design saved to EMS FOLDER]], IF(_xlpm.dieNo = "", "", IF(_xlpm.orderNo = "", "PENDING FOR ORDERING", IF(_xlpm.type = "C", "CANCELLED", IF(_xlpm.type = "H", "HOLD", IF(_xlpm.designReceived = "", "AWAITING FOR DESIGN", IF(_xlpm.designApproved = "", IF(_xlpm.sim = "YES", "UNDER SIMULATION", "PENDING FOR DESIGN APPROVAL"), IF(_xlpm.prEntry = "", "PENDING FOR PR", IF(_xlpm.oracleEntry = "", "PENDING FOR ORACLE ENTRY", IF(_xlpm.ems = "", "PENDING FOR DESIGN TO EMS", "DONE"))))))))) ) -> DONE | X59: =IF(AND(tbl_die_ordering[[#This Row],[TYPE]]<>"C",tbl_die_ordering[[#This Row],[Design Approved Date]]<>""),tbl_die_ordering[[#This Row],[Design Approved Date]]-tbl_die_ordering[[#This Row],[Die Requested Date]],0) -> 29 | AB59: =_xlfn.XLOOKUP(_xlfn.TEXTJOIN("_",TRUE,tbl_die_ordering[[#This Row],[Supplier]],tbl_die_ordering[[#This Row],[DIE NO]]),[1]Tracker!$AQ:$AQ,[1]Tracker!$Y:$Y,"") -> 142501618 | AC59: =_xlfn.XLOOKUP(_xlfn.TEXTJOIN("_",TRUE,tbl_die_ordering[[#This Row],[Supplier]],tbl_die_ordering[[#This Row],[DIE NO]]),[1]Tracker!$AQ:$AQ,[1]Tracker!$AC:$AC,"") -> 45726 | AE59: cav increased | AF59: =TEXT(tbl_die_ordering[[#This Row],[Die Requested Date]],"mmm") -> Jan | AG59: =_xlfn.TEXTJOIN("_",TRUE,tbl_die_ordering[[#This Row],[Supplier]],tbl_die_ordering[[#This Row],[DIE NO]]) -> PHOENIX _29663-601
A60: GEX 1 | B60: =_xlfn.XLOOKUP(_xlfn.TEXTJOIN("_",TRUE,tbl_die_ordering[[#This Row],[Supplier]],tbl_die_ordering[[#This Row],[DIE NO]]),[1]Tracker!$AQ:$AQ,[1]Tracker!$W:$W,"") -> 7630-25 | C60: 29713-501 | D60: B | E60: 320X160 | F60: 45670 | G60: =_xlfn.XLOOKUP(_xlfn.TEXTJOIN("_",TRUE,tbl_die_ordering[[#This Row],[Supplier]],tbl_die_ordering[[#This Row],[DIE NO]]),[1]Tracker!$AQ:$AQ,[1]Tracker!$V:$V,"") -> 45670 | H60: AIR | I60: 1 | J60: 3 | K60: 45680 | L60: 45699 | M60: YES | N60: =IFERROR(IF(tbl_die_ordering[[#This Row],[Design Approved Date]]<>"",L60-K60,""),"") -> 19 | O60: 45700 | P60: 45703 | Q60: 45700 | R60: 112500644 | S60: COMPES | T60: 45700 | V60: des rcd 21/01 entry dia more mail sent to supplier 23/01/2025. simulation result and runout are not satisfying. Ask for revision 29/01/2025, rev received 03.02.2025 | W60: =_xlfn.LET( _xlpm.dieNo, tbl_die_ordering[[#This Row],[DIE NO]], _xlpm.orderNo, tbl_die_ordering[[#This Row],[Order No]], _xlpm.type, tbl_die_ordering[[#This Row],[TYPE]], _xlpm.designReceived, tbl_die_ordering[[#This Row],[Design Received Date]], _xlpm.designApproved, tbl_die_ordering[[#This Row],[Design Approved Date]], _xlpm.sim, tbl_die_ordering[[#This Row],[Sim]], _xlpm.prEntry, tbl_die_ordering[[#This Row],[PR Entry]], _xlpm.oracleEntry, tbl_die_ordering[[#This Row],[Oracle Entry]], _xlpm.ems, tbl_die_ordering[[#This Row],[Design saved to EMS FOLDER]], IF(_xlpm.dieNo = "", "", IF(_xlpm.orderNo = "", "PENDING FOR ORDERING", IF(_xlpm.type = "C", "CANCELLED", IF(_xlpm.type = "H", "HOLD", IF(_xlpm.designReceived = "", "AWAITING FOR DESIGN", IF(_xlpm.designApproved = "", IF(_xlpm.sim = "YES", "UNDER SIMULATION", "PENDING FOR DESIGN APPROVAL"), IF(_xlpm.prEntry = "", "PENDING FOR PR", IF(_xlpm.oracleEntry = "", "PENDING FOR ORACLE ENTRY", IF(_xlpm.ems = "", "PENDING FOR DESIGN TO EMS", "DONE"))))))))) ) -> DONE | X60: =IF(AND(tbl_die_ordering[[#This Row],[TYPE]]<>"C",tbl_die_ordering[[#This Row],[Design Approved Date]]<>""),tbl_die_ordering[[#This Row],[Design Approved Date]]-tbl_die_ordering[[#This Row],[Die Requested Date]],0) -> 29 | AA60: MILL,, POWDER, ANODIZING | AB60: =_xlfn.XLOOKUP(_xlfn.TEXTJOIN("_",TRUE,tbl_die_ordering[[#This Row],[Supplier]],tbl_die_ordering[[#This Row],[DIE NO]]),[1]Tracker!$AQ:$AQ,[1]Tracker!$Y:$Y,"") -> 142501644 | AC60: =_xlfn.XLOOKUP(_xlfn.TEXTJOIN("_",TRUE,tbl_die_ordering[[#This Row],[Supplier]],tbl_die_ordering[[#This Row],[DIE NO]]),[1]Tracker!$AQ:$AQ,[1]Tracker!$AC:$AC,"") -> 45713 | AF60: =TEXT(tbl_die_ordering[[#This Row],[Die Requested Date]],"mmm") -> Jan | AG60: =_xlfn.TEXTJOIN("_",TRUE,tbl_die_ordering[[#This Row],[Supplier]],tbl_die_ordering[[#This Row],[DIE NO]]) -> COMPES_29713-501
A61: GEX 2 | B61: =_xlfn.XLOOKUP(_xlfn.TEXTJOIN("_",TRUE,tbl_die_ordering[[#This Row],[Supplier]],tbl_die_ordering[[#This Row],[DIE NO]]),[1]Tracker!$AQ:$AQ,[1]Tracker!$W:$W,"") -> 7624-25 | C61: 051118-3522 | D61: B | E61: 450X260 | F61: 45670 | G61: =_xlfn.XLOOKUP(_xlfn.TEXTJOIN("_",TRUE,tbl_die_ordering[[#This Row],[Supplier]],tbl_die_ordering[[#This Row],[DIE NO]]),[1]Tracker!$AQ:$AQ,[1]Tracker!$V:$V,"") -> 45670 | H61: LAND | I61: 4 | J61: 4 | K61: 45672 | L61: 45672 | N61: =IFERROR(IF(tbl_die_ordering[[#This Row],[Design Approved Date]]<>"",L61-K61,""),"") -> 0 | O61: 45672 | P61: 45678 | Q61: 45672 | R61: 1300001100 | S61: PDTMC | T61: 45678 | W61: =_xlfn.LET( _xlpm.dieNo, tbl_die_ordering[[#This Row],[DIE NO]], _xlpm.orderNo, tbl_die_ordering[[#This Row],[Order No]], _xlpm.type, tbl_die_ordering[[#This Row],[TYPE]], _xlpm.designReceived, tbl_die_ordering[[#This Row],[Design Received Date]], _xlpm.designApproved, tbl_die_ordering[[#This Row],[Design Approved Date]], _xlpm.sim, tbl_die_ordering[[#This Row],[Sim]], _xlpm.prEntry, tbl_die_ordering[[#This Row],[PR Entry]], _xlpm.oracleEntry, tbl_die_ordering[[#This Row],[Oracle Entry]], _xlpm.ems, tbl_die_ordering[[#This Row],[Design saved to EMS FOLDER]], IF(_xlpm.dieNo = "", "", IF(_xlpm.orderNo = "", "PENDING FOR ORDERING", IF(_xlpm.type = "C", "CANCELLED", IF(_xlpm.type = "H", "HOLD", IF(_xlpm.designReceived = "", "AWAITING FOR DESIGN", IF(_xlpm.designApproved = "", IF(_xlpm.sim = "YES", "UNDER SIMULATION", "PENDING FOR DESIGN APPROVAL"), IF(_xlpm.prEntry = "", "PENDING FOR PR", IF(_xlpm.oracleEntry = "", "PENDING FOR ORACLE ENTRY", IF(_xlpm.ems = "", "PENDING FOR DESIGN TO EMS", "DONE"))))))))) ) -> DONE | X61: =IF(AND(tbl_die_ordering[[#This Row],[TYPE]]<>"C",tbl_die_ordering[[#This Row],[Design Approved Date]]<>""),tbl_die_ordering[[#This Row],[Design Approved Date]]-tbl_die_ordering[[#This Row],[Die Requested Date]],0) -> 2 | AB61: =_xlfn.XLOOKUP(_xlfn.TEXTJOIN("_",TRUE,tbl_die_ordering[[#This Row],[Supplier]],tbl_die_ordering[[#This Row],[DIE NO]]),[1]Tracker!$AQ:$AQ,[1]Tracker!$Y:$Y,"") -> M087 | AC61: =_xlfn.XLOOKUP(_xlfn.TEXTJOIN("_",TRUE,tbl_die_ordering[[#This Row],[Supplier]],tbl_die_ordering[[#This Row],[DIE NO]]),[1]Tracker!$AQ:$AQ,[1]Tracker!$AC:$AC,"") -> 45688 | AF61: =TEXT(tbl_die_ordering[[#This Row],[Die Requested Date]],"mmm") -> Jan | AG61: =_xlfn.TEXTJOIN("_",TRUE,tbl_die_ordering[[#This Row],[Supplier]],tbl_die_ordering[[#This Row],[DIE NO]]) -> PDTMC_051118-3522
A62: GEX 2 | B62: =_xlfn.XLOOKUP(_xlfn.TEXTJOIN("_",TRUE,tbl_die_ordering[[#This Row],[Supplier]],tbl_die_ordering[[#This Row],[DIE NO]]),[1]Tracker!$AQ:$AQ,[1]Tracker!$W:$W,"") -> 7624-25 | C62: 051118-3523 | D62: B | E62: 450X260 | F62: 45670 | G62: =_xlfn.XLOOKUP(_xlfn.TEXTJOIN("_",TRUE,tbl_die_ordering[[#This Row],[Supplier]],tbl_die_ordering[[#This Row],[DIE NO]]),[1]Tracker!$AQ:$AQ,[1]Tracker!$V:$V,"") -> 45670 | H62: LAND | I62: 4 | J62: 4 | K62: 45672 | L62: 45672 | N62: =IFERROR(IF(tbl_die_ordering[[#This Row],[Design Approved Date]]<>"",L62-K62,""),"") -> 0 | O62: 45675 | P62: 45678 | Q62: 45675 | R62: 1300001103 | S62: PDTMC | T62: 45678 | W62: =_xlfn.LET( _xlpm.dieNo, tbl_die_ordering[[#This Row],[DIE NO]], _xlpm.orderNo, tbl_die_ordering[[#This Row],[Order No]], _xlpm.type, tbl_die_ordering[[#This Row],[TYPE]], _xlpm.designReceived, tbl_die_ordering[[#This Row],[Design Received Date]], _xlpm.designApproved, tbl_die_ordering[[#This Row],[Design Approved Date]], _xlpm.sim, tbl_die_ordering[[#This Row],[Sim]], _xlpm.prEntry, tbl_die_ordering[[#This Row],[PR Entry]], _xlpm.oracleEntry, tbl_die_ordering[[#This Row],[Oracle Entry]], _xlpm.ems, tbl_die_ordering[[#This Row],[Design saved to EMS FOLDER]], IF(_xlpm.dieNo = "", "", IF(_xlpm.orderNo = "", "PENDING FOR ORDERING", IF(_xlpm.type = "C", "CANCELLED", IF(_xlpm.type = "H", "HOLD", IF(_xlpm.designReceived = "", "AWAITING FOR DESIGN", IF(_xlpm.designApproved = "", IF(_xlpm.sim = "YES", "UNDER SIMULATION", "PENDING FOR DESIGN APPROVAL"), IF(_xlpm.prEntry = "", "PENDING FOR PR", IF(_xlpm.oracleEntry = "", "PENDING FOR ORACLE ENTRY", IF(_xlpm.ems = "", "PENDING FOR DESIGN TO EMS", "DONE"))))))))) ) -> DONE | X62: =IF(AND(tbl_die_ordering[[#This Row],[TYPE]]<>"C",tbl_die_ordering[[#This Row],[Design Approved Date]]<>""),tbl_die_ordering[[#This Row],[Design Approved Date]]-tbl_die_ordering[[#This Row],[Die Requested Date]],0) -> 2 | AB62: =_xlfn.XLOOKUP(_xlfn.TEXTJOIN("_",TRUE,tbl_die_ordering[[#This Row],[Supplier]],tbl_die_ordering[[#This Row],[DIE NO]]),[1]Tracker!$AQ:$AQ,[1]Tracker!$Y:$Y,"") -> M180 | AC62: =_xlfn.XLOOKUP(_xlfn.TEXTJOIN("_",TRUE,tbl_die_ordering[[#This Row],[Supplier]],tbl_die_ordering[[#This Row],[DIE NO]]),[1]Tracker!$AQ:$AQ,[1]Tracker!$AC:$AC,"") -> 45691 | AF62: =TEXT(tbl_die_ordering[[#This Row],[Die Requested Date]],"mmm") -> Jan | AG62: =_xlfn.TEXTJOIN("_",TRUE,tbl_die_ordering[[#This Row],[Supplier]],tbl_die_ordering[[#This Row],[DIE NO]]) -> PDTMC_051118-3523
A63: GEX 2 | B63: =_xlfn.XLOOKUP(_xlfn.TEXTJOIN("_",TRUE,tbl_die_ordering[[#This Row],[Supplier]],tbl_die_ordering[[#This Row],[DIE NO]]),[1]Tracker!$AQ:$AQ,[1]Tracker!$W:$W,"") -> 7625-25 | C63: 009153-2503 | D63: B | E63: 280X160 | F63: 45670 | G63: =_xlfn.XLOOKUP(_xlfn.TEXTJOIN("_",TRUE,tbl_die_ordering[[#This Row],[Supplier]],tbl_die_ordering[[#This Row],[DIE NO]]),[1]Tracker!$AQ:$AQ,[1]Tracker!$V:$V,"") -> 45670 | H63: AIR | I63: 0 | J63: 0 | K63: 45672 | L63: 45672 | N63: =IFERROR(IF(tbl_die_ordering[[#This Row],[Design Approved Date]]<>"",L63-K63,""),"") -> 0 | O63: 45675 | P63: 45678 | Q63: 45675 | R63: 1300001103 | S63: PHOENIX | T63: 45678 | W63: =_xlfn.LET( _xlpm.dieNo, tbl_die_ordering[[#This Row],[DIE NO]], _xlpm.orderNo, tbl_die_ordering[[#This Row],[Order No]], _xlpm.type, tbl_die_ordering[[#This Row],[TYPE]], _xlpm.designReceived, tbl_die_ordering[[#This Row],[Design Received Date]], _xlpm.designApproved, tbl_die_ordering[[#This Row],[Design Approved Date]], _xlpm.sim, tbl_die_ordering[[#This Row],[Sim]], _xlpm.prEntry, tbl_die_ordering[[#This Row],[PR Entry]], _xlpm.oracleEntry, tbl_die_ordering[[#This Row],[Oracle Entry]], _xlpm.ems, tbl_die_ordering[[#This Row],[Design saved to EMS FOLDER]], IF(_xlpm.dieNo = "", "", IF(_xlpm.orderNo = "", "PENDING FOR ORDERING", IF(_xlpm.type = "C", "CANCELLED", IF(_xlpm.type = "H", "HOLD", IF(_xlpm.designReceived = "", "AWAITING FOR DESIGN", IF(_xlpm.designApproved = "", IF(_xlpm.sim = "YES", "UNDER SIMULATION", "PENDING FOR DESIGN APPROVAL"), IF(_xlpm.prEntry = "", "PENDING FOR PR", IF(_xlpm.oracleEntry = "", "PENDING FOR ORACLE ENTRY", IF(_xlpm.ems = "", "PENDING FOR DESIGN TO EMS", "DONE"))))))))) ) -> DONE | X63: =IF(AND(tbl_die_ordering[[#This Row],[TYPE]]<>"C",tbl_die_ordering[[#This Row],[Design Approved Date]]<>""),tbl_die_ordering[[#This Row],[Design Approved Date]]-tbl_die_ordering[[#This Row],[Die Requested Date]],0) -> 2 | AB63: =_xlfn.XLOOKUP(_xlfn.TEXTJOIN("_",TRUE,tbl_die_ordering[[#This Row],[Supplier]],tbl_die_ordering[[#This Row],[DIE NO]]),[1]Tracker!$AQ:$AQ,[1]Tracker!$Y:$Y,"") -> 242500661 | AC63: =_xlfn.XLOOKUP(_xlfn.TEXTJOIN("_",TRUE,tbl_die_ordering[[#This Row],[Supplier]],tbl_die_ordering[[#This Row],[DIE NO]]),[1]Tracker!$AQ:$AQ,[1]Tracker!$AC:$AC,"") -> 45694 | AF63: =TEXT(tbl_die_ordering[[#This Row],[Die Requested Date]],"mmm") -> Jan | AG63: =_xlfn.TEXTJOIN("_",TRUE,tbl_die_ordering[[#This Row],[Supplier]],tbl_die_ordering[[#This Row],[DIE NO]]) -> PHOENIX _009153-2503
A64: GEX 2 | B64: =_xlfn.XLOOKUP(_xlfn.TEXTJOIN("_",TRUE,tbl_die_ordering[[#This Row],[Supplier]],tbl_die_ordering[[#This Row],[DIE NO]]),[1]Tracker!$AQ:$AQ,[1]Tracker!$W:$W,"") -> 7625-25 | C64: 022161-3501 | D64: B | E64: 355X200 | F64: 45670 | G64: =_xlfn.XLOOKUP(_xlfn.TEXTJOIN("_",TRUE,tbl_die_ordering[[#This Row],[Supplier]],tbl_die_ordering[[#This Row],[DIE NO]]),[1]Tracker!$AQ:$AQ,[1]Tracker!$V:$V,"") -> 45670 | H64: AIR | I64: 0 | J64: 0 | K64: 45670 | L64: 45672 | N64: =IFERROR(IF(tbl_die_ordering[[#This Row],[Design Approved Date]]<>"",L64-K64,""),"") -> 2 | O64: 45675 | P64: 45678 | Q64: 45675 | R64: 1300001103 | S64: PHOENIX | T64: 45678 | W64: =_xlfn.LET( _xlpm.dieNo, tbl_die_ordering[[#This Row],[DIE NO]], _xlpm.orderNo, tbl_die_ordering[[#This Row],[Order No]], _xlpm.type, tbl_die_ordering[[#This Row],[TYPE]], _xlpm.designReceived, tbl_die_ordering[[#This Row],[Design Received Date]], _xlpm.designApproved, tbl_die_ordering[[#This Row],[Design Approved Date]], _xlpm.sim, tbl_die_ordering[[#This Row],[Sim]], _xlpm.prEntry, tbl_die_ordering[[#This Row],[PR Entry]], _xlpm.oracleEntry, tbl_die_ordering[[#This Row],[Oracle Entry]], _xlpm.ems, tbl_die_ordering[[#This Row],[Design saved to EMS FOLDER]], IF(_xlpm.dieNo = "", "", IF(_xlpm.orderNo = "", "PENDING FOR ORDERING", IF(_xlpm.type = "C", "CANCELLED", IF(_xlpm.type = "H", "HOLD", IF(_xlpm.designReceived = "", "AWAITING FOR DESIGN", IF(_xlpm.designApproved = "", IF(_xlpm.sim = "YES", "UNDER SIMULATION", "PENDING FOR DESIGN APPROVAL"), IF(_xlpm.prEntry = "", "PENDING FOR PR", IF(_xlpm.oracleEntry = "", "PENDING FOR ORACLE ENTRY", IF(_xlpm.ems = "", "PENDING FOR DESIGN TO EMS", "DONE"))))))))) ) -> DONE | X64: =IF(AND(tbl_die_ordering[[#This Row],[TYPE]]<>"C",tbl_die_ordering[[#This Row],[Design Approved Date]]<>""),tbl_die_ordering[[#This Row],[Design Approved Date]]-tbl_die_ordering[[#This Row],[Die Requested Date]],0) -> 2 | AB64: =_xlfn.XLOOKUP(_xlfn.TEXTJOIN("_",TRUE,tbl_die_ordering[[#This Row],[Supplier]],tbl_die_ordering[[#This Row],[DIE NO]]),[1]Tracker!$AQ:$AQ,[1]Tracker!$Y:$Y,"") -> 242500661 | AC64: =_xlfn.XLOOKUP(_xlfn.TEXTJOIN("_",TRUE,tbl_die_ordering[[#This Row],[Supplier]],tbl_die_ordering[[#This Row],[DIE NO]]),[1]Tracker!$AQ:$AQ,[1]Tracker!$AC:$AC,"") -> 45694 | AF64: =TEXT(tbl_die_ordering[[#This Row],[Die Requested Date]],"mmm") -> Jan | AG64: =_xlfn.TEXTJOIN("_",TRUE,tbl_die_ordering[[#This Row],[Supplier]],tbl_die_ordering[[#This Row],[DIE NO]]) -> PHOENIX _022161-3501
A65: GEX 2 | B65: =_xlfn.XLOOKUP(_xlfn.TEXTJOIN("_",TRUE,tbl_die_ordering[[#This Row],[Supplier]],tbl_die_ordering[[#This Row],[DIE NO]]),[1]Tracker!$AQ:$AQ,[1]Tracker!$W:$W,"") -> 7631-25 | C65: 007122-2503 | D65: B | E65: 280X160 | F65: 45670 | G65: =_xlfn.XLOOKUP(_xlfn.TEXTJOIN("_",TRUE,tbl_die_ordering[[#This Row],[Supplier]],tbl_die_ordering[[#This Row],[DIE NO]]),[1]Tracker!$AQ:$AQ,[1]Tracker!$V:$V,"") -> 45670 | H65: LAND | I65: 0 | J65: 0 | K65: 45670 | L65: 45672 | N65: =IFERROR(IF(tbl_die_ordering[[#This Row],[Design Approved Date]]<>"",L65-K65,""),"") -> 2 | O65: 45675 | P65: 45678 | Q65: 45675 | R65: 1300001103 | S65: PDTMC | T65: 45678 | W65: =_xlfn.LET( _xlpm.dieNo, tbl_die_ordering[[#This Row],[DIE NO]], _xlpm.orderNo, tbl_die_ordering[[#This Row],[Order No]], _xlpm.type, tbl_die_ordering[[#This Row],[TYPE]], _xlpm.designReceived, tbl_die_ordering[[#This Row],[Design Received Date]], _xlpm.designApproved, tbl_die_ordering[[#This Row],[Design Approved Date]], _xlpm.sim, tbl_die_ordering[[#This Row],[Sim]], _xlpm.prEntry, tbl_die_ordering[[#This Row],[PR Entry]], _xlpm.oracleEntry, tbl_die_ordering[[#This Row],[Oracle Entry]], _xlpm.ems, tbl_die_ordering[[#This Row],[Design saved to EMS FOLDER]], IF(_xlpm.dieNo = "", "", IF(_xlpm.orderNo = "", "PENDING FOR ORDERING", IF(_xlpm.type = "C", "CANCELLED", IF(_xlpm.type = "H", "HOLD", IF(_xlpm.designReceived = "", "AWAITING FOR DESIGN", IF(_xlpm.designApproved = "", IF(_xlpm.sim = "YES", "UNDER SIMULATION", "PENDING FOR DESIGN APPROVAL"), IF(_xlpm.prEntry = "", "PENDING FOR PR", IF(_xlpm.oracleEntry = "", "PENDING FOR ORACLE ENTRY", IF(_xlpm.ems = "", "PENDING FOR DESIGN TO EMS", "DONE"))))))))) ) -> DONE | X65: =IF(AND(tbl_die_ordering[[#This Row],[TYPE]]<>"C",tbl_die_ordering[[#This Row],[Design Approved Date]]<>""),tbl_die_ordering[[#This Row],[Design Approved Date]]-tbl_die_ordering[[#This Row],[Die Requested Date]],0) -> 2 | AB65: =_xlfn.XLOOKUP(_xlfn.TEXTJOIN("_",TRUE,tbl_die_ordering[[#This Row],[Supplier]],tbl_die_ordering[[#This Row],[DIE NO]]),[1]Tracker!$AQ:$AQ,[1]Tracker!$Y:$Y,"") -> 242502857 | AC65: =_xlfn.XLOOKUP(_xlfn.TEXTJOIN("_",TRUE,tbl_die_ordering[[#This Row],[Supplier]],tbl_die_ordering[[#This Row],[DIE NO]]),[1]Tracker!$AQ:$AQ,[1]Tracker!$AC:$AC,"") -> 45694 | AF65: =TEXT(tbl_die_ordering[[#This Row],[Die Requested Date]],"mmm") -> Jan | AG65: =_xlfn.TEXTJOIN("_",TRUE,tbl_die_ordering[[#This Row],[Supplier]],tbl_die_ordering[[#This Row],[DIE NO]]) -> PDTMC_007122-2503
A66: GEX 2 | B66: =_xlfn.XLOOKUP(_xlfn.TEXTJOIN("_",TRUE,tbl_die_ordering[[#This Row],[Supplier]],tbl_die_ordering[[#This Row],[DIE NO]]),[1]Tracker!$AQ:$AQ,[1]Tracker!$W:$W,"") -> 7631-25 | C66: 007122-2504 | D66: B | E66: 280X160 | F66: 45670 | G66: =_xlfn.XLOOKUP(_xlfn.TEXTJOIN("_",TRUE,tbl_die_ordering[[#This Row],[Supplier]],tbl_die_ordering[[#This Row],[DIE NO]]),[1]Tracker!$AQ:$AQ,[1]Tracker!$V:$V,"") -> 45670 | H66: LAND | I66: 0 | J66: 0 | K66: 45670 | L66: 45672 | N66: =IFERROR(IF(tbl_die_ordering[[#This Row],[Design Approved Date]]<>"",L66-K66,""),"") -> 2 | O66: 45675 | P66: 45678 | Q66: 45675 | R66: 1300001103 | S66: PDTMC | T66: 45678 | W66: =_xlfn.LET( _xlpm.dieNo, tbl_die_ordering[[#This Row],[DIE NO]], _xlpm.orderNo, tbl_die_ordering[[#This Row],[Order No]], _xlpm.type, tbl_die_ordering[[#This Row],[TYPE]], _xlpm.designReceived, tbl_die_ordering[[#This Row],[Design Received Date]], _xlpm.designApproved, tbl_die_ordering[[#This Row],[Design Approved Date]], _xlpm.sim, tbl_die_ordering[[#This Row],[Sim]], _xlpm.prEntry, tbl_die_ordering[[#This Row],[PR Entry]], _xlpm.oracleEntry, tbl_die_ordering[[#This Row],[Oracle Entry]], _xlpm.ems, tbl_die_ordering[[#This Row],[Design saved to EMS FOLDER]], IF(_xlpm.dieNo = "", "", IF(_xlpm.orderNo = "", "PENDING FOR ORDERING", IF(_xlpm.type = "C", "CANCELLED", IF(_xlpm.type = "H", "HOLD", IF(_xlpm.designReceived = "", "AWAITING FOR DESIGN", IF(_xlpm.designApproved = "", IF(_xlpm.sim = "YES", "UNDER SIMULATION", "PENDING FOR DESIGN APPROVAL"), IF(_xlpm.prEntry = "", "PENDING FOR PR", IF(_xlpm.oracleEntry = "", "PENDING FOR ORACLE ENTRY", IF(_xlpm.ems = "", "PENDING FOR DESIGN TO EMS", "DONE"))))))))) ) -> DONE | X66: =IF(AND(tbl_die_ordering[[#This Row],[TYPE]]<>"C",tbl_die_ordering[[#This Row],[Design Approved Date]]<>""),tbl_die_ordering[[#This Row],[Design Approved Date]]-tbl_die_ordering[[#This Row],[Die Requested Date]],0) -> 2 | AB66: =_xlfn.XLOOKUP(_xlfn.TEXTJOIN("_",TRUE,tbl_die_ordering[[#This Row],[Supplier]],tbl_die_ordering[[#This Row],[DIE NO]]),[1]Tracker!$AQ:$AQ,[1]Tracker!$Y:$Y,"") -> M181 | AC66: =_xlfn.XLOOKUP(_xlfn.TEXTJOIN("_",TRUE,tbl_die_ordering[[#This Row],[Supplier]],tbl_die_ordering[[#This Row],[DIE NO]]),[1]Tracker!$AQ:$AQ,[1]Tracker!$AC:$AC,"") -> 45694 | AF66: =TEXT(tbl_die_ordering[[#This Row],[Die Requested Date]],"mmm") -> Jan | AG66: =_xlfn.TEXTJOIN("_",TRUE,tbl_die_ordering[[#This Row],[Supplier]],tbl_die_ordering[[#This Row],[DIE NO]]) -> PDTMC_007122-2504
A67: GEX 2 | B67: =_xlfn.XLOOKUP(_xlfn.TEXTJOIN("_",TRUE,tbl_die_ordering[[#This Row],[Supplier]],tbl_die_ordering[[#This Row],[DIE NO]]),[1]Tracker!$AQ:$AQ,[1]Tracker!$W:$W,"") -> 7624-25 | C67: 007208-2504 | D67: B | E67: 320X160 | F67: 45670 | G67: =_xlfn.XLOOKUP(_xlfn.TEXTJOIN("_",TRUE,tbl_die_ordering[[#This Row],[Supplier]],tbl_die_ordering[[#This Row],[DIE NO]]),[1]Tracker!$AQ:$AQ,[1]Tracker!$V:$V,"") -> 45670 | H67: LAND | I67: 0 | J67: 0 | K67: 45670 | L67: 45670 | N67: =IFERROR(IF(tbl_die_ordering[[#This Row],[Design Approved Date]]<>"",L67-K67,""),"") -> 0 | O67: 45682 | P67: 45672 | Q67: 45682 | R67: 1300001104 | S67: PDTMC | T67: 45672 | W67: =_xlfn.LET( _xlpm.dieNo, tbl_die_ordering[[#This Row],[DIE NO]], _xlpm.orderNo, tbl_die_ordering[[#This Row],[Order No]], _xlpm.type, tbl_die_ordering[[#This Row],[TYPE]], _xlpm.designReceived, tbl_die_ordering[[#This Row],[Design Received Date]], _xlpm.designApproved, tbl_die_ordering[[#This Row],[Design Approved Date]], _xlpm.sim, tbl_die_ordering[[#This Row],[Sim]], _xlpm.prEntry, tbl_die_ordering[[#This Row],[PR Entry]], _xlpm.oracleEntry, tbl_die_ordering[[#This Row],[Oracle Entry]], _xlpm.ems, tbl_die_ordering[[#This Row],[Design saved to EMS FOLDER]], IF(_xlpm.dieNo = "", "", IF(_xlpm.orderNo = "", "PENDING FOR ORDERING", IF(_xlpm.type = "C", "CANCELLED", IF(_xlpm.type = "H", "HOLD", IF(_xlpm.designReceived = "", "AWAITING FOR DESIGN", IF(_xlpm.designApproved = "", IF(_xlpm.sim = "YES", "UNDER SIMULATION", "PENDING FOR DESIGN APPROVAL"), IF(_xlpm.prEntry = "", "PENDING FOR PR", IF(_xlpm.oracleEntry = "", "PENDING FOR ORACLE ENTRY", IF(_xlpm.ems = "", "PENDING FOR DESIGN TO EMS", "DONE"))))))))) ) -> DONE | X67: =IF(AND(tbl_die_ordering[[#This Row],[TYPE]]<>"C",tbl_die_ordering[[#This Row],[Design Approved Date]]<>""),tbl_die_ordering[[#This Row],[Design Approved Date]]-tbl_die_ordering[[#This Row],[Die Requested Date]],0) -> 0 | AB67: =_xlfn.XLOOKUP(_xlfn.TEXTJOIN("_",TRUE,tbl_die_ordering[[#This Row],[Supplier]],tbl_die_ordering[[#This Row],[DIE NO]]),[1]Tracker!$AQ:$AQ,[1]Tracker!$Y:$Y,"") -> 242500219 | AC67: =_xlfn.XLOOKUP(_xlfn.TEXTJOIN("_",TRUE,tbl_die_ordering[[#This Row],[Supplier]],tbl_die_ordering[[#This Row],[DIE NO]]),[1]Tracker!$AQ:$AQ,[1]Tracker!$AC:$AC,"") -> 45742.334 | AF67: =TEXT(tbl_die_ordering[[#This Row],[Die Requested Date]],"mmm") -> Jan | AG67: =_xlfn.TEXTJOIN("_",TRUE,tbl_die_ordering[[#This Row],[Supplier]],tbl_die_ordering[[#This Row],[DIE NO]]) -> PDTMC_007208-2504
A68: GEX 2 | B68: =_xlfn.XLOOKUP(_xlfn.TEXTJOIN("_",TRUE,tbl_die_ordering[[#This Row],[Supplier]],tbl_die_ordering[[#This Row],[DIE NO]]),[1]Tracker!$AQ:$AQ,[1]Tracker!$W:$W,"") -> 7624-25 | C68: 007208-2505 | D68: B | E68: 320X160 | F68: 45670 | G68: =_xlfn.XLOOKUP(_xlfn.TEXTJOIN("_",TRUE,tbl_die_ordering[[#This Row],[Supplier]],tbl_die_ordering[[#This Row],[DIE NO]]),[1]Tracker!$AQ:$AQ,[1]Tracker!$V:$V,"") -> 45670 | H68: LAND | I68: 0 | J68: 0 | K68: 45670 | L68: 45684 | N68: =IFERROR(IF(tbl_die_ordering[[#This Row],[Design Approved Date]]<>"",L68-K68,""),"") -> 14 | O68: 45682 | P68: 45685 | Q68: 45682 | R68: 1300001104 | S68: PDTMC | T68: 45685 | W68: =_xlfn.LET( _xlpm.dieNo, tbl_die_ordering[[#This Row],[DIE NO]], _xlpm.orderNo, tbl_die_ordering[[#This Row],[Order No]], _xlpm.type, tbl_die_ordering[[#This Row],[TYPE]], _xlpm.designReceived, tbl_die_ordering[[#This Row],[Design Received Date]], _xlpm.designApproved, tbl_die_ordering[[#This Row],[Design Approved Date]], _xlpm.sim, tbl_die_ordering[[#This Row],[Sim]], _xlpm.prEntry, tbl_die_ordering[[#This Row],[PR Entry]], _xlpm.oracleEntry, tbl_die_ordering[[#This Row],[Oracle Entry]], _xlpm.ems, tbl_die_ordering[[#This Row],[Design saved to EMS FOLDER]], IF(_xlpm.dieNo = "", "", IF(_xlpm.orderNo = "", "PENDING FOR ORDERING", IF(_xlpm.type = "C", "CANCELLED", IF(_xlpm.type = "H", "HOLD", IF(_xlpm.designReceived = "", "AWAITING FOR DESIGN", IF(_xlpm.designApproved = "", IF(_xlpm.sim = "YES", "UNDER SIMULATION", "PENDING FOR DESIGN APPROVAL"), IF(_xlpm.prEntry = "", "PENDING FOR PR", IF(_xlpm.oracleEntry = "", "PENDING FOR ORACLE ENTRY", IF(_xlpm.ems = "", "PENDING FOR DESIGN TO EMS", "DONE"))))))))) ) -> DONE | X68: =IF(AND(tbl_die_ordering[[#This Row],[TYPE]]<>"C",tbl_die_ordering[[#This Row],[Design Approved Date]]<>""),tbl_die_ordering[[#This Row],[Design Approved Date]]-tbl_die_ordering[[#This Row],[Die Requested Date]],0) -> 14 | AB68: =_xlfn.XLOOKUP(_xlfn.TEXTJOIN("_",TRUE,tbl_die_ordering[[#This Row],[Supplier]],tbl_die_ordering[[#This Row],[DIE NO]]),[1]Tracker!$AQ:$AQ,[1]Tracker!$Y:$Y,"") -> 242500219 | AC68: =_xlfn.XLOOKUP(_xlfn.TEXTJOIN("_",TRUE,tbl_die_ordering[[#This Row],[Supplier]],tbl_die_ordering[[#This Row],[DIE NO]]),[1]Tracker!$AQ:$AQ,[1]Tracker!$AC:$AC,"") -> 45742.334 | AF68: =TEXT(tbl_die_ordering[[#This Row],[Die Requested Date]],"mmm") -> Jan | AG68: =_xlfn.TEXTJOIN("_",TRUE,tbl_die_ordering[[#This Row],[Supplier]],tbl_die_ordering[[#This Row],[DIE NO]]) -> PDTMC_007208-2505
A69: GEX 2 | B69: =_xlfn.XLOOKUP(_xlfn.TEXTJOIN("_",TRUE,tbl_die_ordering[[#This Row],[Supplier]],tbl_die_ordering[[#This Row],[DIE NO]]),[1]Tracker!$AQ:$AQ,[1]Tracker!$W:$W,"") -> 7624-25 | C69: 007108-2502 | D69: B | E69: 280x160 | F69: 45670 | G69: =_xlfn.XLOOKUP(_xlfn.TEXTJOIN("_",TRUE,tbl_die_ordering[[#This Row],[Supplier]],tbl_die_ordering[[#This Row],[DIE NO]]),[1]Tracker!$AQ:$AQ,[1]Tracker!$V:$V,"") -> 45670 | H69: LAND | I69: 0 | J69: 0 | K69: 45670 | L69: 45684 | N69: =IFERROR(IF(tbl_die_ordering[[#This Row],[Design Approved Date]]<>"",L69-K69,""),"") -> 14 | O69: 45682 | P69: 45685 | Q69: 45682 | R69: 1300001105 | S69: PDTMC | T69: 45685 | W69: =_xlfn.LET( _xlpm.dieNo, tbl_die_ordering[[#This Row],[DIE NO]], _xlpm.orderNo, tbl_die_ordering[[#This Row],[Order No]], _xlpm.type, tbl_die_ordering[[#This Row],[TYPE]], _xlpm.designReceived, tbl_die_ordering[[#This Row],[Design Received Date]], _xlpm.designApproved, tbl_die_ordering[[#This Row],[Design Approved Date]], _xlpm.sim, tbl_die_ordering[[#This Row],[Sim]], _xlpm.prEntry, tbl_die_ordering[[#This Row],[PR Entry]], _xlpm.oracleEntry, tbl_die_ordering[[#This Row],[Oracle Entry]], _xlpm.ems, tbl_die_ordering[[#This Row],[Design saved to EMS FOLDER]], IF(_xlpm.dieNo = "", "", IF(_xlpm.orderNo = "", "PENDING FOR ORDERING", IF(_xlpm.type = "C", "CANCELLED", IF(_xlpm.type = "H", "HOLD", IF(_xlpm.designReceived = "", "AWAITING FOR DESIGN", IF(_xlpm.designApproved = "", IF(_xlpm.sim = "YES", "UNDER SIMULATION", "PENDING FOR DESIGN APPROVAL"), IF(_xlpm.prEntry = "", "PENDING FOR PR", IF(_xlpm.oracleEntry = "", "PENDING FOR ORACLE ENTRY", IF(_xlpm.ems = "", "PENDING FOR DESIGN TO EMS", "DONE"))))))))) ) -> DONE | X69: =IF(AND(tbl_die_ordering[[#This Row],[TYPE]]<>"C",tbl_die_ordering[[#This Row],[Design Approved Date]]<>""),tbl_die_ordering[[#This Row],[Design Approved Date]]-tbl_die_ordering[[#This Row],[Die Requested Date]],0) -> 14 | AB69: =_xlfn.XLOOKUP(_xlfn.TEXTJOIN("_",TRUE,tbl_die_ordering[[#This Row],[Supplier]],tbl_die_ordering[[#This Row],[DIE NO]]),[1]Tracker!$AQ:$AQ,[1]Tracker!$Y:$Y,"") -> M240 | AC69: =_xlfn.XLOOKUP(_xlfn.TEXTJOIN("_",TRUE,tbl_die_ordering[[#This Row],[Supplier]],tbl_die_ordering[[#This Row],[DIE NO]]),[1]Tracker!$AQ:$AQ,[1]Tracker!$AC:$AC,"") -> 45701 | AF69: =TEXT(tbl_die_ordering[[#This Row],[Die Requested Date]],"mmm") -> Jan | AG69: =_xlfn.TEXTJOIN("_",TRUE,tbl_die_ordering[[#This Row],[Supplier]],tbl_die_ordering[[#This Row],[DIE NO]]) -> PDTMC_007108-2502
A70: GEX 2 | B70: =_xlfn.XLOOKUP(_xlfn.TEXTJOIN("_",TRUE,tbl_die_ordering[[#This Row],[Supplier]],tbl_die_ordering[[#This Row],[DIE NO]]),[1]Tracker!$AQ:$AQ,[1]Tracker!$W:$W,"") -> 7624-25 | C70: 051088-2523 | D70: B | E70: 280X165 | F70: 45670 | G70: =_xlfn.XLOOKUP(_xlfn.TEXTJOIN("_",TRUE,tbl_die_ordering[[#This Row],[Supplier]],tbl_die_ordering[[#This Row],[DIE NO]]),[1]Tracker!$AQ:$AQ,[1]Tracker!$V:$V,"") -> 45670 | H70: LAND | I70: 1 | J70: 2 | K70: 45670 | L70: 45679 | N70: =IFERROR(IF(tbl_die_ordering[[#This Row],[Design Approved Date]]<>"",L70-K70,""),"") -> 9 | O70: 45694 | P70: 45684 | Q70: 45694 | R70: 1300001113 | S70: PDTMC | T70: 45684 | W70: =_xlfn.LET( _xlpm.dieNo, tbl_die_ordering[[#This Row],[DIE NO]], _xlpm.orderNo, tbl_die_ordering[[#This Row],[Order No]], _xlpm.type, tbl_die_ordering[[#This Row],[TYPE]], _xlpm.designReceived, tbl_die_ordering[[#This Row],[Design Received Date]], _xlpm.designApproved, tbl_die_ordering[[#This Row],[Design Approved Date]], _xlpm.sim, tbl_die_ordering[[#This Row],[Sim]], _xlpm.prEntry, tbl_die_ordering[[#This Row],[PR Entry]], _xlpm.oracleEntry, tbl_die_ordering[[#This Row],[Oracle Entry]], _xlpm.ems, tbl_die_ordering[[#This Row],[Design saved to EMS FOLDER]], IF(_xlpm.dieNo = "", "", IF(_xlpm.orderNo = "", "PENDING FOR ORDERING", IF(_xlpm.type = "C", "CANCELLED", IF(_xlpm.type = "H", "HOLD", IF(_xlpm.designReceived = "", "AWAITING FOR DESIGN", IF(_xlpm.designApproved = "", IF(_xlpm.sim = "YES", "UNDER SIMULATION", "PENDING FOR DESIGN APPROVAL"), IF(_xlpm.prEntry = "", "PENDING FOR PR", IF(_xlpm.oracleEntry = "", "PENDING FOR ORACLE ENTRY", IF(_xlpm.ems = "", "PENDING FOR DESIGN TO EMS", "DONE"))))))))) ) -> DONE | X70: =IF(AND(tbl_die_ordering[[#This Row],[TYPE]]<>"C",tbl_die_ordering[[#This Row],[Design Approved Date]]<>""),tbl_die_ordering[[#This Row],[Design Approved Date]]-tbl_die_ordering[[#This Row],[Die Requested Date]],0) -> 9 | AB70: =_xlfn.XLOOKUP(_xlfn.TEXTJOIN("_",TRUE,tbl_die_ordering[[#This Row],[Supplier]],tbl_die_ordering[[#This Row],[DIE NO]]),[1]Tracker!$AQ:$AQ,[1]Tracker!$Y:$Y,"") -> M355 | AC70: =_xlfn.XLOOKUP(_xlfn.TEXTJOIN("_",TRUE,tbl_die_ordering[[#This Row],[Supplier]],tbl_die_ordering[[#This Row],[DIE NO]]),[1]Tracker!$AQ:$AQ,[1]Tracker!$AC:$AC,"") -> 45707 | AF70: =TEXT(tbl_die_ordering[[#This Row],[Die Requested Date]],"mmm") -> Jan | AG70: =_xlfn.TEXTJOIN("_",TRUE,tbl_die_ordering[[#This Row],[Supplier]],tbl_die_ordering[[#This Row],[DIE NO]]) -> PDTMC_051088-2523
A71: GEX 1 | B71: 7627-25 | C71: I-29663 | D71: T | E71: 460X150 | F71: 45670 | G71: =_xlfn.XLOOKUP(_xlfn.TEXTJOIN("_",TRUE,tbl_die_ordering[[#This Row],[Supplier]],tbl_die_ordering[[#This Row],[DIE NO]]),[1]Tracker!$AQ:$AQ,[1]Tracker!$V:$V,"") | H71: AIR | I71: 0 | J71: 0 | K71: 45679 | L71: 45699 | N71: =IFERROR(IF(tbl_die_ordering[[#This Row],[Design Approved Date]]<>"",L71-K71,""),"") -> 20 | O71: 45700 | P71: 45700 | Q71: 45700 | R71: 112500644 | S71: PHOENIX | T71: 45700 | V71: design received 17/01/2025 ask reivision and 3d model 20/01/2025 | W71: =_xlfn.LET( _xlpm.dieNo, tbl_die_ordering[[#This Row],[DIE NO]], _xlpm.orderNo, tbl_die_ordering[[#This Row],[Order No]], _xlpm.type, tbl_die_ordering[[#This Row],[TYPE]], _xlpm.designReceived, tbl_die_ordering[[#This Row],[Design Received Date]], _xlpm.designApproved, tbl_die_ordering[[#This Row],[Design Approved Date]], _xlpm.sim, tbl_die_ordering[[#This Row],[Sim]], _xlpm.prEntry, tbl_die_ordering[[#This Row],[PR Entry]], _xlpm.oracleEntry, tbl_die_ordering[[#This Row],[Oracle Entry]], _xlpm.ems, tbl_die_ordering[[#This Row],[Design saved to EMS FOLDER]], IF(_xlpm.dieNo = "", "", IF(_xlpm.orderNo = "", "PENDING FOR ORDERING", IF(_xlpm.type = "C", "CANCELLED", IF(_xlpm.type = "H", "HOLD", IF(_xlpm.designReceived = "", "AWAITING FOR DESIGN", IF(_xlpm.designApproved = "", IF(_xlpm.sim = "YES", "UNDER SIMULATION", "PENDING FOR DESIGN APPROVAL"), IF(_xlpm.prEntry = "", "PENDING FOR PR", IF(_xlpm.oracleEntry = "", "PENDING FOR ORACLE ENTRY", IF(_xlpm.ems = "", "PENDING FOR DESIGN TO EMS", "DONE"))))))))) ) -> DONE | X71: =IF(AND(tbl_die_ordering[[#This Row],[TYPE]]<>"C",tbl_die_ordering[[#This Row],[Design Approved Date]]<>""),tbl_die_ordering[[#This Row],[Design Approved Date]]-tbl_die_ordering[[#This Row],[Die Requested Date]],0) -> 29 | AB71: =_xlfn.XLOOKUP(_xlfn.TEXTJOIN("_",TRUE,tbl_die_ordering[[#This Row],[Supplier]],tbl_die_ordering[[#This Row],[DIE NO]]),[1]Tracker!$AQ:$AQ,[1]Tracker!$Y:$Y,"") | AC71: =_xlfn.XLOOKUP(_xlfn.TEXTJOIN("_",TRUE,tbl_die_ordering[[#This Row],[Supplier]],tbl_die_ordering[[#This Row],[DIE NO]]),[1]Tracker!$AQ:$AQ,[1]Tracker!$AC:$AC,"") | AF71: =TEXT(tbl_die_ordering[[#This Row],[Die Requested Date]],"mmm") -> Jan | AG71: =_xlfn.TEXTJOIN("_",TRUE,tbl_die_ordering[[#This Row],[Supplier]],tbl_die_ordering[[#This Row],[DIE NO]]) -> PHOENIX _I-29663
A72: GEX 2 | B72: =_xlfn.XLOOKUP(_xlfn.TEXTJOIN("_",TRUE,tbl_die_ordering[[#This Row],[Supplier]],tbl_die_ordering[[#This Row],[DIE NO]]),[1]Tracker!$AQ:$AQ,[1]Tracker!$W:$W,"") -> 7625-25 | C72: 005206-3506 | D72: B | E72: 280X160 | F72: 45670 | G72: =_xlfn.XLOOKUP(_xlfn.TEXTJOIN("_",TRUE,tbl_die_ordering[[#This Row],[Supplier]],tbl_die_ordering[[#This Row],[DIE NO]]),[1]Tracker!$AQ:$AQ,[1]Tracker!$V:$V,"") -> 45670 | H72: AIR | I72: 1 | J72: 1 | K72: 45672 | L72: 45677 | N72: =IFERROR(IF(tbl_die_ordering[[#This Row],[Design Approved Date]]<>"",L72-K72,""),"") -> 5 | O72: 45682 | P72: 45684 | Q72: 45682 | R72: 1300001104 | S72: PHOENIX | T72: 45684 | W72: =_xlfn.LET( _xlpm.dieNo, tbl_die_ordering[[#This Row],[DIE NO]], _xlpm.orderNo, tbl_die_ordering[[#This Row],[Order No]], _xlpm.type, tbl_die_ordering[[#This Row],[TYPE]], _xlpm.designReceived, tbl_die_ordering[[#This Row],[Design Received Date]], _xlpm.designApproved, tbl_die_ordering[[#This Row],[Design Approved Date]], _xlpm.sim, tbl_die_ordering[[#This Row],[Sim]], _xlpm.prEntry, tbl_die_ordering[[#This Row],[PR Entry]], _xlpm.oracleEntry, tbl_die_ordering[[#This Row],[Oracle Entry]], _xlpm.ems, tbl_die_ordering[[#This Row],[Design saved to EMS FOLDER]], IF(_xlpm.dieNo = "", "", IF(_xlpm.orderNo = "", "PENDING FOR ORDERING", IF(_xlpm.type = "C", "CANCELLED", IF(_xlpm.type = "H", "HOLD", IF(_xlpm.designReceived = "", "AWAITING FOR DESIGN", IF(_xlpm.designApproved = "", IF(_xlpm.sim = "YES", "UNDER SIMULATION", "PENDING FOR DESIGN APPROVAL"), IF(_xlpm.prEntry = "", "PENDING FOR PR", IF(_xlpm.oracleEntry = "", "PENDING FOR ORACLE ENTRY", IF(_xlpm.ems = "", "PENDING FOR DESIGN TO EMS", "DONE"))))))))) ) -> DONE | X72: =IF(AND(tbl_die_ordering[[#This Row],[TYPE]]<>"C",tbl_die_ordering[[#This Row],[Design Approved Date]]<>""),tbl_die_ordering[[#This Row],[Design Approved Date]]-tbl_die_ordering[[#This Row],[Die Requested Date]],0) -> 7 | AB72: =_xlfn.XLOOKUP(_xlfn.TEXTJOIN("_",TRUE,tbl_die_ordering[[#This Row],[Supplier]],tbl_die_ordering[[#This Row],[DIE NO]]),[1]Tracker!$AQ:$AQ,[1]Tracker!$Y:$Y,"") -> M258 | AC72: =_xlfn.XLOOKUP(_xlfn.TEXTJOIN("_",TRUE,tbl_die_ordering[[#This Row],[Supplier]],tbl_die_ordering[[#This Row],[DIE NO]]),[1]Tracker!$AQ:$AQ,[1]Tracker!$AC:$AC,"") -> 45695 | AF72: =TEXT(tbl_die_ordering[[#This Row],[Die Requested Date]],"mmm") -> Jan | AG72: =_xlfn.TEXTJOIN("_",TRUE,tbl_die_ordering[[#This Row],[Supplier]],tbl_die_ordering[[#This Row],[DIE NO]]) -> PHOENIX _005206-3506
A73: GEX 1 | B73: =_xlfn.XLOOKUP(_xlfn.TEXTJOIN("_",TRUE,tbl_die_ordering[[#This Row],[Supplier]],tbl_die_ordering[[#This Row],[DIE NO]]),[1]Tracker!$AQ:$AQ,[1]Tracker!$W:$W,"") -> 7635-25 | C73: 27796-201 | D73: N | E73: 355X200 | F73: 45671 | G73: =_xlfn.XLOOKUP(_xlfn.TEXTJOIN("_",TRUE,tbl_die_ordering[[#This Row],[Supplier]],tbl_die_ordering[[#This Row],[DIE NO]]),[1]Tracker!$AQ:$AQ,[1]Tracker!$V:$V,"") -> 45671 | H73: LAND | I73: 0 | J73: 0 | K73: 45671 | L73: 45673 | N73: =IFERROR(IF(tbl_die_ordering[[#This Row],[Design Approved Date]]<>"",L73-K73,""),"") -> 2 | O73: 45675 | P73: 45675 | Q73: 45675 | R73: 112500275 | S73: PHME | T73: 45675 | U73: VERTIV GULF LLC OPC | W73: =_xlfn.LET( _xlpm.dieNo, tbl_die_ordering[[#This Row],[DIE NO]], _xlpm.orderNo, tbl_die_ordering[[#This Row],[Order No]], _xlpm.type, tbl_die_ordering[[#This Row],[TYPE]], _xlpm.designReceived, tbl_die_ordering[[#This Row],[Design Received Date]], _xlpm.designApproved, tbl_die_ordering[[#This Row],[Design Approved Date]], _xlpm.sim, tbl_die_ordering[[#This Row],[Sim]], _xlpm.prEntry, tbl_die_ordering[[#This Row],[PR Entry]], _xlpm.oracleEntry, tbl_die_ordering[[#This Row],[Oracle Entry]], _xlpm.ems, tbl_die_ordering[[#This Row],[Design saved to EMS FOLDER]], IF(_xlpm.dieNo = "", "", IF(_xlpm.orderNo = "", "PENDING FOR ORDERING", IF(_xlpm.type = "C", "CANCELLED", IF(_xlpm.type = "H", "HOLD", IF(_xlpm.designReceived = "", "AWAITING FOR DESIGN", IF(_xlpm.designApproved = "", IF(_xlpm.sim = "YES", "UNDER SIMULATION", "PENDING FOR DESIGN APPROVAL"), IF(_xlpm.prEntry = "", "PENDING FOR PR", IF(_xlpm.oracleEntry = "", "PENDING FOR ORACLE ENTRY", IF(_xlpm.ems = "", "PENDING FOR DESIGN TO EMS", "DONE"))))))))) ) -> DONE | X73: =IF(AND(tbl_die_ordering[[#This Row],[TYPE]]<>"C",tbl_die_ordering[[#This Row],[Design Approved Date]]<>""),tbl_die_ordering[[#This Row],[Design Approved Date]]-tbl_die_ordering[[#This Row],[Die Requested Date]],0) -> 2 | AA73: MILL,, POWDER | AB73: =_xlfn.XLOOKUP(_xlfn.TEXTJOIN("_",TRUE,tbl_die_ordering[[#This Row],[Supplier]],tbl_die_ordering[[#This Row],[DIE NO]]),[1]Tracker!$AQ:$AQ,[1]Tracker!$Y:$Y,"") -> 142500610 | AC73: =_xlfn.XLOOKUP(_xlfn.TEXTJOIN("_",TRUE,tbl_die_ordering[[#This Row],[Supplier]],tbl_die_ordering[[#This Row],[DIE NO]]),[1]Tracker!$AQ:$AQ,[1]Tracker!$AC:$AC,"") -> 45681 | AF73: =TEXT(tbl_die_ordering[[#This Row],[Die Requested Date]],"mmm") -> Jan | AG73: =_xlfn.TEXTJOIN("_",TRUE,tbl_die_ordering[[#This Row],[Supplier]],tbl_die_ordering[[#This Row],[DIE NO]]) -> PHME_27796-201
A74: GEX 1 | B74: =_xlfn.XLOOKUP(_xlfn.TEXTJOIN("_",TRUE,tbl_die_ordering[[#This Row],[Supplier]],tbl_die_ordering[[#This Row],[DIE NO]]),[1]Tracker!$AQ:$AQ,[1]Tracker!$W:$W,"") -> 7634-25 | C74: 14622-205 | D74: B | E74: 320X200 | F74: 45671 | G74: =_xlfn.XLOOKUP(_xlfn.TEXTJOIN("_",TRUE,tbl_die_ordering[[#This Row],[Supplier]],tbl_die_ordering[[#This Row],[DIE NO]]),[1]Tracker!$AQ:$AQ,[1]Tracker!$V:$V,"") -> 45671 | H74: AIR | I74: 2 | J74: 2 | K74: 45672 | L74: 45675 | N74: =IFERROR(IF(tbl_die_ordering[[#This Row],[Design Approved Date]]<>"",L74-K74,""),"") -> 3 | O74: 45675 | P74: 45658 | Q74: 45675 | R74: 112500277 | S74: COMPES | T74: 45675 | V74: (7579-24)This Die order order was cancel from PHOENIX and send it to Compes as per Mr. Rogelio email ON 14.01.2025 | W74: =_xlfn.LET( _xlpm.dieNo, tbl_die_ordering[[#This Row],[DIE NO]], _xlpm.orderNo, tbl_die_ordering[[#This Row],[Order No]], _xlpm.type, tbl_die_ordering[[#This Row],[TYPE]], _xlpm.designReceived, tbl_die_ordering[[#This Row],[Design Received Date]], _xlpm.designApproved, tbl_die_ordering[[#This Row],[Design Approved Date]], _xlpm.sim, tbl_die_ordering[[#This Row],[Sim]], _xlpm.prEntry, tbl_die_ordering[[#This Row],[PR Entry]], _xlpm.oracleEntry, tbl_die_ordering[[#This Row],[Oracle Entry]], _xlpm.ems, tbl_die_ordering[[#This Row],[Design saved to EMS FOLDER]], IF(_xlpm.dieNo = "", "", IF(_xlpm.orderNo = "", "PENDING FOR ORDERING", IF(_xlpm.type = "C", "CANCELLED", IF(_xlpm.type = "H", "HOLD", IF(_xlpm.designReceived = "", "AWAITING FOR DESIGN", IF(_xlpm.designApproved = "", IF(_xlpm.sim = "YES", "UNDER SIMULATION", "PENDING FOR DESIGN APPROVAL"), IF(_xlpm.prEntry = "", "PENDING FOR PR", IF(_xlpm.oracleEntry = "", "PENDING FOR ORACLE ENTRY", IF(_xlpm.ems = "", "PENDING FOR DESIGN TO EMS", "DONE"))))))))) ) -> DONE | X74: =IF(AND(tbl_die_ordering[[#This Row],[TYPE]]<>"C",tbl_die_ordering[[#This Row],[Design Approved Date]]<>""),tbl_die_ordering[[#This Row],[Design Approved Date]]-tbl_die_ordering[[#This Row],[Die Requested Date]],0) -> 4 | AB74: =_xlfn.XLOOKUP(_xlfn.TEXTJOIN("_",TRUE,tbl_die_ordering[[#This Row],[Supplier]],tbl_die_ordering[[#This Row],[DIE NO]]),[1]Tracker!$AQ:$AQ,[1]Tracker!$Y:$Y,"") -> 142500927 | AC74: =_xlfn.XLOOKUP(_xlfn.TEXTJOIN("_",TRUE,tbl_die_ordering[[#This Row],[Supplier]],tbl_die_ordering[[#This Row],[DIE NO]]),[1]Tracker!$AQ:$AQ,[1]Tracker!$AC:$AC,"") -> 45693 | AF74: =TEXT(tbl_die_ordering[[#This Row],[Die Requested Date]],"mmm") -> Jan | AG74: =_xlfn.TEXTJOIN("_",TRUE,tbl_die_ordering[[#This Row],[Supplier]],tbl_die_ordering[[#This Row],[DIE NO]]) -> COMPES_14622-205
